Workbook
Name NativeTimeline_Order_Date: #N/A
Name Slicer_Category: #N/A
Name Slicer_Loyalty_Level: #N/A
Name Slicer_Payment_Type: #N/A
Name Slicer_Region: #N/A
Name Slicer_Store_Type: #N/A

Sheet Sales_Fact
A1: Sales_ID | B1: Order_Date | C1: Customer_ID | D1: Product_ID | E1: Store_ID | F1: Quantity | G1: Unit_Price | H1: Discount | I1: Payment_Type | J1: Total_Amount | K1: Quantity2 | L1: Unit_Price3 | M1: Discount4 | N1: Total_Amount5 | O1: Gross Amount | P1: Discounted Amount | Q1: Order Value Category
A2: SALE0 | B2: 45480 | C2: CUST1409 | D2: PROD97 | E2: STORE3 | F2: 1 | G2: 218.04 | H2: 0.09 | I2: Credit Card | J2: 198.4164 | K2: =IF(ISBLANK(Sales_Fact[[#This Row],[Quantity]]),MEDIAN(Sales_Fact[Quantity]),Sales_Fact[[#This Row],[Quantity]]) -> 1 | L2: =IF(ISBLANK(Sales_Fact[[#This Row],[Unit_Price]]),MEDIAN(Sales_Fact[Unit_Price]),Sales_Fact[[#This Row],[Unit_Price]]) -> 218.04 | M2: =IF(ISBLANK(Sales_Fact[[#This Row],[Discount]]),MEDIAN(Sales_Fact[Discount]),Sales_Fact[[#This Row],[Discount]]) -> 0.09 | N2: =Sales_Fact[[#This Row],[Quantity2]]*Sales_Fact[[#This Row],[Unit_Price3]]*(1-Sales_Fact[[#This Row],[Discount4]]) -> 198.4164 | O2: =Sales_Fact[[#This Row],[Quantity2]]*Sales_Fact[[#This Row],[Unit_Price3]] -> 218.04 | P2: =Sales_Fact[[#This Row],[Gross Amount]]*Sales_Fact[[#This Row],[Discount4]] -> 19.6236 | Q2: =IF(Sales_Fact[[#This Row],[Total_Amount5]]>1000,"High Value","Standard") -> Standard
A3: SALE1 | B3: 45285 | C3: CUST1467 | D3: PROD74 | E3: STORE17 | F3: 3 | G3: 104.47 | H3: 0.27 | I3: PayPal | J3: 228.7893 | K3: =IF(ISBLANK(Sales_Fact[[#This Row],[Quantity]]),MEDIAN(Sales_Fact[Quantity]),Sales_Fact[[#This Row],[Quantity]]) -> 3 | L3: =IF(ISBLANK(Sales_Fact[[#This Row],[Unit_Price]]),MEDIAN(Sales_Fact[Unit_Price]),Sales_Fact[[#This Row],[Unit_Price]]) -> 104.47 | M3: =IF(ISBLANK(Sales_Fact[[#This Row],[Discount]]),MEDIAN(Sales_Fact[Discount]),Sales_Fact[[#This Row],[Discount]]) -> 0.27 | N3: =Sales_Fact[[#This Row],[Quantity2]]*Sales_Fact[[#This Row],[Unit_Price3]]*(1-Sales_Fact[[#This Row],[Discount4]]) -> 228.7893 | O3: =Sales_Fact[[#This Row],[Quantity2]]*Sales_Fact[[#This Row],[Unit_Price3]] -> 313.41 | P3: =Sales_Fact[[#This Row],[Gross Amount]]*Sales_Fact[[#This Row],[Discount4]] -> 84.6207 | Q3: =IF(Sales_Fact[[#This Row],[Total_Amount5]]>1000,"High Value","Standard") -> Standard
A4: SALE2 | B4: 45446 | C4: CUST1056 | D4: PROD49 | E4: STORE8 | F4: 4 | G4: 914.05 | H4: 0.25 | I4: Credit Card | J4: 2742.15 | K4: =IF(ISBLANK(Sales_Fact[[#This Row],[Quantity]]),MEDIAN(Sales_Fact[Quantity]),Sales_Fact[[#This Row],[Quantity]]) -> 4 | L4: =IF(ISBLANK(Sales_Fact[[#This Row],[Unit_Price]]),MEDIAN(Sales_Fact[Unit_Price]),Sales_Fact[[#This Row],[Unit_Price]]) -> 914.05 | M4: =IF(ISBLANK(Sales_Fact[[#This Row],[Discount]]),MEDIAN(Sales_Fact[Discount]),Sales_Fact[[#This Row],[Discount]]) -> 0.25 | N4: =Sales_Fact[[#This Row],[Quantity2]]*Sales_Fact[[#This Row],[Unit_Price3]]*(1-Sales_Fact[[#This Row],[Discount4]]) -> 2742.15 | O4: =Sales_Fact[[#This Row],[Quantity2]]*Sales_Fact[[#This Row],[Unit_Price3]] -> 3656.2 | P4: =Sales_Fact[[#This Row],[Gross Amount]]*Sales_Fact[[#This Row],[Discount4]] -> 914.05 | Q4: =IF(Sales_Fact[[#This Row],[Total_Amount5]]>1000,"High Value","Standard") -> High Value
A5: SALE3 | B5: 45259 | C5: CUST1346 | D5: PROD76 | E5: STORE8 | F5: 1 | G5: 921.51 | H5: 0.16 | I5: COD | J5: 774.0684 | K5: =IF(ISBLANK(Sales_Fact[[#This Row],[Quantity]]),MEDIAN(Sales_Fact[Quantity]),Sales_Fact[[#This Row],[Quantity]]) -> 1 | L5: =IF(ISBLANK(Sales_Fact[[#This Row],[Unit_Price]]),MEDIAN(Sales_Fact[Unit_Price]),Sales_Fact[[#This Row],[Unit_Price]]) -> 921.51 | M5: =IF(ISBLANK(Sales_Fact[[#This Row],[Discount]]),MEDIAN(Sales_Fact[Discount]),Sales_Fact[[#This Row],[Discount]]) -> 0.16 | N5: =Sales_Fact[[#This Row],[Quantity2]]*Sales_Fact[[#This Row],[Unit_Price3]]*(1-Sales_Fact[[#This Row],[Discount4]]) -> 774.0684 | O5: =Sales_Fact[[#This Row],[Quantity2]]*Sales_Fact[[#This Row],[Unit_Price3]] -> 921.51 | P5: =Sales_Fact[[#This Row],[Gross Amount]]*Sales_Fact[[#This Row],[Discount4]] -> 147.4416 | Q5: =IF(Sales_Fact[[#This Row],[Total_Amount5]]>1000,"High Value","Standard") -> Standard
A6: SALE4 | B6: 45297 | C6: CUST1493 | D6: PROD59 | E6: STORE5 | F6: 3 | G6: 745.3 | H6: 0.18 | I6: Credit Card | J6: 1833.438 | K6: =IF(ISBLANK(Sales_Fact[[#This Row],[Quantity]]),MEDIAN(Sales_Fact[Quantity]),Sales_Fact[[#This Row],[Quantity]]) -> 3 | L6: =IF(ISBLANK(Sales_Fact[[#This Row],[Unit_Price]]),MEDIAN(Sales_Fact[Unit_Price]),Sales_Fact[[#This Row],[Unit_Price]]) -> 745.3 | M6: =IF(ISBLANK(Sales_Fact[[#This Row],[Discount]]),MEDIAN(Sales_Fact[Discount]),Sales_Fact[[#This Row],[Discount]]) -> 0.18 | N6: =Sales_Fact[[#This Row],[Quantity2]]*Sales_Fact[[#This Row],[Unit_Price3]]*(1-Sales_Fact[[#This Row],[Discount4]]) -> 1833.438 | O6: =Sales_Fact[[#This Row],[Quantity2]]*Sales_Fact[[#This Row],[Unit_Price3]] -> 2235.9 | P6: =Sales_Fact[[#This Row],[Gross Amount]]*Sales_Fact[[#This Row],[Discount4]] -> 402.462 | Q6: =IF(Sales_Fact[[#This Row],[Total_Amount5]]>1000,"High Value","Standard") -> High Value
A7: SALE5 | B7: 45499 | C7: CUST1116 | D7: PROD15 | E7: STORE7 | F7: 3 | G7: 147.01 | H7: 0.19 | I7: COD | J7: 357.2343 | K7: =IF(ISBLANK(Sales_Fact[[#This Row],[Quantity]]),MEDIAN(Sales_Fact[Quantity]),Sales_Fact[[#This Row],[Quantity]]) -> 3 | L7: =IF(ISBLANK(Sales_Fact[[#This Row],[Unit_Price]]),MEDIAN(Sales_Fact[Unit_Price]),Sales_Fact[[#This Row],[Unit_Price]]) -> 147.01 | M7: =IF(ISBLANK(Sales_Fact[[#This Row],[Discount]]),MEDIAN(Sales_Fact[Discount]),Sales_Fact[[#This Row],[Discount]]) -> 0.19 | N7: =Sales_Fact[[#This Row],[Quantity2]]*Sales_Fact[[#This Row],[Unit_Price3]]*(1-Sales_Fact[[#This Row],[Discount4]]) -> 357.2343 | O7: =Sales_Fact[[#This Row],[Quantity2]]*Sales_Fact[[#This Row],[Unit_Price3]] -> 441.03 | P7: =Sales_Fact[[#This Row],[Gross Amount]]*Sales_Fact[[#This Row],[Discount4]] -> 83.7957 | Q7: =IF(Sales_Fact[[#This Row],[Total_Amount5]]>1000,"High Value","Standard") -> Standard
A8: SALE6 | B8: 45850 | C8: CUST1016 | D8: PROD56 | E8: STORE4 | F8: 2 | G8: 785.31 | H8: 0.15 | I8: PayPal | J8: 1335.027 | K8: =IF(ISBLANK(Sales_Fact[[#This Row],[Quantity]]),MEDIAN(Sales_Fact[Quantity]),Sales_Fact[[#This Row],[Quantity]]) -> 2 | L8: =IF(ISBLANK(Sales_Fact[[#This Row],[Unit_Price]]),MEDIAN(Sales_Fact[Unit_Price]),Sales_Fact[[#This Row],[Unit_Price]]) -> 785.31 | M8: =IF(ISBLANK(Sales_Fact[[#This Row],[Discount]]),MEDIAN(Sales_Fact[Discount]),Sales_Fact[[#This Row],[Discount]]) -> 0.15 | N8: =Sales_Fact[[#This Row],[Quantity2]]*Sales_Fact[[#This Row],[Unit_Price3]]*(1-Sales_Fact[[#This Row],[Discount4]]) -> 1335.027 | O8: =Sales_Fact[[#This Row],[Quantity2]]*Sales_Fact[[#This Row],[Unit_Price3]] -> 1570.62 | P8: =Sales_Fact[[#This Row],[Gross Amount]]*Sales_Fact[[#This Row],[Discount4]] -> 235.593 | Q8: =IF(Sales_Fact[[#This Row],[Total_Amount5]]>1000,"High Value","Standard") -> High Value
A9: SALE7 | B9: 45248 | C9: CUST1152 | D9: PROD70 | E9: STORE8 | F9: 4 | G9: 342.39 | H9: 0.23 | I9: PayPal | J9: 1054.5612 | K9: =IF(ISBLANK(Sales_Fact[[#This Row],[Quantity]]),MEDIAN(Sales_Fact[Quantity]),Sales_Fact[[#This Row],[Quantity]]) -> 4 | L9: =IF(ISBLANK(Sales_Fact[[#This Row],[Unit_Price]]),MEDIAN(Sales_Fact[Unit_Price]),Sales_Fact[[#This Row],[Unit_Price]]) -> 342.39 | M9: =IF(ISBLANK(Sales_Fact[[#This Row],[Discount]]),MEDIAN(Sales_Fact[Discount]),Sales_Fact[[#This Row],[Discount]]) -> 0.23 | N9: =Sales_Fact[[#This Row],[Quantity2]]*Sales_Fact[[#This Row],[Unit_Price3]]*(1-Sales_Fact[[#This Row],[Discount4]]) -> 1054.5612 | O9: =Sales_Fact[[#This Row],[Quantity2]]*Sales_Fact[[#This Row],[Unit_Price3]] -> 1369.56 | P9: =Sales_Fact[[#This Row],[Gross Amount]]*Sales_Fact[[#This Row],[Discount4]] -> 314.9988 | Q9: =IF(Sales_Fact[[#This Row],[Total_Amount5]]>1000,"High Value","Standard") -> High Value
A10: SALE8 | B10: 45781 | C10: CUST1187 | D10: PROD99 | E10: STORE5 | G10: 448.25 | H10: 0.07 | I10: PayPal | J10: 1250.6175 | K10: =IF(ISBLANK(Sales_Fact[[#This Row],[Quantity]]),MEDIAN(Sales_Fact[Quantity]),Sales_Fact[[#This Row],[Quantity]]) -> 2 | L10: =IF(ISBLANK(Sales_Fact[[#This Row],[Unit_Price]]),MEDIAN(Sales_Fact[Unit_Price]),Sales_Fact[[#This Row],[Unit_Price]]) -> 448.25 | M10: =IF(ISBLANK(Sales_Fact[[#This Row],[Discount]]),MEDIAN(Sales_Fact[Discount]),Sales_Fact[[#This Row],[Discount]]) -> 0.07 | N10: =Sales_Fact[[#This Row],[Quantity2]]*Sales_Fact[[#This Row],[Unit_Price3]]*(1-Sales_Fact[[#This Row],[Discount4]]) -> 833.745 | O10: =Sales_Fact[[#This Row],[Quantity2]]*Sales_Fact[[#This Row],[Unit_Price3]] -> 896.5 | P10: =Sales_Fact[[#This Row],[Gross Amount]]*Sales_Fact[[#This Row],[Discount4]] -> 62.755 | Q10: =IF(Sales_Fact[[#This Row],[Total_Amount5]]>1000,"High Value","Standard") -> Standard
A11: SALE9 | B11: 45869 | C11: CUST1464 | D11: PROD33 | E11: STORE0 | F11: 2 | G11: 873.17 | H11: 0.23 | I11: PayPal | J11: 1344.6818 | K11: =IF(ISBLANK(Sales_Fact[[#This Row],[Quantity]]),MEDIAN(Sales_Fact[Quantity]),Sales_Fact[[#This Row],[Quantity]]) -> 2 | L11: =IF(ISBLANK(Sales_Fact[[#This Row],[Unit_Price]]),MEDIAN(Sales_Fact[Unit_Price]),Sales_Fact[[#This Row],[Unit_Price]]) -> 873.17 | M11: =IF(ISBLANK(Sales_Fact[[#This Row],[Discount]]),MEDIAN(Sales_Fact[Discount]),Sales_Fact[[#This Row],[Discount]]) -> 0.23 | N11: =Sales_Fact[[#This Row],[Quantity2]]*Sales_Fact[[#This Row],[Unit_Price3]]*(1-Sales_Fact[[#This Row],[Discount4]]) -> 1344.6818 | O11: =Sales_Fact[[#This Row],[Quantity2]]*Sales_Fact[[#This Row],[Unit_Price3]] -> 1746.34 | P11: =Sales_Fact[[#This Row],[Gross Amount]]*Sales_Fact[[#This Row],[Discount4]] -> 401.6582 | Q11: =IF(Sales_Fact[[#This Row],[Total_Amount5]]>1000,"High Value","Standard") -> High Value
A12: SALE10 | B12: 45335 | C12: CUST1065 | D12: PROD24 | E12: STORE14 | F12: 1 | G12: 278.63 | H12: 0.07 | I12: Credit Card | J12: 259.1259 | K12: =IF(ISBLANK(Sales_Fact[[#This Row],[Quantity]]),MEDIAN(Sales_Fact[Quantity]),Sales_Fact[[#This Row],[Quantity]]) -> 1 | L12: =IF(ISBLANK(Sales_Fact[[#This Row],[Unit_Price]]),MEDIAN(Sales_Fact[Unit_Price]),Sales_Fact[[#This Row],[Unit_Price]]) -> 278.63 | M12: =IF(ISBLANK(Sales_Fact[[#This Row],[Discount]]),MEDIAN(Sales_Fact[Discount]),Sales_Fact[[#This Row],[Discount]]) -> 0.07 | N12: =Sales_Fact[[#This Row],[Quantity2]]*Sales_Fact[[#This Row],[Unit_Price3]]*(1-Sales_Fact[[#This Row],[Discount4]]) -> 259.1259 | O12: =Sales_Fact[[#This Row],[Quantity2]]*Sales_Fact[[#This Row],[Unit_Price3]] -> 278.63 | P12: =Sales_Fact[[#This Row],[Gross Amount]]*Sales_Fact[[#This Row],[Discount4]] -> 19.5041 | Q12: =IF(Sales_Fact[[#This Row],[Total_Amount5]]>1000,"High Value","Standard") -> Standard
A13: SALE11 | B13: 45801 | C13: CUST1320 | D13: PROD39 | E13: STORE1 | F13: 4 | G13: 286.92 | H13: 0.17 | I13: Credit Card | J13: 952.5744 | K13: =IF(ISBLANK(Sales_Fact[[#This Row],[Quantity]]),MEDIAN(Sales_Fact[Quantity]),Sales_Fact[[#This Row],[Quantity]]) -> 4 | L13: =IF(ISBLANK(Sales_Fact[[#This Row],[Unit_Price]]),MEDIAN(Sales_Fact[Unit_Price]),Sales_Fact[[#This Row],[Unit_Price]]) -> 286.92 | M13: =IF(ISBLANK(Sales_Fact[[#This Row],[Discount]]),MEDIAN(Sales_Fact[Discount]),Sales_Fact[[#This Row],[Discount]]) -> 0.17 | N13: =Sales_Fact[[#This Row],[Quantity2]]*Sales_Fact[[#This Row],[Unit_Price3]]*(1-Sales_Fact[[#This Row],[Discount4]]) -> 952.5744 | O13: =Sales_Fact[[#This Row],[Quantity2]]*Sales_Fact[[#This Row],[Unit_Price3]] -> 1147.68 | P13: =Sales_Fact[[#This Row],[Gross Amount]]*Sales_Fact[[#This Row],[Discount4]] -> 195.1056 | Q13: =IF(Sales_Fact[[#This Row],[Total_Amount5]]>1000,"High Value","Standard") -> Standard
A14: SALE12 | B14: 45528 | C14: CUST1237 | D14: PROD88 | E14: STORE4 | F14: 4 | G14: 644.58 | H14: 0.01 | I14: Credit Card | J14: 2552.5368 | K14: =IF(ISBLANK(Sales_Fact[[#This Row],[Quantity]]),MEDIAN(Sales_Fact[Quantity]),Sales_Fact[[#This Row],[Quantity]]) -> 4 | L14: =IF(ISBLANK(Sales_Fact[[#This Row],[Unit_Price]]),MEDIAN(Sales_Fact[Unit_Price]),Sales_Fact[[#This Row],[Unit_Price]]) -> 644.58 | M14: =IF(ISBLANK(Sales_Fact[[#This Row],[Discount]]),MEDIAN(Sales_Fact[Discount]),Sales_Fact[[#This Row],[Discount]]) -> 0.01 | N14: =Sales_Fact[[#This Row],[Quantity2]]*Sales_Fact[[#This Row],[Unit_Price3]]*(1-Sales_Fact[[#This Row],[Discount4]]) -> 2552.5368 | O14: =Sales_Fact[[#This Row],[Quantity2]]*Sales_Fact[[#This Row],[Unit_Price3]] -> 2578.32 | P14: =Sales_Fact[[#This Row],[Gross Amount]]*Sales_Fact[[#This Row],[Discount4]] -> 25.7832 | Q14: =IF(Sales_Fact[[#This Row],[Total_Amount5]]>1000,"High Value","Standard") -> High Value
A15: SALE13 | B15: 45875 | C15: CUST1443 | D15: PROD34 | E15: STORE16 | F15: 2 | G15: 316.9 | H15: 0.3 | I15: PayPal | J15: 443.66 | K15: =IF(ISBLANK(Sales_Fact[[#This Row],[Quantity]]),MEDIAN(Sales_Fact[Quantity]),Sales_Fact[[#This Row],[Quantity]]) -> 2 | L15: =IF(ISBLANK(Sales_Fact[[#This Row],[Unit_Price]]),MEDIAN(Sales_Fact[Unit_Price]),Sales_Fact[[#This Row],[Unit_Price]]) -> 316.9 | M15: =IF(ISBLANK(Sales_Fact[[#This Row],[Discount]]),MEDIAN(Sales_Fact[Discount]),Sales_Fact[[#This Row],[Discount]]) -> 0.3 | N15: =Sales_Fact[[#This Row],[Quantity2]]*Sales_Fact[[#This Row],[Unit_Price3]]*(1-Sales_Fact[[#This Row],[Discount4]]) -> 443.66 | O15: =Sales_Fact[[#This Row],[Quantity2]]*Sales_Fact[[#This Row],[Unit_Price3]] -> 633.8 | P15: =Sales_Fact[[#This Row],[Gross Amount]]*Sales_Fact[[#This Row],[Discount4]] -> 190.14 | Q15: =IF(Sales_Fact[[#This Row],[Total_Amount5]]>1000,"High Value","Standard") -> Standard
A16: SALE14 | B16: 45829 | C16: CUST1348 | D16: PROD24 | E16: STORE15 | F16: 4 | G16: 403.47 | H16: 0.29 | I16: PayPal | J16: 1145.8548 | K16: =IF(ISBLANK(Sales_Fact[[#This Row],[Quantity]]),MEDIAN(Sales_Fact[Quantity]),Sales_Fact[[#This Row],[Quantity]]) -> 4 | L16: =IF(ISBLANK(Sales_Fact[[#This Row],[Unit_Price]]),MEDIAN(Sales_Fact[Unit_Price]),Sales_Fact[[#This Row],[Unit_Price]]) -> 403.47 | M16: =IF(ISBLANK(Sales_Fact[[#This Row],[Discount]]),MEDIAN(Sales_Fact[Discount]),Sales_Fact[[#This Row],[Discount]]) -> 0.29 | N16: =Sales_Fact[[#This Row],[Quantity2]]*Sales_Fact[[#This Row],[Unit_Price3]]*(1-Sales_Fact[[#This Row],[Discount4]]) -> 1145.8548 | O16: =Sales_Fact[[#This Row],[Quantity2]]*Sales_Fact[[#This Row],[Unit_Price3]] -> 1613.88 | P16: =Sales_Fact[[#This Row],[Gross Amount]]*Sales_Fact[[#This Row],[Discount4]] -> 468.0252 | Q16: =IF(Sales_Fact[[#This Row],[Total_Amount5]]>1000,"High Value","Standard") -> High Value
A17: SALE15 | B17: 45636 | C17: CUST1435 | D17: PROD36 | E17: STORE9 | G17: 871.34 | H17: 0.04 | I17: COD | J17: 2509.4592 | K17: =IF(ISBLANK(Sales_Fact[[#This Row],[Quantity]]),MEDIAN(Sales_Fact[Quantity]),Sales_Fact[[#This Row],[Quantity]]) -> 2 | L17: =IF(ISBLANK(Sales_Fact[[#This Row],[Unit_Price]]),MEDIAN(Sales_Fact[Unit_Price]),Sales_Fact[[#This Row],[Unit_Price]]) -> 871.34 | M17: =IF(ISBLANK(Sales_Fact[[#This Row],[Discount]]),MEDIAN(Sales_Fact[Discount]),Sales_Fact[[#This Row],[Discount]]) -> 0.04 | N17: =Sales_Fact[[#This Row],[Quantity2]]*Sales_Fact[[#This Row],[Unit_Price3]]*(1-Sales_Fact[[#This Row],[Discount4]]) -> 1672.9728 | O17: =Sales_Fact[[#This Row],[Quantity2]]*Sales_Fact[[#This Row],[Unit_Price3]] -> 1742.68 | P17: =Sales_Fact[[#This Row],[Gross Amount]]*Sales_Fact[[#This Row],[Discount4]] -> 69.7072 | Q17: =IF(Sales_Fact[[#This Row],[Total_Amount5]]>1000,"High Value","Standard") -> High Value
A18: SALE16 | B18: 45913 | C18: CUST1276 | D18: PROD65 | E18: STORE19 | F18: 2 | G18: 451.98 | H18: 0.25 | I18: Credit Card | J18: 677.97 | K18: =IF(ISBLANK(Sales_Fact[[#This Row],[Quantity]]),MEDIAN(Sales_Fact[Quantity]),Sales_Fact[[#This Row],[Quantity]]) -> 2 | L18: =IF(ISBLANK(Sales_Fact[[#This Row],[Unit_Price]]),MEDIAN(Sales_Fact[Unit_Price]),Sales_Fact[[#This Row],[Unit_Price]]) -> 451.98 | M18: =IF(ISBLANK(Sales_Fact[[#This Row],[Discount]]),MEDIAN(Sales_Fact[Discount]),Sales_Fact[[#This Row],[Discount]]) -> 0.25 | N18: =Sales_Fact[[#This Row],[Quantity2]]*Sales_Fact[[#This Row],[Unit_Price3]]*(1-Sales_Fact[[#This Row],[Discount4]]) -> 677.97 | O18: =Sales_Fact[[#This Row],[Quantity2]]*Sales_Fact[[#This Row],[Unit_Price3]] -> 903.96 | P18: =Sales_Fact[[#This Row],[Gross Amount]]*Sales_Fact[[#This Row],[Discount4]] -> 225.99 | Q18: =IF(Sales_Fact[[#This Row],[Total_Amount5]]>1000,"High Value","Standard") -> Standard
A19: SALE17 | B19: 45637 | C19: CUST1079 | D19: PROD27 | E19: STORE4 | F19: 2 | G19: 502.69 | H19: 0.23 | I19: Credit Card | J19: 774.1426 | K19: =IF(ISBLANK(Sales_Fact[[#This Row],[Quantity]]),MEDIAN(Sales_Fact[Quantity]),Sales_Fact[[#This Row],[Quantity]]) -> 2 | L19: =IF(ISBLANK(Sales_Fact[[#This Row],[Unit_Price]]),MEDIAN(Sales_Fact[Unit_Price]),Sales_Fact[[#This Row],[Unit_Price]]) -> 502.69 | M19: =IF(ISBLANK(Sales_Fact[[#This Row],[Discount]]),MEDIAN(Sales_Fact[Discount]),Sales_Fact[[#This Row],[Discount]]) -> 0.23 | N19: =Sales_Fact[[#This Row],[Quantity2]]*Sales_Fact[[#This Row],[Unit_Price3]]*(1-Sales_Fact[[#This Row],[Discount4]]) -> 774.1426 | O19: =Sales_Fact[[#This Row],[Quantity2]]*Sales_Fact[[#This Row],[Unit_Price3]] -> 1005.38 | P19: =Sales_Fact[[#This Row],[Gross Amount]]*Sales_Fact[[#This Row],[Discount4]] -> 231.2374 | Q19: =IF(Sales_Fact[[#This Row],[Total_Amount5]]>1000,"High Value","Standard") -> Standard
A20: SALE18 | B20: 45517 | C20: CUST1094 | D20: PROD39 | E20: STORE4 | F20: 2 | G20: 559.23 | H20: 0.25 | I20: COD | J20: 838.845 | K20: =IF(ISBLANK(Sales_Fact[[#This Row],[Quantity]]),MEDIAN(Sales_Fact[Quantity]),Sales_Fact[[#This Row],[Quantity]]) -> 2 | L20: =IF(ISBLANK(Sales_Fact[[#This Row],[Unit_Price]]),MEDIAN(Sales_Fact[Unit_Price]),Sales_Fact[[#This Row],[Unit_Price]]) -> 559.23 | M20: =IF(ISBLANK(Sales_Fact[[#This Row],[Discount]]),MEDIAN(Sales_Fact[Discount]),Sales_Fact[[#This Row],[Discount]]) -> 0.25 | N20: =Sales_Fact[[#This Row],[Quantity2]]*Sales_Fact[[#This Row],[Unit_Price3]]*(1-Sales_Fact[[#This Row],[Discount4]]) -> 838.845 | O20: =Sales_Fact[[#This Row],[Quantity2]]*Sales_Fact[[#This Row],[Unit_Price3]] -> 1118.46 | P20: =Sales_Fact[[#This Row],[Gross Amount]]*Sales_Fact[[#This Row],[Discount4]] -> 279.615 | Q20: =IF(Sales_Fact[[#This Row],[Total_Amount5]]>1000,"High Value","Standard") -> Standard
A21: SALE19 | B21: 45369 | C21: CUST1239 | D21: PROD60 | E21: STORE13 | F21: 4 | H21: 0.04 | I21: COD | J21: 1782.4512 | K21: =IF(ISBLANK(Sales_Fact[[#This Row],[Quantity]]),MEDIAN(Sales_Fact[Quantity]),Sales_Fact[[#This Row],[Quantity]]) -> 4 | L21: =IF(ISBLANK(Sales_Fact[[#This Row],[Unit_Price]]),MEDIAN(Sales_Fact[Unit_Price]),Sales_Fact[[#This Row],[Unit_Price]]) -> 522.72 | M21: =IF(ISBLANK(Sales_Fact[[#This Row],[Discount]]),MEDIAN(Sales_Fact[Discount]),Sales_Fact[[#This Row],[Discount]]) -> 0.04 | N21: =Sales_Fact[[#This Row],[Quantity2]]*Sales_Fact[[#This Row],[Unit_Price3]]*(1-Sales_Fact[[#This Row],[Discount4]]) -> 2007.2448 | O21: =Sales_Fact[[#This Row],[Quantity2]]*Sales_Fact[[#This Row],[Unit_Price3]] -> 2090.88 | P21: =Sales_Fact[[#This Row],[Gross Amount]]*Sales_Fact[[#This Row],[Discount4]] -> 83.6352 | Q21: =IF(Sales_Fact[[#This Row],[Total_Amount5]]>1000,"High Value","Standard") -> High Value
A22: SALE20 | B22: 45843 | C22: CUST1144 | D22: PROD72 | E22: STORE17 | F22: 3 | G22: 986.04 | H22: 0.27 | I22: COD | J22: 2159.4276 | K22: =IF(ISBLANK(Sales_Fact[[#This Row],[Quantity]]),MEDIAN(Sales_Fact[Quantity]),Sales_Fact[[#This Row],[Quantity]]) -> 3 | L22: =IF(ISBLANK(Sales_Fact[[#This Row],[Unit_Price]]),MEDIAN(Sales_Fact[Unit_Price]),Sales_Fact[[#This Row],[Unit_Price]]) -> 986.04 | M22: =IF(ISBLANK(Sales_Fact[[#This Row],[Discount]]),MEDIAN(Sales_Fact[Discount]),Sales_Fact[[#This Row],[Discount]]) -> 0.27 | N22: =Sales_Fact[[#This Row],[Quantity2]]*Sales_Fact[[#This Row],[Unit_Price3]]*(1-Sales_Fact[[#This Row],[Discount4]]) -> 2159.4276 | O22: =Sales_Fact[[#This Row],[Quantity2]]*Sales_Fact[[#This Row],[Unit_Price3]] -> 2958.12 | P22: =Sales_Fact[[#This Row],[Gross Amount]]*Sales_Fact[[#This Row],[Discount4]] -> 798.6924 | Q22: =IF(Sales_Fact[[#This Row],[Total_Amount5]]>1000,"High Value","Standard") -> High Value
A23: SALE21 | B23: 45447 | C23: CUST1396 | D23: PROD43 | E23: STORE18 | F23: 1 | G23: 589.56 | H23: 0.22 | I23: Credit Card | J23: 459.8568 | K23: =IF(ISBLANK(Sales_Fact[[#This Row],[Quantity]]),MEDIAN(Sales_Fact[Quantity]),Sales_Fact[[#This Row],[Quantity]]) -> 1 | L23: =IF(ISBLANK(Sales_Fact[[#This Row],[Unit_Price]]),MEDIAN(Sales_Fact[Unit_Price]),Sales_Fact[[#This Row],[Unit_Price]]) -> 589.56 | M23: =IF(ISBLANK(Sales_Fact[[#This Row],[Discount]]),MEDIAN(Sales_Fact[Discount]),Sales_Fact[[#This Row],[Discount]]) -> 0.22 | N23: =Sales_Fact[[#This Row],[Quantity2]]*Sales_Fact[[#This Row],[Unit_Price3]]*(1-Sales_Fact[[#This Row],[Discount4]]) -> 459.8568 | O23: =Sales_Fact[[#This Row],[Quantity2]]*Sales_Fact[[#This Row],[Unit_Price3]] -> 589.56 | P23: =Sales_Fact[[#This Row],[Gross Amount]]*Sales_Fact[[#This Row],[Discount4]] -> 129.7032 | Q23: =IF(Sales_Fact[[#This Row],[Total_Amount5]]>1000,"High Value","Standard") -> Standard
A24: SALE22 | B24: 45394 | C24: CUST1476 | D24: PROD69 | E24: STORE10 | F24: 3 | G24: 979.42 | H24: 0.03 | I24: PayPal | J24: 2850.1122 | K24: =IF(ISBLANK(Sales_Fact[[#This Row],[Quantity]]),MEDIAN(Sales_Fact[Quantity]),Sales_Fact[[#This Row],[Quantity]]) -> 3 | L24: =IF(ISBLANK(Sales_Fact[[#This Row],[Unit_Price]]),MEDIAN(Sales_Fact[Unit_Price]),Sales_Fact[[#This Row],[Unit_Price]]) -> 979.42 | M24: =IF(ISBLANK(Sales_Fact[[#This Row],[Discount]]),MEDIAN(Sales_Fact[Discount]),Sales_Fact[[#This Row],[Discount]]) -> 0.03 | N24: =Sales_Fact[[#This Row],[Quantity2]]*Sales_Fact[[#This Row],[Unit_Price3]]*(1-Sales_Fact[[#This Row],[Discount4]]) -> 2850.1122 | O24: =Sales_Fact[[#This Row],[Quantity2]]*Sales_Fact[[#This Row],[Unit_Price3]] -> 2938.26 | P24: =Sales_Fact[[#This Row],[Gross Amount]]*Sales_Fact[[#This Row],[Discount4]] -> 88.1478 | Q24: =IF(Sales_Fact[[#This Row],[Total_Amount5]]>1000,"High Value","Standard") -> High Value
A25: SALE23 | B25: 45466 | C25: CUST1368 | D25: PROD12 | E25: STORE8 | F25: 1 | G25: 719.28 | H25: 0.08 | I25: Credit Card | J25: 661.7376 | K25: =IF(ISBLANK(Sales_Fact[[#This Row],[Quantity]]),MEDIAN(Sales_Fact[Quantity]),Sales_Fact[[#This Row],[Quantity]]) -> 1 | L25: =IF(ISBLANK(Sales_Fact[[#This Row],[Unit_Price]]),MEDIAN(Sales_Fact[Unit_Price]),Sales_Fact[[#This Row],[Unit_Price]]) -> 719.28 | M25: =IF(ISBLANK(Sales_Fact[[#This Row],[Discount]]),MEDIAN(Sales_Fact[Discount]),Sales_Fact[[#This Row],[Discount]]) -> 0.08 | N25: =Sales_Fact[[#This Row],[Quantity2]]*Sales_Fact[[#This Row],[Unit_Price3]]*(1-Sales_Fact[[#This Row],[Discount4]]) -> 661.7376 | O25: =Sales_Fact[[#This Row],[Quantity2]]*Sales_Fact[[#This Row],[Unit_Price3]] -> 719.28 | P25: =Sales_Fact[[#This Row],[Gross Amount]]*Sales_Fact[[#This Row],[Discount4]] -> 57.5424 | Q25: =IF(Sales_Fact[[#This Row],[Total_Amount5]]>1000,"High Value","Standard") -> Standard
A26: SALE24 | B26: 45908 | C26: CUST1186 | D26: PROD67 | E26: STORE6 | F26: 3 | G26: 77.6 | H26: 0.07 | I26: Credit Card | J26: 216.504 | K26: =IF(ISBLANK(Sales_Fact[[#This Row],[Quantity]]),MEDIAN(Sales_Fact[Quantity]),Sales_Fact[[#This Row],[Quantity]]) -> 3 | L26: =IF(ISBLANK(Sales_Fact[[#This Row],[Unit_Price]]),MEDIAN(Sales_Fact[Unit_Price]),Sales_Fact[[#This Row],[Unit_Price]]) -> 77.6 | M26: =IF(ISBLANK(Sales_Fact[[#This Row],[Discount]]),MEDIAN(Sales_Fact[Discount]),Sales_Fact[[#This Row],[Discount]]) -> 0.07 | N26: =Sales_Fact[[#This Row],[Quantity2]]*Sales_Fact[[#This Row],[Unit_Price3]]*(1-Sales_Fact[[#This Row],[Discount4]]) -> 216.504 | O26: =Sales_Fact[[#This Row],[Quantity2]]*Sales_Fact[[#This Row],[Unit_Price3]] -> 232.8 | P26: =Sales_Fact[[#This Row],[Gross Amount]]*Sales_Fact[[#This Row],[Discount4]] -> 16.296 | Q26: =IF(Sales_Fact[[#This Row],[Total_Amount5]]>1000,"High Value","Standard") -> Standard
A27: SALE25 | B27: 45552 | C27: CUST1381 | D27: PROD5 | E27: STORE3 | F27: 4 | G27: 852.71 | H27: 0.14 | I27: PayPal | J27: 2933.3224 | K27: =IF(ISBLANK(Sales_Fact[[#This Row],[Quantity]]),MEDIAN(Sales_Fact[Quantity]),Sales_Fact[[#This Row],[Quantity]]) -> 4 | L27: =IF(ISBLANK(Sales_Fact[[#This Row],[Unit_Price]]),MEDIAN(Sales_Fact[Unit_Price]),Sales_Fact[[#This Row],[Unit_Price]]) -> 852.71 | M27: =IF(ISBLANK(Sales_Fact[[#This Row],[Discount]]),MEDIAN(Sales_Fact[Discount]),Sales_Fact[[#This Row],[Discount]]) -> 0.14 | N27: =Sales_Fact[[#This Row],[Quantity2]]*Sales_Fact[[#This Row],[Unit_Price3]]*(1-Sales_Fact[[#This Row],[Discount4]]) -> 2933.3224 | O27: =Sales_Fact[[#This Row],[Quantity2]]*Sales_Fact[[#This Row],[Unit_Price3]] -> 3410.84 | P27: =Sales_Fact[[#This Row],[Gross Amount]]*Sales_Fact[[#This Row],[Discount4]] -> 477.5176 | Q27: =IF(Sales_Fact[[#This Row],[Total_Amount5]]>1000,"High Value","Standard") -> High Value
A28: SALE26 | B28: 45294 | C28: CUST1213 | D28: PROD98 | E28: STORE8 | F28: 4 | G28: 156.16 | I28: Credit Card | J28: 599.6544 | K28: =IF(ISBLANK(Sales_Fact[[#This Row],[Quantity]]),MEDIAN(Sales_Fact[Quantity]),Sales_Fact[[#This Row],[Quantity]]) -> 4 | L28: =IF(ISBLANK(Sales_Fact[[#This Row],[Unit_Price]]),MEDIAN(Sales_Fact[Unit_Price]),Sales_Fact[[#This Row],[Unit_Price]]) -> 156.16 | M28: =IF(ISBLANK(Sales_Fact[[#This Row],[Discount]]),MEDIAN(Sales_Fact[Discount]),Sales_Fact[[#This Row],[Discount]]) -> 0.14 | N28: =Sales_Fact[[#This Row],[Quantity2]]*Sales_Fact[[#This Row],[Unit_Price3]]*(1-Sales_Fact[[#This Row],[Discount4]]) -> 537.1904 | O28: =Sales_Fact[[#This Row],[Quantity2]]*Sales_Fact[[#This Row],[Unit_Price3]] -> 624.64 | P28: =Sales_Fact[[#This Row],[Gross Amount]]*Sales_Fact[[#This Row],[Discount4]] -> 87.4496 | Q28: =IF(Sales_Fact[[#This Row],[Total_Amount5]]>1000,"High Value","Standard") -> Standard
A29: SALE27 | B29: 45710 | C29: CUST1200 | D29: PROD77 | E29: STORE8 | F29: 3 | G29: 815.49 | H29: 0.17 | I29: Credit Card | J29: 2030.5701 | K29: =IF(ISBLANK(Sales_Fact[[#This Row],[Quantity]]),MEDIAN(Sales_Fact[Quantity]),Sales_Fact[[#This Row],[Quantity]]) -> 3 | L29: =IF(ISBLANK(Sales_Fact[[#This Row],[Unit_Price]]),MEDIAN(Sales_Fact[Unit_Price]),Sales_Fact[[#This Row],[Unit_Price]]) -> 815.49 | M29: =IF(ISBLANK(Sales_Fact[[#This Row],[Discount]]),MEDIAN(Sales_Fact[Discount]),Sales_Fact[[#This Row],[Discount]]) -> 0.17 | N29: =Sales_Fact[[#This Row],[Quantity2]]*Sales_Fact[[#This Row],[Unit_Price3]]*(1-Sales_Fact[[#This Row],[Discount4]]) -> 2030.5701 | O29: =Sales_Fact[[#This Row],[Quantity2]]*Sales_Fact[[#This Row],[Unit_Price3]] -> 2446.47 | P29: =Sales_Fact[[#This Row],[Gross Amount]]*Sales_Fact[[#This Row],[Discount4]] -> 415.8999 | Q29: =IF(Sales_Fact[[#This Row],[Total_Amount5]]>1000,"High Value","Standard") -> High Value
A30: SALE28 | B30: 45923 | C30: CUST1148 | D30: PROD13 | E30: STORE2 | F30: 2 | G30: 74.21 | H30: 0.11 | I30: PayPal | J30: 132.0938 | K30: =IF(ISBLANK(Sales_Fact[[#This Row],[Quantity]]),MEDIAN(Sales_Fact[Quantity]),Sales_Fact[[#This Row],[Quantity]]) -> 2 | L30: =IF(ISBLANK(Sales_Fact[[#This Row],[Unit_Price]]),MEDIAN(Sales_Fact[Unit_Price]),Sales_Fact[[#This Row],[Unit_Price]]) -> 74.21 | M30: =IF(ISBLANK(Sales_Fact[[#This Row],[Discount]]),MEDIAN(Sales_Fact[Discount]),Sales_Fact[[#This Row],[Discount]]) -> 0.11 | N30: =Sales_Fact[[#This Row],[Quantity2]]*Sales_Fact[[#This Row],[Unit_Price3]]*(1-Sales_Fact[[#This Row],[Discount4]]) -> 132.0938 | O30: =Sales_Fact[[#This Row],[Quantity2]]*Sales_Fact[[#This Row],[Unit_Price3]] -> 148.42 | P30: =Sales_Fact[[#This Row],[Gross Amount]]*Sales_Fact[[#This Row],[Discount4]] -> 16.3262 | Q30: =IF(Sales_Fact[[#This Row],[Total_Amount5]]>1000,"High Value","Standard") -> Standard
A31: SALE29 | B31: 45302 | C31: CUST1348 | D31: PROD99 | E31: STORE3 | G31: 451.67 | H31: 0.15 | I31: Credit Card | J31: 1535.678 | K31: =IF(ISBLANK(Sales_Fact[[#This Row],[Quantity]]),MEDIAN(Sales_Fact[Quantity]),Sales_Fact[[#This Row],[Quantity]]) -> 2 | L31: =IF(ISBLANK(Sales_Fact[[#This Row],[Unit_Price]]),MEDIAN(Sales_Fact[Unit_Price]),Sales_Fact[[#This Row],[Unit_Price]]) -> 451.67 | M31: =IF(ISBLANK(Sales_Fact[[#This Row],[Discount]]),MEDIAN(Sales_Fact[Discount]),Sales_Fact[[#This Row],[Discount]]) -> 0.15 | N31: =Sales_Fact[[#This Row],[Quantity2]]*Sales_Fact[[#This Row],[Unit_Price3]]*(1-Sales_Fact[[#This Row],[Discount4]]) -> 767.839 | O31: =Sales_Fact[[#This Row],[Quantity2]]*Sales_Fact[[#This Row],[Unit_Price3]] -> 903.34 | P31: =Sales_Fact[[#This Row],[Gross Amount]]*Sales_Fact[[#This Row],[Discount4]] -> 135.501 | Q31: =IF(Sales_Fact[[#This Row],[Total_Amount5]]>1000,"High Value","Standard") -> Standard
A32: SALE30 | B32: 45217 | C32: CUST1028 | D32: PROD5 | E32: STORE19 | F32: 1 | G32: 429.38 | H32: 0.13 | I32: PayPal | J32: 373.5606 | K32: =IF(ISBLANK(Sales_Fact[[#This Row],[Quantity]]),MEDIAN(Sales_Fact[Quantity]),Sales_Fact[[#This Row],[Quantity]]) -> 1 | L32: =IF(ISBLANK(Sales_Fact[[#This Row],[Unit_Price]]),MEDIAN(Sales_Fact[Unit_Price]),Sales_Fact[[#This Row],[Unit_Price]]) -> 429.38 | M32: =IF(ISBLANK(Sales_Fact[[#This Row],[Discount]]),MEDIAN(Sales_Fact[Discount]),Sales_Fact[[#This Row],[Discount]]) -> 0.13 | N32: =Sales_Fact[[#This Row],[Quantity2]]*Sales_Fact[[#This Row],[Unit_Price3]]*(1-Sales_Fact[[#This Row],[Discount4]]) -> 373.5606 | O32: =Sales_Fact[[#This Row],[Quantity2]]*Sales_Fact[[#This Row],[Unit_Price3]] -> 429.38 | P32: =Sales_Fact[[#This Row],[Gross Amount]]*Sales_Fact[[#This Row],[Discount4]] -> 55.8194 | Q32: =IF(Sales_Fact[[#This Row],[Total_Amount5]]>1000,"High Value","Standard") -> Standard
A33: SALE31 | B33: 45593 | C33: CUST1412 | D33: PROD53 | E33: STORE12 | F33: 2 | G33: 148.96 | H33: 0.03 | I33: COD | J33: 288.9824 | K33: =IF(ISBLANK(Sales_Fact[[#This Row],[Quantity]]),MEDIAN(Sales_Fact[Quantity]),Sales_Fact[[#This Row],[Quantity]]) -> 2 | L33: =IF(ISBLANK(Sales_Fact[[#This Row],[Unit_Price]]),MEDIAN(Sales_Fact[Unit_Price]),Sales_Fact[[#This Row],[Unit_Price]]) -> 148.96 | M33: =IF(ISBLANK(Sales_Fact[[#This Row],[Discount]]),MEDIAN(Sales_Fact[Discount]),Sales_Fact[[#This Row],[Discount]]) -> 0.03 | N33: =Sales_Fact[[#This Row],[Quantity2]]*Sales_Fact[[#This Row],[Unit_Price3]]*(1-Sales_Fact[[#This Row],[Discount4]]) -> 288.9824 | O33: =Sales_Fact[[#This Row],[Quantity2]]*Sales_Fact[[#This Row],[Unit_Price3]] -> 297.92 | P33: =Sales_Fact[[#This Row],[Gross Amount]]*Sales_Fact[[#This Row],[Discount4]] -> 8.9376 | Q33: =IF(Sales_Fact[[#This Row],[Total_Amount5]]>1000,"High Value","Standard") -> Standard
A34: SALE32 | B34: 45597 | C34: CUST1398 | D34: PROD75 | E34: STORE8 | F34: 4 | G34: 313.83 | H34: 0.08 | I34: Credit Card | J34: 1154.8944 | K34: =IF(ISBLANK(Sales_Fact[[#This Row],[Quantity]]),MEDIAN(Sales_Fact[Quantity]),Sales_Fact[[#This Row],[Quantity]]) -> 4 | L34: =IF(ISBLANK(Sales_Fact[[#This Row],[Unit_Price]]),MEDIAN(Sales_Fact[Unit_Price]),Sales_Fact[[#This Row],[Unit_Price]]) -> 313.83 | M34: =IF(ISBLANK(Sales_Fact[[#This Row],[Discount]]),MEDIAN(Sales_Fact[Discount]),Sales_Fact[[#This Row],[Discount]]) -> 0.08 | N34: =Sales_Fact[[#This Row],[Quantity2]]*Sales_Fact[[#This Row],[Unit_Price3]]*(1-Sales_Fact[[#This Row],[Discount4]]) -> 1154.8944 | O34: =Sales_Fact[[#This Row],[Quantity2]]*Sales_Fact[[#This Row],[Unit_Price3]] -> 1255.32 | P34: =Sales_Fact[[#This Row],[Gross Amount]]*Sales_Fact[[#This Row],[Discount4]] -> 100.4256 | Q34: =IF(Sales_Fact[[#This Row],[Total_Amount5]]>1000,"High Value","Standard") -> High Value
A35: SALE33 | B35: 45620 | C35: CUST1453 | D35: PROD12 | E35: STORE6 | F35: 2 | G35: 717.31 | H35: 0.15 | I35: Credit Card | J35: 1219.427 | K35: =IF(ISBLANK(Sales_Fact[[#This Row],[Quantity]]),MEDIAN(Sales_Fact[Quantity]),Sales_Fact[[#This Row],[Quantity]]) -> 2 | L35: =IF(ISBLANK(Sales_Fact[[#This Row],[Unit_Price]]),MEDIAN(Sales_Fact[Unit_Price]),Sales_Fact[[#This Row],[Unit_Price]]) -> 717.31 | M35: =IF(ISBLANK(Sales_Fact[[#This Row],[Discount]]),MEDIAN(Sales_Fact[Discount]),Sales_Fact[[#This Row],[Discount]]) -> 0.15 | N35: =Sales_Fact[[#This Row],[Quantity2]]*Sales_Fact[[#This Row],[Unit_Price3]]*(1-Sales_Fact[[#This Row],[Discount4]]) -> 1219.427 | O35: =Sales_Fact[[#This Row],[Quantity2]]*Sales_Fact[[#This Row],[Unit_Price3]] -> 1434.62 | P35: =Sales_Fact[[#This Row],[Gross Amount]]*Sales_Fact[[#This Row],[Discount4]] -> 215.193 | Q35: =IF(Sales_Fact[[#This Row],[Total_Amount5]]>1000,"High Value","Standard") -> High Value
A36: SALE34 | B36: 45215 | C36: CUST1344 | D36: PROD79 | E36: STORE1 | G36: 873.22 | H36: 0.18 | I36: Credit Card | J36: 2148.1212 | K36: =IF(ISBLANK(Sales_Fact[[#This Row],[Quantity]]),MEDIAN(Sales_Fact[Quantity]),Sales_Fact[[#This Row],[Quantity]]) -> 2 | L36: =IF(ISBLANK(Sales_Fact[[#This Row],[Unit_Price]]),MEDIAN(Sales_Fact[Unit_Price]),Sales_Fact[[#This Row],[Unit_Price]]) -> 873.22 | M36: =IF(ISBLANK(Sales_Fact[[#This Row],[Discount]]),MEDIAN(Sales_Fact[Discount]),Sales_Fact[[#This Row],[Discount]]) -> 0.18 | N36: =Sales_Fact[[#This Row],[Quantity2]]*Sales_Fact[[#This Row],[Unit_Price3]]*(1-Sales_Fact[[#This Row],[Discount4]]) -> 1432.0808 | O36: =Sales_Fact[[#This Row],[Quantity2]]*Sales_Fact[[#This Row],[Unit_Price3]] -> 1746.44 | P36: =Sales_Fact[[#This Row],[Gross Amount]]*Sales_Fact[[#This Row],[Discount4]] -> 314.3592 | Q36: =IF(Sales_Fact[[#This Row],[Total_Amount5]]>1000,"High Value","Standard") -> High Value
A37: SALE35 | B37: 45878 | C37: CUST1218 | D37: PROD16 | E37: STORE3 | F37: 4 | G37: 109.36 | H37: 0.19 | I37: COD | J37: 354.3264 | K37: =IF(ISBLANK(Sales_Fact[[#This Row],[Quantity]]),MEDIAN(Sales_Fact[Quantity]),Sales_Fact[[#This Row],[Quantity]]) -> 4 | L37: =IF(ISBLANK(Sales_Fact[[#This Row],[Unit_Price]]),MEDIAN(Sales_Fact[Unit_Price]),Sales_Fact[[#This Row],[Unit_Price]]) -> 109.36 | M37: =IF(ISBLANK(Sales_Fact[[#This Row],[Discount]]),MEDIAN(Sales_Fact[Discount]),Sales_Fact[[#This Row],[Discount]]) -> 0.19 | N37: =Sales_Fact[[#This Row],[Quantity2]]*Sales_Fact[[#This Row],[Unit_Price3]]*(1-Sales_Fact[[#This Row],[Discount4]]) -> 354.3264 | O37: =Sales_Fact[[#This Row],[Quantity2]]*Sales_Fact[[#This Row],[Unit_Price3]] -> 437.44 | P37: =Sales_Fact[[#This Row],[Gross Amount]]*Sales_Fact[[#This Row],[Discount4]] -> 83.1136 | Q37: =IF(Sales_Fact[[#This Row],[Total_Amount5]]>1000,"High Value","Standard") -> Standard
A38: SALE36 | B38: 45635 | C38: CUST1086 | D38: PROD5 | E38: STORE7 | F38: 3 | G38: 559.52 | H38: 0.16 | I38: PayPal | J38: 1409.9904 | K38: =IF(ISBLANK(Sales_Fact[[#This Row],[Quantity]]),MEDIAN(Sales_Fact[Quantity]),Sales_Fact[[#This Row],[Quantity]]) -> 3 | L38: =IF(ISBLANK(Sales_Fact[[#This Row],[Unit_Price]]),MEDIAN(Sales_Fact[Unit_Price]),Sales_Fact[[#This Row],[Unit_Price]]) -> 559.52 | M38: =IF(ISBLANK(Sales_Fact[[#This Row],[Discount]]),MEDIAN(Sales_Fact[Discount]),Sales_Fact[[#This Row],[Discount]]) -> 0.16 | N38: =Sales_Fact[[#This Row],[Quantity2]]*Sales_Fact[[#This Row],[Unit_Price3]]*(1-Sales_Fact[[#This Row],[Discount4]]) -> 1409.9904 | O38: =Sales_Fact[[#This Row],[Quantity2]]*Sales_Fact[[#This Row],[Unit_Price3]] -> 1678.56 | P38: =Sales_Fact[[#This Row],[Gross Amount]]*Sales_Fact[[#This Row],[Discount4]] -> 268.5696 | Q38: =IF(Sales_Fact[[#This Row],[Total_Amount5]]>1000,"High Value","Standard") -> High Value
A39: SALE37 | B39: 45329 | C39: CUST1492 | D39: PROD10 | E39: STORE17 | F39: 3 | G39: 121.76 | H39: 0.27 | I39: PayPal | J39: 266.6544 | K39: =IF(ISBLANK(Sales_Fact[[#This Row],[Quantity]]),MEDIAN(Sales_Fact[Quantity]),Sales_Fact[[#This Row],[Quantity]]) -> 3 | L39: =IF(ISBLANK(Sales_Fact[[#This Row],[Unit_Price]]),MEDIAN(Sales_Fact[Unit_Price]),Sales_Fact[[#This Row],[Unit_Price]]) -> 121.76 | M39: =IF(ISBLANK(Sales_Fact[[#This Row],[Discount]]),MEDIAN(Sales_Fact[Discount]),Sales_Fact[[#This Row],[Discount]]) -> 0.27 | N39: =Sales_Fact[[#This Row],[Quantity2]]*Sales_Fact[[#This Row],[Unit_Price3]]*(1-Sales_Fact[[#This Row],[Discount4]]) -> 266.6544 | O39: =Sales_Fact[[#This Row],[Quantity2]]*Sales_Fact[[#This Row],[Unit_Price3]] -> 365.28 | P39: =Sales_Fact[[#This Row],[Gross Amount]]*Sales_Fact[[#This Row],[Discount4]] -> 98.6256 | Q39: =IF(Sales_Fact[[#This Row],[Total_Amount5]]>1000,"High Value","Standard") -> Standard
A40: SALE38 | B40: 45378 | C40: CUST1189 | D40: PROD33 | E40: STORE13 | F40: 4 | G40: 735.32 | H40: 0.06 | I40: COD | J40: 2764.8032 | K40: =IF(ISBLANK(Sales_Fact[[#This Row],[Quantity]]),MEDIAN(Sales_Fact[Quantity]),Sales_Fact[[#This Row],[Quantity]]) -> 4 | L40: =IF(ISBLANK(Sales_Fact[[#This Row],[Unit_Price]]),MEDIAN(Sales_Fact[Unit_Price]),Sales_Fact[[#This Row],[Unit_Price]]) -> 735.32 | M40: =IF(ISBLANK(Sales_Fact[[#This Row],[Discount]]),MEDIAN(Sales_Fact[Discount]),Sales_Fact[[#This Row],[Discount]]) -> 0.06 | N40: =Sales_Fact[[#This Row],[Quantity2]]*Sales_Fact[[#This Row],[Unit_Price3]]*(1-Sales_Fact[[#This Row],[Discount4]]) -> 2764.8032 | O40: =Sales_Fact[[#This Row],[Quantity2]]*Sales_Fact[[#This Row],[Unit_Price3]] -> 2941.28 | P40: =Sales_Fact[[#This Row],[Gross Amount]]*Sales_Fact[[#This Row],[Discount4]] -> 176.4768 | Q40: =IF(Sales_Fact[[#This Row],[Total_Amount5]]>1000,"High Value","Standard") -> High Value
A41: SALE39 | B41: 45264 | C41: CUST1431 | D41: PROD94 | E41: STORE3 | F41: 2 | G41: 600.73 | H41: 0.08 | I41: Credit Card | J41: 1105.3432 | K41: =IF(ISBLANK(Sales_Fact[[#This Row],[Quantity]]),MEDIAN(Sales_Fact[Quantity]),Sales_Fact[[#This Row],[Quantity]]) -> 2 | L41: =IF(ISBLANK(Sales_Fact[[#This Row],[Unit_Price]]),MEDIAN(Sales_Fact[Unit_Price]),Sales_Fact[[#This Row],[Unit_Price]]) -> 600.73 | M41: =IF(ISBLANK(Sales_Fact[[#This Row],[Discount]]),MEDIAN(Sales_Fact[Discount]),Sales_Fact[[#This Row],[Discount]]) -> 0.08 | N41: =Sales_Fact[[#This Row],[Quantity2]]*Sales_Fact[[#This Row],[Unit_Price3]]*(1-Sales_Fact[[#This Row],[Discount4]]) -> 1105.3432 | O41: =Sales_Fact[[#This Row],[Quantity2]]*Sales_Fact[[#This Row],[Unit_Price3]] -> 1201.46 | P41: =Sales_Fact[[#This Row],[Gross Amount]]*Sales_Fact[[#This Row],[Discount4]] -> 96.1168 | Q41: =IF(Sales_Fact[[#This Row],[Total_Amount5]]>1000,"High Value","Standard") -> High Value
A42: SALE40 | B42: 45486 | C42: CUST1072 | D42: PROD26 | E42: STORE19 | F42: 2 | G42: 873.86 | H42: 0.07 | I42: COD | J42: 1625.3796 | K42: =IF(ISBLANK(Sales_Fact[[#This Row],[Quantity]]),MEDIAN(Sales_Fact[Quantity]),Sales_Fact[[#This Row],[Quantity]]) -> 2 | L42: =IF(ISBLANK(Sales_Fact[[#This Row],[Unit_Price]]),MEDIAN(Sales_Fact[Unit_Price]),Sales_Fact[[#This Row],[Unit_Price]]) -> 873.86 | M42: =IF(ISBLANK(Sales_Fact[[#This Row],[Discount]]),MEDIAN(Sales_Fact[Discount]),Sales_Fact[[#This Row],[Discount]]) -> 0.07 | N42: =Sales_Fact[[#This Row],[Quantity2]]*Sales_Fact[[#This Row],[Unit_Price3]]*(1-Sales_Fact[[#This Row],[Discount4]]) -> 1625.3796 | O42: =Sales_Fact[[#This Row],[Quantity2]]*Sales_Fact[[#This Row],[Unit_Price3]] -> 1747.72 | P42: =Sales_Fact[[#This Row],[Gross Amount]]*Sales_Fact[[#This Row],[Discount4]] -> 122.3404 | Q42: =IF(Sales_Fact[[#This Row],[Total_Amount5]]>1000,"High Value","Standard") -> High Value
A43: SALE41 | B43: 45241 | C43: CUST1302 | D43: PROD23 | E43: STORE8 | F43: 3 | G43: 342.47 | H43: 0.08 | I43: PayPal | J43: 945.2172 | K43: =IF(ISBLANK(Sales_Fact[[#This Row],[Quantity]]),MEDIAN(Sales_Fact[Quantity]),Sales_Fact[[#This Row],[Quantity]]) -> 3 | L43: =IF(ISBLANK(Sales_Fact[[#This Row],[Unit_Price]]),MEDIAN(Sales_Fact[Unit_Price]),Sales_Fact[[#This Row],[Unit_Price]]) -> 342.47 | M43: =IF(ISBLANK(Sales_Fact[[#This Row],[Discount]]),MEDIAN(Sales_Fact[Discount]),Sales_Fact[[#This Row],[Discount]]) -> 0.08 | N43: =Sales_Fact[[#This Row],[Quantity2]]*Sales_Fact[[#This Row],[Unit_Price3]]*(1-Sales_Fact[[#This Row],[Discount4]]) -> 945.2172 | O43: =Sales_Fact[[#This Row],[Quantity2]]*Sales_Fact[[#This Row],[Unit_Price3]] -> 1027.41 | P43: =Sales_Fact[[#This Row],[Gross Amount]]*Sales_Fact[[#This Row],[Discount4]] -> 82.1928 | Q43: =IF(Sales_Fact[[#This Row],[Total_Amount5]]>1000,"High Value","Standard") -> Standard
A44: SALE42 | B44: 45649 | C44: CUST1335 | D44: PROD29 | E44: STORE9 | F44: 2 | G44: 915.15 | H44: 0.16 | I44: PayPal | J44: 1537.452 | K44: =IF(ISBLANK(Sales_Fact[[#This Row],[Quantity]]),MEDIAN(Sales_Fact[Quantity]),Sales_Fact[[#This Row],[Quantity]]) -> 2 | L44: =IF(ISBLANK(Sales_Fact[[#This Row],[Unit_Price]]),MEDIAN(Sales_Fact[Unit_Price]),Sales_Fact[[#This Row],[Unit_Price]]) -> 915.15 | M44: =IF(ISBLANK(Sales_Fact[[#This Row],[Discount]]),MEDIAN(Sales_Fact[Discount]),Sales_Fact[[#This Row],[Discount]]) -> 0.16 | N44: =Sales_Fact[[#This Row],[Quantity2]]*Sales_Fact[[#This Row],[Unit_Price3]]*(1-Sales_Fact[[#This Row],[Discount4]]) -> 1537.452 | O44: =Sales_Fact[[#This Row],[Quantity2]]*Sales_Fact[[#This Row],[Unit_Price3]] -> 1830.3 | P44: =Sales_Fact[[#This Row],[Gross Amount]]*Sales_Fact[[#This Row],[Discount4]] -> 292.848 | Q44: =IF(Sales_Fact[[#This Row],[Total_Amount5]]>1000,"High Value","Standard") -> High Value
A45: SALE43 | B45: 45677 | C45: CUST1084 | D45: PROD33 | E45: STORE17 | G45: 863.11 | H45: 0.28 | I45: PayPal | J45: 1864.3176 | K45: =IF(ISBLANK(Sales_Fact[[#This Row],[Quantity]]),MEDIAN(Sales_Fact[Quantity]),Sales_Fact[[#This Row],[Quantity]]) -> 2 | L45: =IF(ISBLANK(Sales_Fact[[#This Row],[Unit_Price]]),MEDIAN(Sales_Fact[Unit_Price]),Sales_Fact[[#This Row],[Unit_Price]]) -> 863.11 | M45: =IF(ISBLANK(Sales_Fact[[#This Row],[Discount]]),MEDIAN(Sales_Fact[Discount]),Sales_Fact[[#This Row],[Discount]]) -> 0.28 | N45: =Sales_Fact[[#This Row],[Quantity2]]*Sales_Fact[[#This Row],[Unit_Price3]]*(1-Sales_Fact[[#This Row],[Discount4]]) -> 1242.8784 | O45: =Sales_Fact[[#This Row],[Quantity2]]*Sales_Fact[[#This Row],[Unit_Price3]] -> 1726.22 | P45: =Sales_Fact[[#This Row],[Gross Amount]]*Sales_Fact[[#This Row],[Discount4]] -> 483.3416 | Q45: =IF(Sales_Fact[[#This Row],[Total_Amount5]]>1000,"High Value","Standard") -> High Value
A46: SALE44 | B46: 45538 | C46: CUST1203 | D46: PROD43 | E46: STORE12 | F46: 2 | G46: 209.32 | H46: 0.23 | I46: COD | J46: 322.3528 | K46: =IF(ISBLANK(Sales_Fact[[#This Row],[Quantity]]),MEDIAN(Sales_Fact[Quantity]),Sales_Fact[[#This Row],[Quantity]]) -> 2 | L46: =IF(ISBLANK(Sales_Fact[[#This Row],[Unit_Price]]),MEDIAN(Sales_Fact[Unit_Price]),Sales_Fact[[#This Row],[Unit_Price]]) -> 209.32 | M46: =IF(ISBLANK(Sales_Fact[[#This Row],[Discount]]),MEDIAN(Sales_Fact[Discount]),Sales_Fact[[#This Row],[Discount]]) -> 0.23 | N46: =Sales_Fact[[#This Row],[Quantity2]]*Sales_Fact[[#This Row],[Unit_Price3]]*(1-Sales_Fact[[#This Row],[Discount4]]) -> 322.3528 | O46: =Sales_Fact[[#This Row],[Quantity2]]*Sales_Fact[[#This Row],[Unit_Price3]] -> 418.64 | P46: =Sales_Fact[[#This Row],[Gross Amount]]*Sales_Fact[[#This Row],[Discount4]] -> 96.2872 | Q46: =IF(Sales_Fact[[#This Row],[Total_Amount5]]>1000,"High Value","Standard") -> Standard
A47: SALE45 | B47: 45606 | C47: CUST1470 | D47: PROD59 | E47: STORE8 | F47: 4 | G47: 288.6 | H47: 0.09 | I47: PayPal | J47: 1050.504 | K47: =IF(ISBLANK(Sales_Fact[[#This Row],[Quantity]]),MEDIAN(Sales_Fact[Quantity]),Sales_Fact[[#This Row],[Quantity]]) -> 4 | L47: =IF(ISBLANK(Sales_Fact[[#This Row],[Unit_Price]]),MEDIAN(Sales_Fact[Unit_Price]),Sales_Fact[[#This Row],[Unit_Price]]) -> 288.6 | M47: =IF(ISBLANK(Sales_Fact[[#This Row],[Discount]]),MEDIAN(Sales_Fact[Discount]),Sales_Fact[[#This Row],[Discount]]) -> 0.09 | N47: =Sales_Fact[[#This Row],[Quantity2]]*Sales_Fact[[#This Row],[Unit_Price3]]*(1-Sales_Fact[[#This Row],[Discount4]]) -> 1050.504 | O47: =Sales_Fact[[#This Row],[Quantity2]]*Sales_Fact[[#This Row],[Unit_Price3]] -> 1154.4 | P47: =Sales_Fact[[#This Row],[Gross Amount]]*Sales_Fact[[#This Row],[Discount4]] -> 103.896 | Q47: =IF(Sales_Fact[[#This Row],[Total_Amount5]]>1000,"High Value","Standard") -> High Value
A48: SALE46 | B48: 45570 | C48: CUST1070 | D48: PROD78 | E48: STORE16 | F48: 1 | G48: 418.69 | H48: 0.06 | I48: PayPal | J48: 393.5686 | K48: =IF(ISBLANK(Sales_Fact[[#This Row],[Quantity]]),MEDIAN(Sales_Fact[Quantity]),Sales_Fact[[#This Row],[Quantity]]) -> 1 | L48: =IF(ISBLANK(Sales_Fact[[#This Row],[Unit_Price]]),MEDIAN(Sales_Fact[Unit_Price]),Sales_Fact[[#This Row],[Unit_Price]]) -> 418.69 | M48: =IF(ISBLANK(Sales_Fact[[#This Row],[Discount]]),MEDIAN(Sales_Fact[Discount]),Sales_Fact[[#This Row],[Discount]]) -> 0.06 | N48: =Sales_Fact[[#This Row],[Quantity2]]*Sales_Fact[[#This Row],[Unit_Price3]]*(1-Sales_Fact[[#This Row],[Discount4]]) -> 393.5686 | O48: =Sales_Fact[[#This Row],[Quantity2]]*Sales_Fact[[#This Row],[Unit_Price3]] -> 418.69 | P48: =Sales_Fact[[#This Row],[Gross Amount]]*Sales_Fact[[#This Row],[Discount4]] -> 25.1214 | Q48: =IF(Sales_Fact[[#This Row],[Total_Amount5]]>1000,"High Value","Standard") -> Standard
A49: SALE47 | B49: 45466 | C49: CUST1008 | D49: PROD30 | E49: STORE11 | F49: 1 | G49: 135.78 | H49: 0.14 | I49: PayPal | J49: 116.7708 | K49: =IF(ISBLANK(Sales_Fact[[#This Row],[Quantity]]),MEDIAN(Sales_Fact[Quantity]),Sales_Fact[[#This Row],[Quantity]]) -> 1 | L49: =IF(ISBLANK(Sales_Fact[[#This Row],[Unit_Price]]),MEDIAN(Sales_Fact[Unit_Price]),Sales_Fact[[#This Row],[Unit_Price]]) -> 135.78 | M49: =IF(ISBLANK(Sales_Fact[[#This Row],[Discount]]),MEDIAN(Sales_Fact[Discount]),Sales_Fact[[#This Row],[Discount]]) -> 0.14 | N49: =Sales_Fact[[#This Row],[Quantity2]]*Sales_Fact[[#This Row],[Unit_Price3]]*(1-Sales_Fact[[#This Row],[Discount4]]) -> 116.7708 | O49: =Sales_Fact[[#This Row],[Quantity2]]*Sales_Fact[[#This Row],[Unit_Price3]] -> 135.78 | P49: =Sales_Fact[[#This Row],[Gross Amount]]*Sales_Fact[[#This Row],[Discount4]] -> 19.0092 | Q49: =IF(Sales_Fact[[#This Row],[Total_Amount5]]>1000,"High Value","Standard") -> Standard
A50: SALE48 | B50: 45218 | C50: CUST1203 | D50: PROD44 | E50: STORE17 | F50: 1 | G50: 517.13 | H50: 0.28 | I50: Credit Card | J50: 372.3336 | K50: =IF(ISBLANK(Sales_Fact[[#This Row],[Quantity]]),MEDIAN(Sales_Fact[Quantity]),Sales_Fact[[#This Row],[Quantity]]) -> 1 | L50: =IF(ISBLANK(Sales_Fact[[#This Row],[Unit_Price]]),MEDIAN(Sales_Fact[Unit_Price]),Sales_Fact[[#This Row],[Unit_Price]]) -> 517.13 | M50: =IF(ISBLANK(Sales_Fact[[#This Row],[Discount]]),MEDIAN(Sales_Fact[Discount]),Sales_Fact[[#This Row],[Discount]]) -> 0.28 | N50: =Sales_Fact[[#This Row],[Quantity2]]*Sales_Fact[[#This Row],[Unit_Price3]]*(1-Sales_Fact[[#This Row],[Discount4]]) -> 372.3336 | O50: =Sales_Fact[[#This Row],[Quantity2]]*Sales_Fact[[#This Row],[Unit_Price3]] -> 517.13 | P50: =Sales_Fact[[#This Row],[Gross Amount]]*Sales_Fact[[#This Row],[Discount4]] -> 144.7964 | Q50: =IF(Sales_Fact[[#This Row],[Total_Amount5]]>1000,"High Value","Standard") -> Standard
A51: SALE49 | B51: 45607 | C51: CUST1420 | D51: PROD21 | E51: STORE16 | F51: 2 | G51: 384.66 | H51: 0.08 | I51: COD | J51: 707.7744 | K51: =IF(ISBLANK(Sales_Fact[[#This Row],[Quantity]]),MEDIAN(Sales_Fact[Quantity]),Sales_Fact[[#This Row],[Quantity]]) -> 2 | L51: =IF(ISBLANK(Sales_Fact[[#This Row],[Unit_Price]]),MEDIAN(Sales_Fact[Unit_Price]),Sales_Fact[[#This Row],[Unit_Price]]) -> 384.66 | M51: =IF(ISBLANK(Sales_Fact[[#This Row],[Discount]]),MEDIAN(Sales_Fact[Discount]),Sales_Fact[[#This Row],[Discount]]) -> 0.08 | N51: =Sales_Fact[[#This Row],[Quantity2]]*Sales_Fact[[#This Row],[Unit_Price3]]*(1-Sales_Fact[[#This Row],[Discount4]]) -> 707.7744 | O51: =Sales_Fact[[#This Row],[Quantity2]]*Sales_Fact[[#This Row],[Unit_Price3]] -> 769.32 | P51: =Sales_Fact[[#This Row],[Gross Amount]]*Sales_Fact[[#This Row],[Discount4]] -> 61.5456 | Q51: =IF(Sales_Fact[[#This Row],[Total_Amount5]]>1000,"High Value","Standard") -> Standard
A52: SALE50 | B52: 45291 | C52: CUST1070 | D52: PROD52 | E52: STORE9 | F52: 3 | G52: 83.7 | H52: 0.24 | I52: PayPal | J52: 190.836 | K52: =IF(ISBLANK(Sales_Fact[[#This Row],[Quantity]]),MEDIAN(Sales_Fact[Quantity]),Sales_Fact[[#This Row],[Quantity]]) -> 3 | L52: =IF(ISBLANK(Sales_Fact[[#This Row],[Unit_Price]]),MEDIAN(Sales_Fact[Unit_Price]),Sales_Fact[[#This Row],[Unit_Price]]) -> 83.7 | M52: =IF(ISBLANK(Sales_Fact[[#This Row],[Discount]]),MEDIAN(Sales_Fact[Discount]),Sales_Fact[[#This Row],[Discount]]) -> 0.24 | N52: =Sales_Fact[[#This Row],[Quantity2]]*Sales_Fact[[#This Row],[Unit_Price3]]*(1-Sales_Fact[[#This Row],[Discount4]]) -> 190.836 | O52: =Sales_Fact[[#This Row],[Quantity2]]*Sales_Fact[[#This Row],[Unit_Price3]] -> 251.1 | P52: =Sales_Fact[[#This Row],[Gross Amount]]*Sales_Fact[[#This Row],[Discount4]] -> 60.264 | Q52: =IF(Sales_Fact[[#This Row],[Total_Amount5]]>1000,"High Value","Standard") -> Standard
A53: SALE51 | B53: 45689 | C53: CUST1142 | D53: PROD69 | E53: STORE7 | F53: 3 | G53: 76.57 | H53: 0.26 | I53: Credit Card | J53: 169.9854 | K53: =IF(ISBLANK(Sales_Fact[[#This Row],[Quantity]]),MEDIAN(Sales_Fact[Quantity]),Sales_Fact[[#This Row],[Quantity]]) -> 3 | L53: =IF(ISBLANK(Sales_Fact[[#This Row],[Unit_Price]]),MEDIAN(Sales_Fact[Unit_Price]),Sales_Fact[[#This Row],[Unit_Price]]) -> 76.57 | M53: =IF(ISBLANK(Sales_Fact[[#This Row],[Discount]]),MEDIAN(Sales_Fact[Discount]),Sales_Fact[[#This Row],[Discount]]) -> 0.26 | N53: =Sales_Fact[[#This Row],[Quantity2]]*Sales_Fact[[#This Row],[Unit_Price3]]*(1-Sales_Fact[[#This Row],[Discount4]]) -> 169.9854 | O53: =Sales_Fact[[#This Row],[Quantity2]]*Sales_Fact[[#This Row],[Unit_Price3]] -> 229.71 | P53: =Sales_Fact[[#This Row],[Gross Amount]]*Sales_Fact[[#This Row],[Discount4]] -> 59.7246 | Q53: =IF(Sales_Fact[[#This Row],[Total_Amount5]]>1000,"High Value","Standard") -> Standard
A54: SALE52 | B54: 45894 | C54: CUST1148 | D54: PROD89 | E54: STORE6 | F54: 3 | I54: Credit Card | J54: 486.0633 | K54: =IF(ISBLANK(Sales_Fact[[#This Row],[Quantity]]),MEDIAN(Sales_Fact[Quantity]),Sales_Fact[[#This Row],[Quantity]]) -> 3 | L54: =IF(ISBLANK(Sales_Fact[[#This Row],[Unit_Price]]),MEDIAN(Sales_Fact[Unit_Price]),Sales_Fact[[#This Row],[Unit_Price]]) -> 522.72 | M54: =IF(ISBLANK(Sales_Fact[[#This Row],[Discount]]),MEDIAN(Sales_Fact[Discount]),Sales_Fact[[#This Row],[Discount]]) -> 0.14 | N54: =Sales_Fact[[#This Row],[Quantity2]]*Sales_Fact[[#This Row],[Unit_Price3]]*(1-Sales_Fact[[#This Row],[Discount4]]) -> 1348.6176 | O54: =Sales_Fact[[#This Row],[Quantity2]]*Sales_Fact[[#This Row],[Unit_Price3]] -> 1568.16 | P54: =Sales_Fact[[#This Row],[Gross Amount]]*Sales_Fact[[#This Row],[Discount4]] -> 219.5424 | Q54: =IF(Sales_Fact[[#This Row],[Total_Amount5]]>1000,"High Value","Standard") -> High Value
A55: SALE53 | B55: 45677 | C55: CUST1324 | D55: PROD20 | E55: STORE8 | F55: 1 | G55: 900.35 | H55: 0.13 | I55: COD | J55: 783.3045 | K55: =IF(ISBLANK(Sales_Fact[[#This Row],[Quantity]]),MEDIAN(Sales_Fact[Quantity]),Sales_Fact[[#This Row],[Quantity]]) -> 1 | L55: =IF(ISBLANK(Sales_Fact[[#This Row],[Unit_Price]]),MEDIAN(Sales_Fact[Unit_Price]),Sales_Fact[[#This Row],[Unit_Price]]) -> 900.35 | M55: =IF(ISBLANK(Sales_Fact[[#This Row],[Discount]]),MEDIAN(Sales_Fact[Discount]),Sales_Fact[[#This Row],[Discount]]) -> 0.13 | N55: =Sales_Fact[[#This Row],[Quantity2]]*Sales_Fact[[#This Row],[Unit_Price3]]*(1-Sales_Fact[[#This Row],[Discount4]]) -> 783.3045 | O55: =Sales_Fact[[#This Row],[Quantity2]]*Sales_Fact[[#This Row],[Unit_Price3]] -> 900.35 | P55: =Sales_Fact[[#This Row],[Gross Amount]]*Sales_Fact[[#This Row],[Discount4]] -> 117.0455 | Q55: =IF(Sales_Fact[[#This Row],[Total_Amount5]]>1000,"High Value","Standard") -> Standard
A56: SALE54 | B56: 45706 | C56: CUST1095 | D56: PROD40 | E56: STORE10 | F56: 4 | G56: 428.09 | H56: 0.07 | I56: Credit Card | J56: 1592.4948 | K56: =IF(ISBLANK(Sales_Fact[[#This Row],[Quantity]]),MEDIAN(Sales_Fact[Quantity]),Sales_Fact[[#This Row],[Quantity]]) -> 4 | L56: =IF(ISBLANK(Sales_Fact[[#This Row],[Unit_Price]]),MEDIAN(Sales_Fact[Unit_Price]),Sales_Fact[[#This Row],[Unit_Price]]) -> 428.09 | M56: =IF(ISBLANK(Sales_Fact[[#This Row],[Discount]]),MEDIAN(Sales_Fact[Discount]),Sales_Fact[[#This Row],[Discount]]) -> 0.07 | N56: =Sales_Fact[[#This Row],[Quantity2]]*Sales_Fact[[#This Row],[Unit_Price3]]*(1-Sales_Fact[[#This Row],[Discount4]]) -> 1592.4948 | O56: =Sales_Fact[[#This Row],[Quantity2]]*Sales_Fact[[#This Row],[Unit_Price3]] -> 1712.36 | P56: =Sales_Fact[[#This Row],[Gross Amount]]*Sales_Fact[[#This Row],[Discount4]] -> 119.8652 | Q56: =IF(Sales_Fact[[#This Row],[Total_Amount5]]>1000,"High Value","Standard") -> High Value
A57: SALE55 | B57: 45589 | C57: CUST1416 | D57: PROD49 | E57: STORE11 | F57: 2 | G57: 559.71 | H57: 0.3 | I57: COD | J57: 783.594 | K57: =IF(ISBLANK(Sales_Fact[[#This Row],[Quantity]]),MEDIAN(Sales_Fact[Quantity]),Sales_Fact[[#This Row],[Quantity]]) -> 2 | L57: =IF(ISBLANK(Sales_Fact[[#This Row],[Unit_Price]]),MEDIAN(Sales_Fact[Unit_Price]),Sales_Fact[[#This Row],[Unit_Price]]) -> 559.71 | M57: =IF(ISBLANK(Sales_Fact[[#This Row],[Discount]]),MEDIAN(Sales_Fact[Discount]),Sales_Fact[[#This Row],[Discount]]) -> 0.3 | N57: =Sales_Fact[[#This Row],[Quantity2]]*Sales_Fact[[#This Row],[Unit_Price3]]*(1-Sales_Fact[[#This Row],[Discount4]]) -> 783.594 | O57: =Sales_Fact[[#This Row],[Quantity2]]*Sales_Fact[[#This Row],[Unit_Price3]] -> 1119.42 | P57: =Sales_Fact[[#This Row],[Gross Amount]]*Sales_Fact[[#This Row],[Discount4]] -> 335.826 | Q57: =IF(Sales_Fact[[#This Row],[Total_Amount5]]>1000,"High Value","Standard") -> Standard
A58: SALE56 | B58: 45282 | C58: CUST1080 | D58: PROD34 | E58: STORE6 | F58: 2 | G58: 833.7 | H58: 0.06 | I58: PayPal | J58: 1567.356 | K58: =IF(ISBLANK(Sales_Fact[[#This Row],[Quantity]]),MEDIAN(Sales_Fact[Quantity]),Sales_Fact[[#This Row],[Quantity]]) -> 2 | L58: =IF(ISBLANK(Sales_Fact[[#This Row],[Unit_Price]]),MEDIAN(Sales_Fact[Unit_Price]),Sales_Fact[[#This Row],[Unit_Price]]) -> 833.7 | M58: =IF(ISBLANK(Sales_Fact[[#This Row],[Discount]]),MEDIAN(Sales_Fact[Discount]),Sales_Fact[[#This Row],[Discount]]) -> 0.06 | N58: =Sales_Fact[[#This Row],[Quantity2]]*Sales_Fact[[#This Row],[Unit_Price3]]*(1-Sales_Fact[[#This Row],[Discount4]]) -> 1567.356 | O58: =Sales_Fact[[#This Row],[Quantity2]]*Sales_Fact[[#This Row],[Unit_Price3]] -> 1667.4 | P58: =Sales_Fact[[#This Row],[Gross Amount]]*Sales_Fact[[#This Row],[Discount4]] -> 100.044 | Q58: =IF(Sales_Fact[[#This Row],[Total_Amount5]]>1000,"High Value","Standard") -> High Value
A59: SALE57 | B59: 45462 | C59: CUST1467 | D59: PROD47 | E59: STORE14 | F59: 2 | G59: 680.16 | H59: 0.28 | I59: Credit Card | J59: 979.4304 | K59: =IF(ISBLANK(Sales_Fact[[#This Row],[Quantity]]),MEDIAN(Sales_Fact[Quantity]),Sales_Fact[[#This Row],[Quantity]]) -> 2 | L59: =IF(ISBLANK(Sales_Fact[[#This Row],[Unit_Price]]),MEDIAN(Sales_Fact[Unit_Price]),Sales_Fact[[#This Row],[Unit_Price]]) -> 680.16 | M59: =IF(ISBLANK(Sales_Fact[[#This Row],[Discount]]),MEDIAN(Sales_Fact[Discount]),Sales_Fact[[#This Row],[Discount]]) -> 0.28 | N59: =Sales_Fact[[#This Row],[Quantity2]]*Sales_Fact[[#This Row],[Unit_Price3]]*(1-Sales_Fact[[#This Row],[Discount4]]) -> 979.4304 | O59: =Sales_Fact[[#This Row],[Quantity2]]*Sales_Fact[[#This Row],[Unit_Price3]] -> 1360.32 | P59: =Sales_Fact[[#This Row],[Gross Amount]]*Sales_Fact[[#This Row],[Discount4]] -> 380.8896 | Q59: =IF(Sales_Fact[[#This Row],[Total_Amount5]]>1000,"High Value","Standard") -> Standard
A60: SALE58 | B60: 45633 | C60: CUST1404 | D60: PROD15 | E60: STORE7 | F60: 4 | G60: 733.42 | I60: PayPal | J60: 2552.3016 | K60: =IF(ISBLANK(Sales_Fact[[#This Row],[Quantity]]),MEDIAN(Sales_Fact[Quantity]),Sales_Fact[[#This Row],[Quantity]]) -> 4 | L60: =IF(ISBLANK(Sales_Fact[[#This Row],[Unit_Price]]),MEDIAN(Sales_Fact[Unit_Price]),Sales_Fact[[#This Row],[Unit_Price]]) -> 733.42 | M60: =IF(ISBLANK(Sales_Fact[[#This Row],[Discount]]),MEDIAN(Sales_Fact[Discount]),Sales_Fact[[#This Row],[Discount]]) -> 0.14 | N60: =Sales_Fact[[#This Row],[Quantity2]]*Sales_Fact[[#This Row],[Unit_Price3]]*(1-Sales_Fact[[#This Row],[Discount4]]) -> 2522.9648 | O60: =Sales_Fact[[#This Row],[Quantity2]]*Sales_Fact[[#This Row],[Unit_Price3]] -> 2933.68 | P60: =Sales_Fact[[#This Row],[Gross Amount]]*Sales_Fact[[#This Row],[Discount4]] -> 410.7152 | Q60: =IF(Sales_Fact[[#This Row],[Total_Amount5]]>1000,"High Value","Standard") -> High Value
A61: SALE59 | B61: 45257 | C61: CUST1367 | D61: PROD89 | E61: STORE11 | F61: 1 | G61: 996.33 | H61: 0.23 | I61: PayPal | J61: 767.1741 | K61: =IF(ISBLANK(Sales_Fact[[#This Row],[Quantity]]),MEDIAN(Sales_Fact[Quantity]),Sales_Fact[[#This Row],[Quantity]]) -> 1 | L61: =IF(ISBLANK(Sales_Fact[[#This Row],[Unit_Price]]),MEDIAN(Sales_Fact[Unit_Price]),Sales_Fact[[#This Row],[Unit_Price]]) -> 996.33 | M61: =IF(ISBLANK(Sales_Fact[[#This Row],[Discount]]),MEDIAN(Sales_Fact[Discount]),Sales_Fact[[#This Row],[Discount]]) -> 0.23 | N61: =Sales_Fact[[#This Row],[Quantity2]]*Sales_Fact[[#This Row],[Unit_Price3]]*(1-Sales_Fact[[#This Row],[Discount4]]) -> 767.1741 | O61: =Sales_Fact[[#This Row],[Quantity2]]*Sales_Fact[[#This Row],[Unit_Price3]] -> 996.33 | P61: =Sales_Fact[[#This Row],[Gross Amount]]*Sales_Fact[[#This Row],[Discount4]] -> 229.1559 | Q61: =IF(Sales_Fact[[#This Row],[Total_Amount5]]>1000,"High Value","Standard") -> Standard
A62: SALE60 | B62: 45854 | C62: CUST1408 | D62: PROD31 | E62: STORE10 | F62: 1 | G62: 198.83 | H62: 0.09 | I62: COD | J62: 180.9353 | K62: =IF(ISBLANK(Sales_Fact[[#This Row],[Quantity]]),MEDIAN(Sales_Fact[Quantity]),Sales_Fact[[#This Row],[Quantity]]) -> 1 | L62: =IF(ISBLANK(Sales_Fact[[#This Row],[Unit_Price]]),MEDIAN(Sales_Fact[Unit_Price]),Sales_Fact[[#This Row],[Unit_Price]]) -> 198.83 | M62: =IF(ISBLANK(Sales_Fact[[#This Row],[Discount]]),MEDIAN(Sales_Fact[Discount]),Sales_Fact[[#This Row],[Discount]]) -> 0.09 | N62: =Sales_Fact[[#This Row],[Quantity2]]*Sales_Fact[[#This Row],[Unit_Price3]]*(1-Sales_Fact[[#This Row],[Discount4]]) -> 180.9353 | O62: =Sales_Fact[[#This Row],[Quantity2]]*Sales_Fact[[#This Row],[Unit_Price3]] -> 198.83 | P62: =Sales_Fact[[#This Row],[Gross Amount]]*Sales_Fact[[#This Row],[Discount4]] -> 17.8947 | Q62: =IF(Sales_Fact[[#This Row],[Total_Amount5]]>1000,"High Value","Standard") -> Standard
A63: SALE61 | B63: 45716 | C63: CUST1239 | D63: PROD19 | E63: STORE7 | F63: 1 | G63: 374.92 | H63: 0.18 | I63: PayPal | J63: 307.4344 | K63: =IF(ISBLANK(Sales_Fact[[#This Row],[Quantity]]),MEDIAN(Sales_Fact[Quantity]),Sales_Fact[[#This Row],[Quantity]]) -> 1 | L63: =IF(ISBLANK(Sales_Fact[[#This Row],[Unit_Price]]),MEDIAN(Sales_Fact[Unit_Price]),Sales_Fact[[#This Row],[Unit_Price]]) -> 374.92 | M63: =IF(ISBLANK(Sales_Fact[[#This Row],[Discount]]),MEDIAN(Sales_Fact[Discount]),Sales_Fact[[#This Row],[Discount]]) -> 0.18 | N63: =Sales_Fact[[#This Row],[Quantity2]]*Sales_Fact[[#This Row],[Unit_Price3]]*(1-Sales_Fact[[#This Row],[Discount4]]) -> 307.4344 | O63: =Sales_Fact[[#This Row],[Quantity2]]*Sales_Fact[[#This Row],[Unit_Price3]] -> 374.92 | P63: =Sales_Fact[[#This Row],[Gross Amount]]*Sales_Fact[[#This Row],[Discount4]] -> 67.4856 | Q63: =IF(Sales_Fact[[#This Row],[Total_Amount5]]>1000,"High Value","Standard") -> Standard
A64: SALE62 | B64: 45515 | C64: CUST1464 | D64: PROD93 | E64: STORE16 | F64: 1 | G64: 468.94 | H64: 0.12 | I64: Credit Card | J64: 412.6672 | K64: =IF(ISBLANK(Sales_Fact[[#This Row],[Quantity]]),MEDIAN(Sales_Fact[Quantity]),Sales_Fact[[#This Row],[Quantity]]) -> 1 | L64: =IF(ISBLANK(Sales_Fact[[#This Row],[Unit_Price]]),MEDIAN(Sales_Fact[Unit_Price]),Sales_Fact[[#This Row],[Unit_Price]]) -> 468.94 | M64: =IF(ISBLANK(Sales_Fact[[#This Row],[Discount]]),MEDIAN(Sales_Fact[Discount]),Sales_Fact[[#This Row],[Discount]]) -> 0.12 | N64: =Sales_Fact[[#This Row],[Quantity2]]*Sales_Fact[[#This Row],[Unit_Price3]]*(1-Sales_Fact[[#This Row],[Discount4]]) -> 412.6672 | O64: =Sales_Fact[[#This Row],[Quantity2]]*Sales_Fact[[#This Row],[Unit_Price3]] -> 468.94 | P64: =Sales_Fact[[#This Row],[Gross Amount]]*Sales_Fact[[#This Row],[Discount4]] -> 56.2728 | Q64: =IF(Sales_Fact[[#This Row],[Total_Amount5]]>1000,"High Value","Standard") -> Standard
A65: SALE63 | B65: 45927 | C65: CUST1126 | D65: PROD89 | E65: STORE12 | F65: 2 | G65: 121.37 | H65: 0.05 | I65: Credit Card | J65: 230.603 | K65: =IF(ISBLANK(Sales_Fact[[#This Row],[Quantity]]),MEDIAN(Sales_Fact[Quantity]),Sales_Fact[[#This Row],[Quantity]]) -> 2 | L65: =IF(ISBLANK(Sales_Fact[[#This Row],[Unit_Price]]),MEDIAN(Sales_Fact[Unit_Price]),Sales_Fact[[#This Row],[Unit_Price]]) -> 121.37 | M65: =IF(ISBLANK(Sales_Fact[[#This Row],[Discount]]),MEDIAN(Sales_Fact[Discount]),Sales_Fact[[#This Row],[Discount]]) -> 0.05 | N65: =Sales_Fact[[#This Row],[Quantity2]]*Sales_Fact[[#This Row],[Unit_Price3]]*(1-Sales_Fact[[#This Row],[Discount4]]) -> 230.603 | O65: =Sales_Fact[[#This Row],[Quantity2]]*Sales_Fact[[#This Row],[Unit_Price3]] -> 242.74 | P65: =Sales_Fact[[#This Row],[Gross Amount]]*Sales_Fact[[#This Row],[Discount4]] -> 12.137 | Q65: =IF(Sales_Fact[[#This Row],[Total_Amount5]]>1000,"High Value","Standard") -> Standard
A66: SALE64 | B66: 45914 | C66: CUST1255 | D66: PROD53 | E66: STORE10 | F66: 3 | G66: 480.06 | H66: 0.01 | I66: Credit Card | K66: =IF(ISBLANK(Sales_Fact[[#This Row],[Quantity]]),MEDIAN(Sales_Fact[Quantity]),Sales_Fact[[#This Row],[Quantity]]) -> 3 | L66: =IF(ISBLANK(Sales_Fact[[#This Row],[Unit_Price]]),MEDIAN(Sales_Fact[Unit_Price]),Sales_Fact[[#This Row],[Unit_Price]]) -> 480.06 | M66: =IF(ISBLANK(Sales_Fact[[#This Row],[Discount]]),MEDIAN(Sales_Fact[Discount]),Sales_Fact[[#This Row],[Discount]]) -> 0.01 | N66: =Sales_Fact[[#This Row],[Quantity2]]*Sales_Fact[[#This Row],[Unit_Price3]]*(1-Sales_Fact[[#This Row],[Discount4]]) -> 1425.7782 | O66: =Sales_Fact[[#This Row],[Quantity2]]*Sales_Fact[[#This Row],[Unit_Price3]] -> 1440.18 | P66: =Sales_Fact[[#This Row],[Gross Amount]]*Sales_Fact[[#This Row],[Discount4]] -> 14.4018 | Q66: =IF(Sales_Fact[[#This Row],[Total_Amount5]]>1000,"High Value","Standard") -> High Value
A67: SALE65 | B67: 45290 | C67: CUST1162 | D67: PROD99 | E67: STORE17 | F67: 2 | G67: 856.57 | H67: 0.24 | I67: Credit Card | J67: 1301.9864 | K67: =IF(ISBLANK(Sales_Fact[[#This Row],[Quantity]]),MEDIAN(Sales_Fact[Quantity]),Sales_Fact[[#This Row],[Quantity]]) -> 2 | L67: =IF(ISBLANK(Sales_Fact[[#This Row],[Unit_Price]]),MEDIAN(Sales_Fact[Unit_Price]),Sales_Fact[[#This Row],[Unit_Price]]) -> 856.57 | M67: =IF(ISBLANK(Sales_Fact[[#This Row],[Discount]]),MEDIAN(Sales_Fact[Discount]),Sales_Fact[[#This Row],[Discount]]) -> 0.24 | N67: =Sales_Fact[[#This Row],[Quantity2]]*Sales_Fact[[#This Row],[Unit_Price3]]*(1-Sales_Fact[[#This Row],[Discount4]]) -> 1301.9864 | O67: =Sales_Fact[[#This Row],[Quantity2]]*Sales_Fact[[#This Row],[Unit_Price3]] -> 1713.14 | P67: =Sales_Fact[[#This Row],[Gross Amount]]*Sales_Fact[[#This Row],[Discount4]] -> 411.1536 | Q67: =IF(Sales_Fact[[#This Row],[Total_Amount5]]>1000,"High Value","Standard") -> High Value
A68: SALE66 | B68: 45213 | C68: CUST1269 | D68: PROD77 | E68: STORE2 | F68: 4 | G68: 814.25 | H68: 0.18 | I68: Credit Card | J68: 2670.74 | K68: =IF(ISBLANK(Sales_Fact[[#This Row],[Quantity]]),MEDIAN(Sales_Fact[Quantity]),Sales_Fact[[#This Row],[Quantity]]) -> 4 | L68: =IF(ISBLANK(Sales_Fact[[#This Row],[Unit_Price]]),MEDIAN(Sales_Fact[Unit_Price]),Sales_Fact[[#This Row],[Unit_Price]]) -> 814.25 | M68: =IF(ISBLANK(Sales_Fact[[#This Row],[Discount]]),MEDIAN(Sales_Fact[Discount]),Sales_Fact[[#This Row],[Discount]]) -> 0.18 | N68: =Sales_Fact[[#This Row],[Quantity2]]*Sales_Fact[[#This Row],[Unit_Price3]]*(1-Sales_Fact[[#This Row],[Discount4]]) -> 2670.74 | O68: =Sales_Fact[[#This Row],[Quantity2]]*Sales_Fact[[#This Row],[Unit_Price3]] -> 3257 | P68: =Sales_Fact[[#This Row],[Gross Amount]]*Sales_Fact[[#This Row],[Discount4]] -> 586.26 | Q68: =IF(Sales_Fact[[#This Row],[Total_Amount5]]>1000,"High Value","Standard") -> High Value
A69: SALE67 | B69: 45255 | C69: CUST1483 | D69: PROD12 | E69: STORE2 | F69: 1 | G69: 989.17 | H69: 0.2 | I69: PayPal | J69: 791.336 | K69: =IF(ISBLANK(Sales_Fact[[#This Row],[Quantity]]),MEDIAN(Sales_Fact[Quantity]),Sales_Fact[[#This Row],[Quantity]]) -> 1 | L69: =IF(ISBLANK(Sales_Fact[[#This Row],[Unit_Price]]),MEDIAN(Sales_Fact[Unit_Price]),Sales_Fact[[#This Row],[Unit_Price]]) -> 989.17 | M69: =IF(ISBLANK(Sales_Fact[[#This Row],[Discount]]),MEDIAN(Sales_Fact[Discount]),Sales_Fact[[#This Row],[Discount]]) -> 0.2 | N69: =Sales_Fact[[#This Row],[Quantity2]]*Sales_Fact[[#This Row],[Unit_Price3]]*(1-Sales_Fact[[#This Row],[Discount4]]) -> 791.336 | O69: =Sales_Fact[[#This Row],[Quantity2]]*Sales_Fact[[#This Row],[Unit_Price3]] -> 989.17 | P69: =Sales_Fact[[#This Row],[Gross Amount]]*Sales_Fact[[#This Row],[Discount4]] -> 197.834 | Q69: =IF(Sales_Fact[[#This Row],[Total_Amount5]]>1000,"High Value","Standard") -> Standard
A70: SALE68 | B70: 45270 | C70: CUST1372 | D70: PROD72 | E70: STORE10 | F70: 4 | G70: 62.48 | H70: 0.18 | I70: Credit Card | J70: 204.9344 | K70: =IF(ISBLANK(Sales_Fact[[#This Row],[Quantity]]),MEDIAN(Sales_Fact[Quantity]),Sales_Fact[[#This Row],[Quantity]]) -> 4 | L70: =IF(ISBLANK(Sales_Fact[[#This Row],[Unit_Price]]),MEDIAN(Sales_Fact[Unit_Price]),Sales_Fact[[#This Row],[Unit_Price]]) -> 62.48 | M70: =IF(ISBLANK(Sales_Fact[[#This Row],[Discount]]),MEDIAN(Sales_Fact[Discount]),Sales_Fact[[#This Row],[Discount]]) -> 0.18 | N70: =Sales_Fact[[#This Row],[Quantity2]]*Sales_Fact[[#This Row],[Unit_Price3]]*(1-Sales_Fact[[#This Row],[Discount4]]) -> 204.9344 | O70: =Sales_Fact[[#This Row],[Quantity2]]*Sales_Fact[[#This Row],[Unit_Price3]] -> 249.92 | P70: =Sales_Fact[[#This Row],[Gross Amount]]*Sales_Fact[[#This Row],[Discount4]] -> 44.9856 | Q70: =IF(Sales_Fact[[#This Row],[Total_Amount5]]>1000,"High Value","Standard") -> Standard
A71: SALE69 | B71: 45897 | C71: CUST1423 | D71: PROD13 | E71: STORE16 | F71: 4 | G71: 561.24 | H71: 0.24 | I71: Credit Card | J71: 1706.1696 | K71: =IF(ISBLANK(Sales_Fact[[#This Row],[Quantity]]),MEDIAN(Sales_Fact[Quantity]),Sales_Fact[[#This Row],[Quantity]]) -> 4 | L71: =IF(ISBLANK(Sales_Fact[[#This Row],[Unit_Price]]),MEDIAN(Sales_Fact[Unit_Price]),Sales_Fact[[#This Row],[Unit_Price]]) -> 561.24 | M71: =IF(ISBLANK(Sales_Fact[[#This Row],[Discount]]),MEDIAN(Sales_Fact[Discount]),Sales_Fact[[#This Row],[Discount]]) -> 0.24 | N71: =Sales_Fact[[#This Row],[Quantity2]]*Sales_Fact[[#This Row],[Unit_Price3]]*(1-Sales_Fact[[#This Row],[Discount4]]) -> 1706.1696 | O71: =Sales_Fact[[#This Row],[Quantity2]]*Sales_Fact[[#This Row],[Unit_Price3]] -> 2244.96 | P71: =Sales_Fact[[#This Row],[Gross Amount]]*Sales_Fact[[#This Row],[Discount4]] -> 538.7904 | Q71: =IF(Sales_Fact[[#This Row],[Total_Amount5]]>1000,"High Value","Standard") -> High Value
A72: SALE70 | B72: 45849 | C72: CUST1058 | D72: PROD60 | E72: STORE5 | F72: 3 | G72: 92.24 | H72: 0.28 | I72: COD | K72: =IF(ISBLANK(Sales_Fact[[#This Row],[Quantity]]),MEDIAN(Sales_Fact[Quantity]),Sales_Fact[[#This Row],[Quantity]]) -> 3 | L72: =IF(ISBLANK(Sales_Fact[[#This Row],[Unit_Price]]),MEDIAN(Sales_Fact[Unit_Price]),Sales_Fact[[#This Row],[Unit_Price]]) -> 92.24 | M72: =IF(ISBLANK(Sales_Fact[[#This Row],[Discount]]),MEDIAN(Sales_Fact[Discount]),Sales_Fact[[#This Row],[Discount]]) -> 0.28 | N72: =Sales_Fact[[#This Row],[Quantity2]]*Sales_Fact[[#This Row],[Unit_Price3]]*(1-Sales_Fact[[#This Row],[Discount4]]) -> 199.2384 | O72: =Sales_Fact[[#This Row],[Quantity2]]*Sales_Fact[[#This Row],[Unit_Price3]] -> 276.72 | P72: =Sales_Fact[[#This Row],[Gross Amount]]*Sales_Fact[[#This Row],[Discount4]] -> 77.4816 | Q72: =IF(Sales_Fact[[#This Row],[Total_Amount5]]>1000,"High Value","Standard") -> Standard
A73: SALE71 | B73: 45889 | C73: CUST1168 | D73: PROD72 | E73: STORE1 | F73: 2 | G73: 668.3 | H73: 0.07 | I73: Credit Card | J73: 1243.038 | K73: =IF(ISBLANK(Sales_Fact[[#This Row],[Quantity]]),MEDIAN(Sales_Fact[Quantity]),Sales_Fact[[#This Row],[Quantity]]) -> 2 | L73: =IF(ISBLANK(Sales_Fact[[#This Row],[Unit_Price]]),MEDIAN(Sales_Fact[Unit_Price]),Sales_Fact[[#This Row],[Unit_Price]]) -> 668.3 | M73: =IF(ISBLANK(Sales_Fact[[#This Row],[Discount]]),MEDIAN(Sales_Fact[Discount]),Sales_Fact[[#This Row],[Discount]]) -> 0.07 | N73: =Sales_Fact[[#This Row],[Quantity2]]*Sales_Fact[[#This Row],[Unit_Price3]]*(1-Sales_Fact[[#This Row],[Discount4]]) -> 1243.038 | O73: =Sales_Fact[[#This Row],[Quantity2]]*Sales_Fact[[#This Row],[Unit_Price3]] -> 1336.6 | P73: =Sales_Fact[[#This Row],[Gross Amount]]*Sales_Fact[[#This Row],[Discount4]] -> 93.562 | Q73: =IF(Sales_Fact[[#This Row],[Total_Amount5]]>1000,"High Value","Standard") -> High Value
A74: SALE72 | B74: 45533 | C74: CUST1409 | D74: PROD38 | E74: STORE5 | F74: 1 | G74: 553.82 | H74: 0.09 | I74: Credit Card | J74: 503.9762 | K74: =IF(ISBLANK(Sales_Fact[[#This Row],[Quantity]]),MEDIAN(Sales_Fact[Quantity]),Sales_Fact[[#This Row],[Quantity]]) -> 1 | L74: =IF(ISBLANK(Sales_Fact[[#This Row],[Unit_Price]]),MEDIAN(Sales_Fact[Unit_Price]),Sales_Fact[[#This Row],[Unit_Price]]) -> 553.82 | M74: =IF(ISBLANK(Sales_Fact[[#This Row],[Discount]]),MEDIAN(Sales_Fact[Discount]),Sales_Fact[[#This Row],[Discount]]) -> 0.09 | N74: =Sales_Fact[[#This Row],[Quantity2]]*Sales_Fact[[#This Row],[Unit_Price3]]*(1-Sales_Fact[[#This Row],[Discount4]]) -> 503.9762 | O74: =Sales_Fact[[#This Row],[Quantity2]]*Sales_Fact[[#This Row],[Unit_Price3]] -> 553.82 | P74: =Sales_Fact[[#This Row],[Gross Amount]]*Sales_Fact[[#This Row],[Discount4]] -> 49.8438 | Q74: =IF(Sales_Fact[[#This Row],[Total_Amount5]]>1000,"High Value","Standard") -> Standard
A75: SALE73 | B75: 45626 | C75: CUST1037 | D75: PROD45 | E75: STORE11 | F75: 2 | G75: 556.43 | H75: 0.13 | I75: Credit Card | J75: 968.1882 | K75: =IF(ISBLANK(Sales_Fact[[#This Row],[Quantity]]),MEDIAN(Sales_Fact[Quantity]),Sales_Fact[[#This Row],[Quantity]]) -> 2 | L75: =IF(ISBLANK(Sales_Fact[[#This Row],[Unit_Price]]),MEDIAN(Sales_Fact[Unit_Price]),Sales_Fact[[#This Row],[Unit_Price]]) -> 556.43 | M75: =IF(ISBLANK(Sales_Fact[[#This Row],[Discount]]),MEDIAN(Sales_Fact[Discount]),Sales_Fact[[#This Row],[Discount]]) -> 0.13 | N75: =Sales_Fact[[#This Row],[Quantity2]]*Sales_Fact[[#This Row],[Unit_Price3]]*(1-Sales_Fact[[#This Row],[Discount4]]) -> 968.1882 | O75: =Sales_Fact[[#This Row],[Quantity2]]*Sales_Fact[[#This Row],[Unit_Price3]] -> 1112.86 | P75: =Sales_Fact[[#This Row],[Gross Amount]]*Sales_Fact[[#This Row],[Discount4]] -> 144.6718 | Q75: =IF(Sales_Fact[[#This Row],[Total_Amount5]]>1000,"High Value","Standard") -> Standard
A76: SALE74 | B76: 45942 | C76: CUST1273 | D76: PROD20 | E76: STORE8 | F76: 1 | G76: 184.98 | H76: 0.1 | I76: COD | J76: 166.482 | K76: =IF(ISBLANK(Sales_Fact[[#This Row],[Quantity]]),MEDIAN(Sales_Fact[Quantity]),Sales_Fact[[#This Row],[Quantity]]) -> 1 | L76: =IF(ISBLANK(Sales_Fact[[#This Row],[Unit_Price]]),MEDIAN(Sales_Fact[Unit_Price]),Sales_Fact[[#This Row],[Unit_Price]]) -> 184.98 | M76: =IF(ISBLANK(Sales_Fact[[#This Row],[Discount]]),MEDIAN(Sales_Fact[Discount]),Sales_Fact[[#This Row],[Discount]]) -> 0.1 | N76: =Sales_Fact[[#This Row],[Quantity2]]*Sales_Fact[[#This Row],[Unit_Price3]]*(1-Sales_Fact[[#This Row],[Discount4]]) -> 166.482 | O76: =Sales_Fact[[#This Row],[Quantity2]]*Sales_Fact[[#This Row],[Unit_Price3]] -> 184.98 | P76: =Sales_Fact[[#This Row],[Gross Amount]]*Sales_Fact[[#This Row],[Discount4]] -> 18.498 | Q76: =IF(Sales_Fact[[#This Row],[Total_Amount5]]>1000,"High Value","Standard") -> Standard
A77: SALE75 | B77: 45500 | C77: CUST1035 | D77: PROD97 | E77: STORE12 | F77: 4 | G77: 700.18 | H77: 0.23 | I77: Credit Card | J77: 2156.5544 | K77: =IF(ISBLANK(Sales_Fact[[#This Row],[Quantity]]),MEDIAN(Sales_Fact[Quantity]),Sales_Fact[[#This Row],[Quantity]]) -> 4 | L77: =IF(ISBLANK(Sales_Fact[[#This Row],[Unit_Price]]),MEDIAN(Sales_Fact[Unit_Price]),Sales_Fact[[#This Row],[Unit_Price]]) -> 700.18 | M77: =IF(ISBLANK(Sales_Fact[[#This Row],[Discount]]),MEDIAN(Sales_Fact[Discount]),Sales_Fact[[#This Row],[Discount]]) -> 0.23 | N77: =Sales_Fact[[#This Row],[Quantity2]]*Sales_Fact[[#This Row],[Unit_Price3]]*(1-Sales_Fact[[#This Row],[Discount4]]) -> 2156.5544 | O77: =Sales_Fact[[#This Row],[Quantity2]]*Sales_Fact[[#This Row],[Unit_Price3]] -> 2800.72 | P77: =Sales_Fact[[#This Row],[Gross Amount]]*Sales_Fact[[#This Row],[Discount4]] -> 644.1656 | Q77: =IF(Sales_Fact[[#This Row],[Total_Amount5]]>1000,"High Value","Standard") -> High Value
A78: SALE76 | B78: 45285 | C78: CUST1019 | D78: PROD76 | E78: STORE10 | F78: 2 | G78: 686.31 | H78: 0.25 | I78: Credit Card | J78: 1029.465 | K78: =IF(ISBLANK(Sales_Fact[[#This Row],[Quantity]]),MEDIAN(Sales_Fact[Quantity]),Sales_Fact[[#This Row],[Quantity]]) -> 2 | L78: =IF(ISBLANK(Sales_Fact[[#This Row],[Unit_Price]]),MEDIAN(Sales_Fact[Unit_Price]),Sales_Fact[[#This Row],[Unit_Price]]) -> 686.31 | M78: =IF(ISBLANK(Sales_Fact[[#This Row],[Discount]]),MEDIAN(Sales_Fact[Discount]),Sales_Fact[[#This Row],[Discount]]) -> 0.25 | N78: =Sales_Fact[[#This Row],[Quantity2]]*Sales_Fact[[#This Row],[Unit_Price3]]*(1-Sales_Fact[[#This Row],[Discount4]]) -> 1029.465 | O78: =Sales_Fact[[#This Row],[Quantity2]]*Sales_Fact[[#This Row],[Unit_Price3]] -> 1372.62 | P78: =Sales_Fact[[#This Row],[Gross Amount]]*Sales_Fact[[#This Row],[Discount4]] -> 343.155 | Q78: =IF(Sales_Fact[[#This Row],[Total_Amount5]]>1000,"High Value","Standard") -> High Value
A79: SALE77 | B79: 45800 | C79: CUST1007 | D79: PROD67 | E79: STORE15 | F79: 1 | G79: 687.82 | H79: 0.27 | I79: COD | J79: 502.1086 | K79: =IF(ISBLANK(Sales_Fact[[#This Row],[Quantity]]),MEDIAN(Sales_Fact[Quantity]),Sales_Fact[[#This Row],[Quantity]]) -> 1 | L79: =IF(ISBLANK(Sales_Fact[[#This Row],[Unit_Price]]),MEDIAN(Sales_Fact[Unit_Price]),Sales_Fact[[#This Row],[Unit_Price]]) -> 687.82 | M79: =IF(ISBLANK(Sales_Fact[[#This Row],[Discount]]),MEDIAN(Sales_Fact[Discount]),Sales_Fact[[#This Row],[Discount]]) -> 0.27 | N79: =Sales_Fact[[#This Row],[Quantity2]]*Sales_Fact[[#This Row],[Unit_Price3]]*(1-Sales_Fact[[#This Row],[Discount4]]) -> 502.1086 | O79: =Sales_Fact[[#This Row],[Quantity2]]*Sales_Fact[[#This Row],[Unit_Price3]] -> 687.82 | P79: =Sales_Fact[[#This Row],[Gross Amount]]*Sales_Fact[[#This Row],[Discount4]] -> 185.7114 | Q79: =IF(Sales_Fact[[#This Row],[Total_Amount5]]>1000,"High Value","Standard") -> Standard
A80: SALE78 | B80: 45609 | C80: CUST1221 | D80: PROD83 | E80: STORE8 | F80: 2 | G80: 900.55 | H80: 0.16 | I80: Credit Card | J80: 1512.924 | K80: =IF(ISBLANK(Sales_Fact[[#This Row],[Quantity]]),MEDIAN(Sales_Fact[Quantity]),Sales_Fact[[#This Row],[Quantity]]) -> 2 | L80: =IF(ISBLANK(Sales_Fact[[#This Row],[Unit_Price]]),MEDIAN(Sales_Fact[Unit_Price]),Sales_Fact[[#This Row],[Unit_Price]]) -> 900.55 | M80: =IF(ISBLANK(Sales_Fact[[#This Row],[Discount]]),MEDIAN(Sales_Fact[Discount]),Sales_Fact[[#This Row],[Discount]]) -> 0.16 | N80: =Sales_Fact[[#This Row],[Quantity2]]*Sales_Fact[[#This Row],[Unit_Price3]]*(1-Sales_Fact[[#This Row],[Discount4]]) -> 1512.924 | O80: =Sales_Fact[[#This Row],[Quantity2]]*Sales_Fact[[#This Row],[Unit_Price3]] -> 1801.1 | P80: =Sales_Fact[[#This Row],[Gross Amount]]*Sales_Fact[[#This Row],[Discount4]] -> 288.176 | Q80: =IF(Sales_Fact[[#This Row],[Total_Amount5]]>1000,"High Value","Standard") -> High Value
A81: SALE79 | B81: 45268 | C81: CUST1115 | D81: PROD21 | E81: STORE2 | F81: 1 | G81: 341.17 | H81: 0.15 | I81: Credit Card | J81: 289.9945 | K81: =IF(ISBLANK(Sales_Fact[[#This Row],[Quantity]]),MEDIAN(Sales_Fact[Quantity]),Sales_Fact[[#This Row],[Quantity]]) -> 1 | L81: =IF(ISBLANK(Sales_Fact[[#This Row],[Unit_Price]]),MEDIAN(Sales_Fact[Unit_Price]),Sales_Fact[[#This Row],[Unit_Price]]) -> 341.17 | M81: =IF(ISBLANK(Sales_Fact[[#This Row],[Discount]]),MEDIAN(Sales_Fact[Discount]),Sales_Fact[[#This Row],[Discount]]) -> 0.15 | N81: =Sales_Fact[[#This Row],[Quantity2]]*Sales_Fact[[#This Row],[Unit_Price3]]*(1-Sales_Fact[[#This Row],[Discount4]]) -> 289.9945 | O81: =Sales_Fact[[#This Row],[Quantity2]]*Sales_Fact[[#This Row],[Unit_Price3]] -> 341.17 | P81: =Sales_Fact[[#This Row],[Gross Amount]]*Sales_Fact[[#This Row],[Discount4]] -> 51.1755 | Q81: =IF(Sales_Fact[[#This Row],[Total_Amount5]]>1000,"High Value","Standard") -> Standard
A82: SALE80 | B82: 45885 | C82: CUST1176 | D82: PROD52 | E82: STORE8 | F82: 1 | G82: 442.27 | H82: 0.06 | I82: COD | J82: 415.7338 | K82: =IF(ISBLANK(Sales_Fact[[#This Row],[Quantity]]),MEDIAN(Sales_Fact[Quantity]),Sales_Fact[[#This Row],[Quantity]]) -> 1 | L82: =IF(ISBLANK(Sales_Fact[[#This Row],[Unit_Price]]),MEDIAN(Sales_Fact[Unit_Price]),Sales_Fact[[#This Row],[Unit_Price]]) -> 442.27 | M82: =IF(ISBLANK(Sales_Fact[[#This Row],[Discount]]),MEDIAN(Sales_Fact[Discount]),Sales_Fact[[#This Row],[Discount]]) -> 0.06 | N82: =Sales_Fact[[#This Row],[Quantity2]]*Sales_Fact[[#This Row],[Unit_Price3]]*(1-Sales_Fact[[#This Row],[Discount4]]) -> 415.7338 | O82: =Sales_Fact[[#This Row],[Quantity2]]*Sales_Fact[[#This Row],[Unit_Price3]] -> 442.27 | P82: =Sales_Fact[[#This Row],[Gross Amount]]*Sales_Fact[[#This Row],[Discount4]] -> 26.5362 | Q82: =IF(Sales_Fact[[#This Row],[Total_Amount5]]>1000,"High Value","Standard") -> Standard
A83: SALE81 | B83: 45616 | C83: CUST1253 | D83: PROD71 | E83: STORE9 | F83: 1 | G83: 363.73 | H83: 0.25 | I83: PayPal | J83: 272.7975 | K83: =IF(ISBLANK(Sales_Fact[[#This Row],[Quantity]]),MEDIAN(Sales_Fact[Quantity]),Sales_Fact[[#This Row],[Quantity]]) -> 1 | L83: =IF(ISBLANK(Sales_Fact[[#This Row],[Unit_Price]]),MEDIAN(Sales_Fact[Unit_Price]),Sales_Fact[[#This Row],[Unit_Price]]) -> 363.73 | M83: =IF(ISBLANK(Sales_Fact[[#This Row],[Discount]]),MEDIAN(Sales_Fact[Discount]),Sales_Fact[[#This Row],[Discount]]) -> 0.25 | N83: =Sales_Fact[[#This Row],[Quantity2]]*Sales_Fact[[#This Row],[Unit_Price3]]*(1-Sales_Fact[[#This Row],[Discount4]]) -> 272.7975 | O83: =Sales_Fact[[#This Row],[Quantity2]]*Sales_Fact[[#This Row],[Unit_Price3]] -> 363.73 | P83: =Sales_Fact[[#This Row],[Gross Amount]]*Sales_Fact[[#This Row],[Discount4]] -> 90.9325 | Q83: =IF(Sales_Fact[[#This Row],[Total_Amount5]]>1000,"High Value","Standard") -> Standard
A84: SALE82 | B84: 45518 | C84: CUST1378 | D84: PROD91 | E84: STORE17 | F84: 2 | G84: 601.33 | H84: 0.16 | I84: PayPal | J84: 1010.2344 | K84: =IF(ISBLANK(Sales_Fact[[#This Row],[Quantity]]),MEDIAN(Sales_Fact[Quantity]),Sales_Fact[[#This Row],[Quantity]]) -> 2 | L84: =IF(ISBLANK(Sales_Fact[[#This Row],[Unit_Price]]),MEDIAN(Sales_Fact[Unit_Price]),Sales_Fact[[#This Row],[Unit_Price]]) -> 601.33 | M84: =IF(ISBLANK(Sales_Fact[[#This Row],[Discount]]),MEDIAN(Sales_Fact[Discount]),Sales_Fact[[#This Row],[Discount]]) -> 0.16 | N84: =Sales_Fact[[#This Row],[Quantity2]]*Sales_Fact[[#This Row],[Unit_Price3]]*(1-Sales_Fact[[#This Row],[Discount4]]) -> 1010.2344 | O84: =Sales_Fact[[#This Row],[Quantity2]]*Sales_Fact[[#This Row],[Unit_Price3]] -> 1202.66 | P84: =Sales_Fact[[#This Row],[Gross Amount]]*Sales_Fact[[#This Row],[Discount4]] -> 192.4256 | Q84: =IF(Sales_Fact[[#This Row],[Total_Amount5]]>1000,"High Value","Standard") -> High Value
A85: SALE83 | B85: 45427 | C85: CUST1403 | D85: PROD17 | E85: STORE18 | F85: 4 | G85: 34.39 | H85: 0.03 | I85: PayPal | J85: 133.4332 | K85: =IF(ISBLANK(Sales_Fact[[#This Row],[Quantity]]),MEDIAN(Sales_Fact[Quantity]),Sales_Fact[[#This Row],[Quantity]]) -> 4 | L85: =IF(ISBLANK(Sales_Fact[[#This Row],[Unit_Price]]),MEDIAN(Sales_Fact[Unit_Price]),Sales_Fact[[#This Row],[Unit_Price]]) -> 34.39 | M85: =IF(ISBLANK(Sales_Fact[[#This Row],[Discount]]),MEDIAN(Sales_Fact[Discount]),Sales_Fact[[#This Row],[Discount]]) -> 0.03 | N85: =Sales_Fact[[#This Row],[Quantity2]]*Sales_Fact[[#This Row],[Unit_Price3]]*(1-Sales_Fact[[#This Row],[Discount4]]) -> 133.4332 | O85: =Sales_Fact[[#This Row],[Quantity2]]*Sales_Fact[[#This Row],[Unit_Price3]] -> 137.56 | P85: =Sales_Fact[[#This Row],[Gross Amount]]*Sales_Fact[[#This Row],[Discount4]] -> 4.1268 | Q85: =IF(Sales_Fact[[#This Row],[Total_Amount5]]>1000,"High Value","Standard") -> Standard
A86: SALE84 | B86: 45268 | C86: CUST1423 | D86: PROD46 | E86: STORE17 | F86: 1 | G86: 773.57 | H86: 0.05 | I86: COD | K86: =IF(ISBLANK(Sales_Fact[[#This Row],[Quantity]]),MEDIAN(Sales_Fact[Quantity]),Sales_Fact[[#This Row],[Quantity]]) -> 1 | L86: =IF(ISBLANK(Sales_Fact[[#This Row],[Unit_Price]]),MEDIAN(Sales_Fact[Unit_Price]),Sales_Fact[[#This Row],[Unit_Price]]) -> 773.57 | M86: =IF(ISBLANK(Sales_Fact[[#This Row],[Discount]]),MEDIAN(Sales_Fact[Discount]),Sales_Fact[[#This Row],[Discount]]) -> 0.05 | N86: =Sales_Fact[[#This Row],[Quantity2]]*Sales_Fact[[#This Row],[Unit_Price3]]*(1-Sales_Fact[[#This Row],[Discount4]]) -> 734.8915 | O86: =Sales_Fact[[#This Row],[Quantity2]]*Sales_Fact[[#This Row],[Unit_Price3]] -> 773.57 | P86: =Sales_Fact[[#This Row],[Gross Amount]]*Sales_Fact[[#This Row],[Discount4]] -> 38.6785 | Q86: =IF(Sales_Fact[[#This Row],[Total_Amount5]]>1000,"High Value","Standard") -> Standard
A87: SALE85 | B87: 45282 | C87: CUST1054 | D87: PROD88 | E87: STORE7 | F87: 4 | G87: 127.1 | H87: 0.24 | I87: COD | J87: 386.384 | K87: =IF(ISBLANK(Sales_Fact[[#This Row],[Quantity]]),MEDIAN(Sales_Fact[Quantity]),Sales_Fact[[#This Row],[Quantity]]) -> 4 | L87: =IF(ISBLANK(Sales_Fact[[#This Row],[Unit_Price]]),MEDIAN(Sales_Fact[Unit_Price]),Sales_Fact[[#This Row],[Unit_Price]]) -> 127.1 | M87: =IF(ISBLANK(Sales_Fact[[#This Row],[Discount]]),MEDIAN(Sales_Fact[Discount]),Sales_Fact[[#This Row],[Discount]]) -> 0.24 | N87: =Sales_Fact[[#This Row],[Quantity2]]*Sales_Fact[[#This Row],[Unit_Price3]]*(1-Sales_Fact[[#This Row],[Discount4]]) -> 386.384 | O87: =Sales_Fact[[#This Row],[Quantity2]]*Sales_Fact[[#This Row],[Unit_Price3]] -> 508.4 | P87: =Sales_Fact[[#This Row],[Gross Amount]]*Sales_Fact[[#This Row],[Discount4]] -> 122.016 | Q87: =IF(Sales_Fact[[#This Row],[Total_Amount5]]>1000,"High Value","Standard") -> Standard
A88: SALE86 | B88: 45545 | C88: CUST1303 | D88: PROD20 | E88: STORE3 | F88: 3 | G88: 899.58 | H88: 0.28 | I88: PayPal | J88: 1943.0928 | K88: =IF(ISBLANK(Sales_Fact[[#This Row],[Quantity]]),MEDIAN(Sales_Fact[Quantity]),Sales_Fact[[#This Row],[Quantity]]) -> 3 | L88: =IF(ISBLANK(Sales_Fact[[#This Row],[Unit_Price]]),MEDIAN(Sales_Fact[Unit_Price]),Sales_Fact[[#This Row],[Unit_Price]]) -> 899.58 | M88: =IF(ISBLANK(Sales_Fact[[#This Row],[Discount]]),MEDIAN(Sales_Fact[Discount]),Sales_Fact[[#This Row],[Discount]]) -> 0.28 | N88: =Sales_Fact[[#This Row],[Quantity2]]*Sales_Fact[[#This Row],[Unit_Price3]]*(1-Sales_Fact[[#This Row],[Discount4]]) -> 1943.0928 | O88: =Sales_Fact[[#This Row],[Quantity2]]*Sales_Fact[[#This Row],[Unit_Price3]] -> 2698.74 | P88: =Sales_Fact[[#This Row],[Gross Amount]]*Sales_Fact[[#This Row],[Discount4]] -> 755.6472 | Q88: =IF(Sales_Fact[[#This Row],[Total_Amount5]]>1000,"High Value","Standard") -> High Value
A89: SALE87 | B89: 45755 | C89: CUST1327 | D89: PROD1 | E89: STORE10 | F89: 3 | G89: 964.39 | H89: 0.04 | I89: Credit Card | J89: 2777.4432 | K89: =IF(ISBLANK(Sales_Fact[[#This Row],[Quantity]]),MEDIAN(Sales_Fact[Quantity]),Sales_Fact[[#This Row],[Quantity]]) -> 3 | L89: =IF(ISBLANK(Sales_Fact[[#This Row],[Unit_Price]]),MEDIAN(Sales_Fact[Unit_Price]),Sales_Fact[[#This Row],[Unit_Price]]) -> 964.39 | M89: =IF(ISBLANK(Sales_Fact[[#This Row],[Discount]]),MEDIAN(Sales_Fact[Discount]),Sales_Fact[[#This Row],[Discount]]) -> 0.04 | N89: =Sales_Fact[[#This Row],[Quantity2]]*Sales_Fact[[#This Row],[Unit_Price3]]*(1-Sales_Fact[[#This Row],[Discount4]]) -> 2777.4432 | O89: =Sales_Fact[[#This Row],[Quantity2]]*Sales_Fact[[#This Row],[Unit_Price3]] -> 2893.17 | P89: =Sales_Fact[[#This Row],[Gross Amount]]*Sales_Fact[[#This Row],[Discount4]] -> 115.7268 | Q89: =IF(Sales_Fact[[#This Row],[Total_Amount5]]>1000,"High Value","Standard") -> High Value
A90: SALE88 | B90: 45588 | C90: CUST1183 | D90: PROD38 | E90: STORE0 | F90: 2 | G90: 217.83 | H90: 0.14 | I90: PayPal | J90: 374.6676 | K90: =IF(ISBLANK(Sales_Fact[[#This Row],[Quantity]]),MEDIAN(Sales_Fact[Quantity]),Sales_Fact[[#This Row],[Quantity]]) -> 2 | L90: =IF(ISBLANK(Sales_Fact[[#This Row],[Unit_Price]]),MEDIAN(Sales_Fact[Unit_Price]),Sales_Fact[[#This Row],[Unit_Price]]) -> 217.83 | M90: =IF(ISBLANK(Sales_Fact[[#This Row],[Discount]]),MEDIAN(Sales_Fact[Discount]),Sales_Fact[[#This Row],[Discount]]) -> 0.14 | N90: =Sales_Fact[[#This Row],[Quantity2]]*Sales_Fact[[#This Row],[Unit_Price3]]*(1-Sales_Fact[[#This Row],[Discount4]]) -> 374.6676 | O90: =Sales_Fact[[#This Row],[Quantity2]]*Sales_Fact[[#This Row],[Unit_Price3]] -> 435.66 | P90: =Sales_Fact[[#This Row],[Gross Amount]]*Sales_Fact[[#This Row],[Discount4]] -> 60.9924 | Q90: =IF(Sales_Fact[[#This Row],[Total_Amount5]]>1000,"High Value","Standard") -> Standard
A91: SALE89 | B91: 45848 | C91: CUST1143 | D91: PROD17 | E91: STORE1 | F91: 4 | G91: 187.71 | H91: 0.06 | I91: COD | J91: 705.7896 | K91: =IF(ISBLANK(Sales_Fact[[#This Row],[Quantity]]),MEDIAN(Sales_Fact[Quantity]),Sales_Fact[[#This Row],[Quantity]]) -> 4 | L91: =IF(ISBLANK(Sales_Fact[[#This Row],[Unit_Price]]),MEDIAN(Sales_Fact[Unit_Price]),Sales_Fact[[#This Row],[Unit_Price]]) -> 187.71 | M91: =IF(ISBLANK(Sales_Fact[[#This Row],[Discount]]),MEDIAN(Sales_Fact[Discount]),Sales_Fact[[#This Row],[Discount]]) -> 0.06 | N91: =Sales_Fact[[#This Row],[Quantity2]]*Sales_Fact[[#This Row],[Unit_Price3]]*(1-Sales_Fact[[#This Row],[Discount4]]) -> 705.7896 | O91: =Sales_Fact[[#This Row],[Quantity2]]*Sales_Fact[[#This Row],[Unit_Price3]] -> 750.84 | P91: =Sales_Fact[[#This Row],[Gross Amount]]*Sales_Fact[[#This Row],[Discount4]] -> 45.0504 | Q91: =IF(Sales_Fact[[#This Row],[Total_Amount5]]>1000,"High Value","Standard") -> Standard
A92: SALE90 | B92: 45577 | C92: CUST1010 | D92: PROD33 | E92: STORE18 | F92: 2 | G92: 350.12 | H92: 0.12 | I92: COD | J92: 616.2112 | K92: =IF(ISBLANK(Sales_Fact[[#This Row],[Quantity]]),MEDIAN(Sales_Fact[Quantity]),Sales_Fact[[#This Row],[Quantity]]) -> 2 | L92: =IF(ISBLANK(Sales_Fact[[#This Row],[Unit_Price]]),MEDIAN(Sales_Fact[Unit_Price]),Sales_Fact[[#This Row],[Unit_Price]]) -> 350.12 | M92: =IF(ISBLANK(Sales_Fact[[#This Row],[Discount]]),MEDIAN(Sales_Fact[Discount]),Sales_Fact[[#This Row],[Discount]]) -> 0.12 | N92: =Sales_Fact[[#This Row],[Quantity2]]*Sales_Fact[[#This Row],[Unit_Price3]]*(1-Sales_Fact[[#This Row],[Discount4]]) -> 616.2112 | O92: =Sales_Fact[[#This Row],[Quantity2]]*Sales_Fact[[#This Row],[Unit_Price3]] -> 700.24 | P92: =Sales_Fact[[#This Row],[Gross Amount]]*Sales_Fact[[#This Row],[Discount4]] -> 84.0288 | Q92: =IF(Sales_Fact[[#This Row],[Total_Amount5]]>1000,"High Value","Standard") -> Standard
A93: SALE91 | B93: 45312 | C93: CUST1406 | D93: PROD16 | E93: STORE1 | F93: 4 | G93: 102.19 | H93: 0.17 | I93: PayPal | J93: 339.2708 | K93: =IF(ISBLANK(Sales_Fact[[#This Row],[Quantity]]),MEDIAN(Sales_Fact[Quantity]),Sales_Fact[[#This Row],[Quantity]]) -> 4 | L93: =IF(ISBLANK(Sales_Fact[[#This Row],[Unit_Price]]),MEDIAN(Sales_Fact[Unit_Price]),Sales_Fact[[#This Row],[Unit_Price]]) -> 102.19 | M93: =IF(ISBLANK(Sales_Fact[[#This Row],[Discount]]),MEDIAN(Sales_Fact[Discount]),Sales_Fact[[#This Row],[Discount]]) -> 0.17 | N93: =Sales_Fact[[#This Row],[Quantity2]]*Sales_Fact[[#This Row],[Unit_Price3]]*(1-Sales_Fact[[#This Row],[Discount4]]) -> 339.2708 | O93: =Sales_Fact[[#This Row],[Quantity2]]*Sales_Fact[[#This Row],[Unit_Price3]] -> 408.76 | P93: =Sales_Fact[[#This Row],[Gross Amount]]*Sales_Fact[[#This Row],[Discount4]] -> 69.4892 | Q93: =IF(Sales_Fact[[#This Row],[Total_Amount5]]>1000,"High Value","Standard") -> Standard
A94: SALE92 | B94: 45350 | C94: CUST1007 | D94: PROD86 | E94: STORE4 | F94: 1 | G94: 696.53 | H94: 0.17 | I94: Credit Card | J94: 578.1199 | K94: =IF(ISBLANK(Sales_Fact[[#This Row],[Quantity]]),MEDIAN(Sales_Fact[Quantity]),Sales_Fact[[#This Row],[Quantity]]) -> 1 | L94: =IF(ISBLANK(Sales_Fact[[#This Row],[Unit_Price]]),MEDIAN(Sales_Fact[Unit_Price]),Sales_Fact[[#This Row],[Unit_Price]]) -> 696.53 | M94: =IF(ISBLANK(Sales_Fact[[#This Row],[Discount]]),MEDIAN(Sales_Fact[Discount]),Sales_Fact[[#This Row],[Discount]]) -> 0.17 | N94: =Sales_Fact[[#This Row],[Quantity2]]*Sales_Fact[[#This Row],[Unit_Price3]]*(1-Sales_Fact[[#This Row],[Discount4]]) -> 578.1199 | O94: =Sales_Fact[[#This Row],[Quantity2]]*Sales_Fact[[#This Row],[Unit_Price3]] -> 696.53 | P94: =Sales_Fact[[#This Row],[Gross Amount]]*Sales_Fact[[#This Row],[Discount4]] -> 118.4101 | Q94: =IF(Sales_Fact[[#This Row],[Total_Amount5]]>1000,"High Value","Standard") -> Standard
A95: SALE93 | B95: 45657 | C95: CUST1065 | D95: PROD19 | E95: STORE4 | F95: 2 | G95: 327.52 | H95: 0.15 | I95: PayPal | J95: 556.784 | K95: =IF(ISBLANK(Sales_Fact[[#This Row],[Quantity]]),MEDIAN(Sales_Fact[Quantity]),Sales_Fact[[#This Row],[Quantity]]) -> 2 | L95: =IF(ISBLANK(Sales_Fact[[#This Row],[Unit_Price]]),MEDIAN(Sales_Fact[Unit_Price]),Sales_Fact[[#This Row],[Unit_Price]]) -> 327.52 | M95: =IF(ISBLANK(Sales_Fact[[#This Row],[Discount]]),MEDIAN(Sales_Fact[Discount]),Sales_Fact[[#This Row],[Discount]]) -> 0.15 | N95: =Sales_Fact[[#This Row],[Quantity2]]*Sales_Fact[[#This Row],[Unit_Price3]]*(1-Sales_Fact[[#This Row],[Discount4]]) -> 556.784 | O95: =Sales_Fact[[#This Row],[Quantity2]]*Sales_Fact[[#This Row],[Unit_Price3]] -> 655.04 | P95: =Sales_Fact[[#This Row],[Gross Amount]]*Sales_Fact[[#This Row],[Discount4]] -> 98.256 | Q95: =IF(Sales_Fact[[#This Row],[Total_Amount5]]>1000,"High Value","Standard") -> Standard
A96: SALE94 | B96: 45530 | C96: CUST1298 | D96: PROD97 | E96: STORE19 | F96: 2 | G96: 569.36 | H96: 0.01 | I96: PayPal | K96: =IF(ISBLANK(Sales_Fact[[#This Row],[Quantity]]),MEDIAN(Sales_Fact[Quantity]),Sales_Fact[[#This Row],[Quantity]]) -> 2 | L96: =IF(ISBLANK(Sales_Fact[[#This Row],[Unit_Price]]),MEDIAN(Sales_Fact[Unit_Price]),Sales_Fact[[#This Row],[Unit_Price]]) -> 569.36 | M96: =IF(ISBLANK(Sales_Fact[[#This Row],[Discount]]),MEDIAN(Sales_Fact[Discount]),Sales_Fact[[#This Row],[Discount]]) -> 0.01 | N96: =Sales_Fact[[#This Row],[Quantity2]]*Sales_Fact[[#This Row],[Unit_Price3]]*(1-Sales_Fact[[#This Row],[Discount4]]) -> 1127.3328 | O96: =Sales_Fact[[#This Row],[Quantity2]]*Sales_Fact[[#This Row],[Unit_Price3]] -> 1138.72 | P96: =Sales_Fact[[#This Row],[Gross Amount]]*Sales_Fact[[#This Row],[Discount4]] -> 11.3872 | Q96: =IF(Sales_Fact[[#This Row],[Total_Amount5]]>1000,"High Value","Standard") -> High Value
A97: SALE95 | B97: 45556 | C97: CUST1321 | D97: PROD99 | E97: STORE6 | F97: 2 | G97: 68.29 | H97: 0.14 | I97: COD | J97: 117.4588 | K97: =IF(ISBLANK(Sales_Fact[[#This Row],[Quantity]]),MEDIAN(Sales_Fact[Quantity]),Sales_Fact[[#This Row],[Quantity]]) -> 2 | L97: =IF(ISBLANK(Sales_Fact[[#This Row],[Unit_Price]]),MEDIAN(Sales_Fact[Unit_Price]),Sales_Fact[[#This Row],[Unit_Price]]) -> 68.29 | M97: =IF(ISBLANK(Sales_Fact[[#This Row],[Discount]]),MEDIAN(Sales_Fact[Discount]),Sales_Fact[[#This Row],[Discount]]) -> 0.14 | N97: =Sales_Fact[[#This Row],[Quantity2]]*Sales_Fact[[#This Row],[Unit_Price3]]*(1-Sales_Fact[[#This Row],[Discount4]]) -> 117.4588 | O97: =Sales_Fact[[#This Row],[Quantity2]]*Sales_Fact[[#This Row],[Unit_Price3]] -> 136.58 | P97: =Sales_Fact[[#This Row],[Gross Amount]]*Sales_Fact[[#This Row],[Discount4]] -> 19.1212 | Q97: =IF(Sales_Fact[[#This Row],[Total_Amount5]]>1000,"High Value","Standard") -> Standard
A98: SALE96 | B98: 45523 | C98: CUST1244 | D98: PROD50 | E98: STORE10 | F98: 1 | G98: 842.9 | H98: 0.06 | I98: COD | J98: 792.326 | K98: =IF(ISBLANK(Sales_Fact[[#This Row],[Quantity]]),MEDIAN(Sales_Fact[Quantity]),Sales_Fact[[#This Row],[Quantity]]) -> 1 | L98: =IF(ISBLANK(Sales_Fact[[#This Row],[Unit_Price]]),MEDIAN(Sales_Fact[Unit_Price]),Sales_Fact[[#This Row],[Unit_Price]]) -> 842.9 | M98: =IF(ISBLANK(Sales_Fact[[#This Row],[Discount]]),MEDIAN(Sales_Fact[Discount]),Sales_Fact[[#This Row],[Discount]]) -> 0.06 | N98: =Sales_Fact[[#This Row],[Quantity2]]*Sales_Fact[[#This Row],[Unit_Price3]]*(1-Sales_Fact[[#This Row],[Discount4]]) -> 792.326 | O98: =Sales_Fact[[#This Row],[Quantity2]]*Sales_Fact[[#This Row],[Unit_Price3]] -> 842.9 | P98: =Sales_Fact[[#This Row],[Gross Amount]]*Sales_Fact[[#This Row],[Discount4]] -> 50.574 | Q98: =IF(Sales_Fact[[#This Row],[Total_Amount5]]>1000,"High Value","Standard") -> Standard
A99: SALE97 | B99: 45587 | C99: CUST1287 | D99: PROD3 | E99: STORE3 | F99: 3 | G99: 751.94 | H99: 0.26 | I99: PayPal | J99: 1669.3068 | K99: =IF(ISBLANK(Sales_Fact[[#This Row],[Quantity]]),MEDIAN(Sales_Fact[Quantity]),Sales_Fact[[#This Row],[Quantity]]) -> 3 | L99: =IF(ISBLANK(Sales_Fact[[#This Row],[Unit_Price]]),MEDIAN(Sales_Fact[Unit_Price]),Sales_Fact[[#This Row],[Unit_Price]]) -> 751.94 | M99: =IF(ISBLANK(Sales_Fact[[#This Row],[Discount]]),MEDIAN(Sales_Fact[Discount]),Sales_Fact[[#This Row],[Discount]]) -> 0.26 | N99: =Sales_Fact[[#This Row],[Quantity2]]*Sales_Fact[[#This Row],[Unit_Price3]]*(1-Sales_Fact[[#This Row],[Discount4]]) -> 1669.3068 | O99: =Sales_Fact[[#This Row],[Quantity2]]*Sales_Fact[[#This Row],[Unit_Price3]] -> 2255.82 | P99: =Sales_Fact[[#This Row],[Gross Amount]]*Sales_Fact[[#This Row],[Discount4]] -> 586.5132 | Q99: =IF(Sales_Fact[[#This Row],[Total_Amount5]]>1000,"High Value","Standard") -> High Value
A100: SALE98 | B100: 45580 | C100: CUST1131 | D100: PROD56 | E100: STORE7 | F100: 4 | G100: 476.28 | H100: 0.17 | I100: Credit Card | J100: 1581.2496 | K100: =IF(ISBLANK(Sales_Fact[[#This Row],[Quantity]]),MEDIAN(Sales_Fact[Quantity]),Sales_Fact[[#This Row],[Quantity]]) -> 4 | L100: =IF(ISBLANK(Sales_Fact[[#This Row],[Unit_Price]]),MEDIAN(Sales_Fact[Unit_Price]),Sales_Fact[[#This Row],[Unit_Price]]) -> 476.28 | M100: =IF(ISBLANK(Sales_Fact[[#This Row],[Discount]]),MEDIAN(Sales_Fact[Discount]),Sales_Fact[[#This Row],[Discount]]) -> 0.17 | N100: =Sales_Fact[[#This Row],[Quantity2]]*Sales_Fact[[#This Row],[Unit_Price3]]*(1-Sales_Fact[[#This Row],[Discount4]]) -> 1581.2496 | O100: =Sales_Fact[[#This Row],[Quantity2]]*Sales_Fact[[#This Row],[Unit_Price3]] -> 1905.12 | P100: =Sales_Fact[[#This Row],[Gross Amount]]*Sales_Fact[[#This Row],[Discount4]] -> 323.8704 | Q100: =IF(Sales_Fact[[#This Row],[Total_Amount5]]>1000,"High Value","Standard") -> High Value
...

Sheet Store_Dim
A1: Store_ID | B1: Store_Name | C1: Region | D1: City | E1: Store_Type | F1: Region_Storetype
A2: STORE0 | B2: Rivera-Warner | C2: East | D2: Washingtonfurt | E2: Flagship | F2: =Store_Dim[[#This Row],[Region]]&" - "&Store_Dim[[#This Row],[Store_Type]] -> East - Flagship
A3: STORE1 | B3: Martinez, Adkins and Johnson | C3: North | D3: Danielmouth | E3: Flagship | F3: =Store_Dim[[#This Row],[Region]]&" - "&Store_Dim[[#This Row],[Store_Type]] -> North - Flagship
A4: STORE2 | B4: Black-Horn | C4: South | D4: North Nancyview | E4: Outlet | F4: =Store_Dim[[#This Row],[Region]]&" - "&Store_Dim[[#This Row],[Store_Type]] -> South - Outlet
A5: STORE3 | B5: Johnson-Wright | C5: North | D5: Hoodberg | E5: Outlet | F5: =Store_Dim[[#This Row],[Region]]&" - "&Store_Dim[[#This Row],[Store_Type]] -> North - Outlet
A6: STORE4 | B6: Alexander Group | C6: South | D6: Port Sharon | E6: Online | F6: =Store_Dim[[#This Row],[Region]]&" - "&Store_Dim[[#This Row],[Store_Type]] -> South - Online
A7: STORE5 | B7: Gray Ltd | C7: North | D7: New Michaelchester | E7: Outlet | F7: =Store_Dim[[#This Row],[Region]]&" - "&Store_Dim[[#This Row],[Store_Type]] -> North - Outlet
A8: STORE6 | B8: Benson-Elliott | C8: East | D8: Port Josephberg | E8: Online | F8: =Store_Dim[[#This Row],[Region]]&" - "&Store_Dim[[#This Row],[Store_Type]] -> East - Online
A9: STORE7 | B9: Martinez-Mullins | C9: South | D9: Williamsfurt | E9: Online | F9: =Store_Dim[[#This Row],[Region]]&" - "&Store_Dim[[#This Row],[Store_Type]] -> South - Online
A10: STORE8 | B10: Bean, Jones and Park | C10: West | D10: Thompsonborough | E10: Online | F10: =Store_Dim[[#This Row],[Region]]&" - "&Store_Dim[[#This Row],[Store_Type]] -> West - Online
A11: STORE9 | B11: Moore, Padilla and Butler | C11: South | D11: East Johnstad | E11: Flagship | F11: =Store_Dim[[#This Row],[Region]]&" - "&Store_Dim[[#This Row],[Store_Type]] -> South - Flagship
A12: STORE10 | B12: Hill, Wagner and Ballard | C12: East | D12: East Davidville | E12: Online | F12: =Store_Dim[[#This Row],[Region]]&" - "&Store_Dim[[#This Row],[Store_Type]] -> East - Online
A13: STORE11 | B13: Aguirre-Keller | C13: South | D13: Lake Michael | E13: Online | F13: =Store_Dim[[#This Row],[Region]]&" - "&Store_Dim[[#This Row],[Store_Type]] -> South - Online
... A21: STORE19 | B21: Mann-Austin | C21: East | D21: Vasquezborough | E21: Online | F21: =Store_Dim[[#This Row],[Region]]&" - "&Store_Dim[[#This Row],[Store_Type]] -> East - Online

Sheet Customer_Dim
A1: Customer_ID | B1: Name | C1: Age | D1: Gender | E1: City | F1: State | G1: Country | H1: Loyalty_Level | I1: Loyalty_Level2 | J1: Name2 | K1: City2 | L1: Age Group | M1: =COUNTBLANK(Customer_Dim[Loyalty_Level]) -> 4
A2: CUST1000 | B2: sheena bonilla | C2: 55 | D2: Male | E2: Donaldton | F2: North Carolina | G2: USA | I2: =IF(ISBLANK(Customer_Dim[[#This Row],[Loyalty_Level]]),"Platinum",Customer_Dim[[#This Row],[Loyalty_Level]]) -> Platinum | J2: =PROPER(TRIM(Customer_Dim[[#This Row],[Name]])) -> Sheena Bonilla | K2: =PROPER(TRIM(Customer_Dim[[#This Row],[City]])) -> Donaldton | L2: =IF(Customer_Dim[[#This Row],[Age]]<30,"Young",IF(Customer_Dim[[#This Row],[Age]]<50,"Middle Age","Senior")) -> Senior | M2: =COUNTIF(Customer_Dim[Loyalty_Level],"Platinum") -> 145
A3: CUST1001 | B3: Eugene Nelson | C3: 26 | D3: Female | E3: Phillipsmouth | F3: North Dakota | G3: USA | H3: Platinum | I3: =IF(ISBLANK(Customer_Dim[[#This Row],[Loyalty_Level]]),"Platinum",Customer_Dim[[#This Row],[Loyalty_Level]]) -> Platinum | J3: =PROPER(TRIM(Customer_Dim[[#This Row],[Name]])) -> Eugene Nelson | K3: =PROPER(TRIM(Customer_Dim[[#This Row],[City]])) -> Phillipsmouth | L3: =IF(Customer_Dim[[#This Row],[Age]]<30,"Young",IF(Customer_Dim[[#This Row],[Age]]<50,"Middle Age","Senior")) -> Young | M3: =COUNTIF(Customer_Dim[Loyalty_Level],"Gold") -> 122
A4: CUST1002 | B4: dr. Benjamin Price | C4: 29 | D4: Female | E4: Kylebury | F4: Alabama | G4: USA | H4: Platinum | I4: =IF(ISBLANK(Customer_Dim[[#This Row],[Loyalty_Level]]),"Platinum",Customer_Dim[[#This Row],[Loyalty_Level]]) -> Platinum | J4: =PROPER(TRIM(Customer_Dim[[#This Row],[Name]])) -> Dr. Benjamin Price | K4: =PROPER(TRIM(Customer_Dim[[#This Row],[City]])) -> Kylebury | L4: =IF(Customer_Dim[[#This Row],[Age]]<30,"Young",IF(Customer_Dim[[#This Row],[Age]]<50,"Middle Age","Senior")) -> Young | M4: =COUNTIF(Customer_Dim[Loyalty_Level],"Silver") -> 104
A5: CUST1003 | B5: jeremy harris | C5: 59 | D5: Female | E5: Thomastown | F5: Ohio | G5: USA | H5: Bronze | I5: =IF(ISBLANK(Customer_Dim[[#This Row],[Loyalty_Level]]),"Platinum",Customer_Dim[[#This Row],[Loyalty_Level]]) -> Bronze | J5: =PROPER(TRIM(Customer_Dim[[#This Row],[Name]])) -> Jeremy Harris | K5: =PROPER(TRIM(Customer_Dim[[#This Row],[City]])) -> Thomastown | L5: =IF(Customer_Dim[[#This Row],[Age]]<30,"Young",IF(Customer_Dim[[#This Row],[Age]]<50,"Middle Age","Senior")) -> Senior | M5: =COUNTIF(Customer_Dim[Loyalty_Level],"Bronze") -> 125
A6: CUST1004 | B6: Caroline Collins | C6: 64 | D6: Female | E6: Nicholasshire | F6: California | G6: USA | H6: Silver | I6: =IF(ISBLANK(Customer_Dim[[#This Row],[Loyalty_Level]]),"Platinum",Customer_Dim[[#This Row],[Loyalty_Level]]) -> Silver | J6: =PROPER(TRIM(Customer_Dim[[#This Row],[Name]])) -> Caroline Collins | K6: =PROPER(TRIM(Customer_Dim[[#This Row],[City]])) -> Nicholasshire | L6: =IF(Customer_Dim[[#This Row],[Age]]<30,"Young",IF(Customer_Dim[[#This Row],[Age]]<50,"Middle Age","Senior")) -> Senior
A7: CUST1005 | B7: Christine Vaughn | C7: 24 | D7: Male | E7: East Amandamouth | F7: Oregon | G7: USA | H7: Bronze | I7: =IF(ISBLANK(Customer_Dim[[#This Row],[Loyalty_Level]]),"Platinum",Customer_Dim[[#This Row],[Loyalty_Level]]) -> Bronze | J7: =PROPER(TRIM(Customer_Dim[[#This Row],[Name]])) -> Christine Vaughn | K7: =PROPER(TRIM(Customer_Dim[[#This Row],[City]])) -> East Amandamouth | L7: =IF(Customer_Dim[[#This Row],[Age]]<30,"Young",IF(Customer_Dim[[#This Row],[Age]]<50,"Middle Age","Senior")) -> Young
A8: CUST1006 | B8: Amber Jackson | C8: 29 | D8: Female | E8: Deborahborough | F8: South Dakota | G8: USA | H8: Platinum | I8: =IF(ISBLANK(Customer_Dim[[#This Row],[Loyalty_Level]]),"Platinum",Customer_Dim[[#This Row],[Loyalty_Level]]) -> Platinum | J8: =PROPER(TRIM(Customer_Dim[[#This Row],[Name]])) -> Amber Jackson | K8: =PROPER(TRIM(Customer_Dim[[#This Row],[City]])) -> Deborahborough | L8: =IF(Customer_Dim[[#This Row],[Age]]<30,"Young",IF(Customer_Dim[[#This Row],[Age]]<50,"Middle Age","Senior")) -> Young
A9: CUST1007 | B9: Daniel Boyd | C9: 29 | D9: Female | E9: West Pamelafurt | F9: West Virginia | G9: USA | H9: Bronze | I9: =IF(ISBLANK(Customer_Dim[[#This Row],[Loyalty_Level]]),"Platinum",Customer_Dim[[#This Row],[Loyalty_Level]]) -> Bronze | J9: =PROPER(TRIM(Customer_Dim[[#This Row],[Name]])) -> Daniel Boyd | K9: =PROPER(TRIM(Customer_Dim[[#This Row],[City]])) -> West Pamelafurt | L9: =IF(Customer_Dim[[#This Row],[Age]]<30,"Young",IF(Customer_Dim[[#This Row],[Age]]<50,"Middle Age","Senior")) -> Young
A10: CUST1008 | B10: Melissa Howard | C10: 53 | D10: Female | E10: Maynardton | F10: New Hampshire | G10: USA | H10: Gold | I10: =IF(ISBLANK(Customer_Dim[[#This Row],[Loyalty_Level]]),"Platinum",Customer_Dim[[#This Row],[Loyalty_Level]]) -> Gold | J10: =PROPER(TRIM(Customer_Dim[[#This Row],[Name]])) -> Melissa Howard | K10: =PROPER(TRIM(Customer_Dim[[#This Row],[City]])) -> Maynardton | L10: =IF(Customer_Dim[[#This Row],[Age]]<30,"Young",IF(Customer_Dim[[#This Row],[Age]]<50,"Middle Age","Senior")) -> Senior
A11: CUST1009 | B11: Ms. Maria Leach | C11: 64 | D11: Male | E11: Melissashire | F11: Pennsylvania | G11: USA | H11: Platinum | I11: =IF(ISBLANK(Customer_Dim[[#This Row],[Loyalty_Level]]),"Platinum",Customer_Dim[[#This Row],[Loyalty_Level]]) -> Platinum | J11: =PROPER(TRIM(Customer_Dim[[#This Row],[Name]])) -> Ms. Maria Leach | K11: =PROPER(TRIM(Customer_Dim[[#This Row],[City]])) -> Melissashire | L11: =IF(Customer_Dim[[#This Row],[Age]]<30,"Young",IF(Customer_Dim[[#This Row],[Age]]<50,"Middle Age","Senior")) -> Senior
A12: CUST1010 | B12: Dominic Page | C12: 53 | D12: Male | E12: Port Michaelburgh | F12: Pennsylvania | G12: USA | H12: Bronze | I12: =IF(ISBLANK(Customer_Dim[[#This Row],[Loyalty_Level]]),"Platinum",Customer_Dim[[#This Row],[Loyalty_Level]]) -> Bronze | J12: =PROPER(TRIM(Customer_Dim[[#This Row],[Name]])) -> Dominic Page | K12: =PROPER(TRIM(Customer_Dim[[#This Row],[City]])) -> Port Michaelburgh | L12: =IF(Customer_Dim[[#This Row],[Age]]<30,"Young",IF(Customer_Dim[[#This Row],[Age]]<50,"Middle Age","Senior")) -> Senior
A13: CUST1011 | B13: Brian Lopez | C13: 28 | D13: Female | E13: East Krista | F13: New York | G13: USA | H13: Gold | I13: =IF(ISBLANK(Customer_Dim[[#This Row],[Loyalty_Level]]),"Platinum",Customer_Dim[[#This Row],[Loyalty_Level]]) -> Gold | J13: =PROPER(TRIM(Customer_Dim[[#This Row],[Name]])) -> Brian Lopez | K13: =PROPER(TRIM(Customer_Dim[[#This Row],[City]])) -> East Krista | L13: =IF(Customer_Dim[[#This Row],[Age]]<30,"Young",IF(Customer_Dim[[#This Row],[Age]]<50,"Middle Age","Senior")) -> Young
A14: CUST1012 | B14: Kenneth Lambert | C14: 55 | D14: Female | E14: North Kathryn | F14: Kansas | G14: USA | H14: Platinum | I14: =IF(ISBLANK(Customer_Dim[[#This Row],[Loyalty_Level]]),"Platinum",Customer_Dim[[#This Row],[Loyalty_Level]]) -> Platinum | J14: =PROPER(TRIM(Customer_Dim[[#This Row],[Name]])) -> Kenneth Lambert | K14: =PROPER(TRIM(Customer_Dim[[#This Row],[City]])) -> North Kathryn | L14: =IF(Customer_Dim[[#This Row],[Age]]<30,"Young",IF(Customer_Dim[[#This Row],[Age]]<50,"Middle Age","Senior")) -> Senior
A15: CUST1013 | B15: Nathan Hernandez | C15: 32 | D15: Female | E15: New Becky | F15: Montana | G15: USA | H15: Silver | I15: =IF(ISBLANK(Customer_Dim[[#This Row],[Loyalty_Level]]),"Platinum",Customer_Dim[[#This Row],[Loyalty_Level]]) -> Silver | J15: =PROPER(TRIM(Customer_Dim[[#This Row],[Name]])) -> Nathan Hernandez | K15: =PROPER(TRIM(Customer_Dim[[#This Row],[City]])) -> New Becky | L15: =IF(Customer_Dim[[#This Row],[Age]]<30,"Young",IF(Customer_Dim[[#This Row],[Age]]<50,"Middle Age","Senior")) -> Middle Age
A16: CUST1014 | B16: Ashley Cohen | C16: 53 | D16: Female | E16: Lake Kristamouth | F16: Nebraska | G16: USA | H16: Silver | I16: =IF(ISBLANK(Customer_Dim[[#This Row],[Loyalty_Level]]),"Platinum",Customer_Dim[[#This Row],[Loyalty_Level]]) -> Silver | J16: =PROPER(TRIM(Customer_Dim[[#This Row],[Name]])) -> Ashley Cohen | K16: =PROPER(TRIM(Customer_Dim[[#This Row],[City]])) -> Lake Kristamouth | L16: =IF(Customer_Dim[[#This Row],[Age]]<30,"Young",IF(Customer_Dim[[#This Row],[Age]]<50,"Middle Age","Senior")) -> Senior
A17: CUST1015 | B17: Laura Alvarez | C17: 49 | D17: Female | E17: Lawsonhaven | F17: Washington | G17: USA | H17: Platinum | I17: =IF(ISBLANK(Customer_Dim[[#This Row],[Loyalty_Level]]),"Platinum",Customer_Dim[[#This Row],[Loyalty_Level]]) -> Platinum | J17: =PROPER(TRIM(Customer_Dim[[#This Row],[Name]])) -> Laura Alvarez | K17: =PROPER(TRIM(Customer_Dim[[#This Row],[City]])) -> Lawsonhaven | L17: =IF(Customer_Dim[[#This Row],[Age]]<30,"Young",IF(Customer_Dim[[#This Row],[Age]]<50,"Middle Age","Senior")) -> Middle Age
... A19: CUST1017 | B19: Adam Cruz | C19: 60 | D19: Female | E19: Brandonville | F19: Georgia | G19: USA | H19: Platinum | I19: =IF(ISBLANK(Customer_Dim[[#This Row],[Loyalty_Level]]),"Platinum",Customer_Dim[[#This Row],[Loyalty_Level]]) -> Platinum | J19: =PROPER(TRIM(Customer_Dim[[#This Row],[Name]])) -> Adam Cruz | K19: =PROPER(TRIM(Customer_Dim[[#This Row],[City]])) -> Brandonville | L19: =IF(Customer_Dim[[#This Row],[Age]]<30,"Young",IF(Customer_Dim[[#This Row],[Age]]<50,"Middle Age","Senior")) -> Senior
A20: CUST1018 | B20: Rhonda Moss | C20: 43 | D20: Male | E20: South William | F20: Kansas | G20: USA | I20: =IF(ISBLANK(Customer_Dim[[#This Row],[Loyalty_Level]]),"Platinum",Customer_Dim[[#This Row],[Loyalty_Level]]) -> Platinum | J20: =PROPER(TRIM(Customer_Dim[[#This Row],[Name]])) -> Rhonda Moss | K20: =PROPER(TRIM(Customer_Dim[[#This Row],[City]])) -> South William | L20: =IF(Customer_Dim[[#This Row],[Age]]<30,"Young",IF(Customer_Dim[[#This Row],[Age]]<50,"Middle Age","Senior")) -> Middle Age
A21: CUST1019 | B21: Michael Torres | C21: 46 | D21: Female | E21: Gonzalezfort | F21: New Jersey | G21: USA | H21: Platinum | I21: =IF(ISBLANK(Customer_Dim[[#This Row],[Loyalty_Level]]),"Platinum",Customer_Dim[[#This Row],[Loyalty_Level]]) -> Platinum | J21: =PROPER(TRIM(Customer_Dim[[#This Row],[Name]])) -> Michael Torres | K21: =PROPER(TRIM(Customer_Dim[[#This Row],[City]])) -> Gonzalezfort | L21: =IF(Customer_Dim[[#This Row],[Age]]<30,"Young",IF(Customer_Dim[[#This Row],[Age]]<50,"Middle Age","Senior")) -> Middle Age
A22: CUST1020 | B22: Bridget Allen | C22: 59 | D22: Male | E22: Lake Shaneburgh | F22: Delaware | G22: USA | H22: Silver | I22: =IF(ISBLANK(Customer_Dim[[#This Row],[Loyalty_Level]]),"Platinum",Customer_Dim[[#This Row],[Loyalty_Level]]) -> Silver | J22: =PROPER(TRIM(Customer_Dim[[#This Row],[Name]])) -> Bridget Allen | K22: =PROPER(TRIM(Customer_Dim[[#This Row],[City]])) -> Lake Shaneburgh | L22: =IF(Customer_Dim[[#This Row],[Age]]<30,"Young",IF(Customer_Dim[[#This Row],[Age]]<50,"Middle Age","Senior")) -> Senior
A23: CUST1021 | B23: Jeff Martinez | C23: 36 | D23: Female | E23: Smithburgh | F23: Oklahoma | G23: USA | H23: Gold | I23: =IF(ISBLANK(Customer_Dim[[#This Row],[Loyalty_Level]]),"Platinum",Customer_Dim[[#This Row],[Loyalty_Level]]) -> Gold | J23: =PROPER(TRIM(Customer_Dim[[#This Row],[Name]])) -> Jeff Martinez | K23: =PROPER(TRIM(Customer_Dim[[#This Row],[City]])) -> Smithburgh | L23: =IF(Customer_Dim[[#This Row],[Age]]<30,"Young",IF(Customer_Dim[[#This Row],[Age]]<50,"Middle Age","Senior")) -> Middle Age
A24: CUST1022 | B24: paul fox | C24: 33 | D24: Female | E24: Michaelton | F24: Hawaii | G24: USA | H24: Silver | I24: =IF(ISBLANK(Customer_Dim[[#This Row],[Loyalty_Level]]),"Platinum",Customer_Dim[[#This Row],[Loyalty_Level]]) -> Silver | J24: =PROPER(TRIM(Customer_Dim[[#This Row],[Name]])) -> Paul Fox | K24: =PROPER(TRIM(Customer_Dim[[#This Row],[City]])) -> Michaelton | L24: =IF(Customer_Dim[[#This Row],[Age]]<30,"Young",IF(Customer_Dim[[#This Row],[Age]]<50,"Middle Age","Senior")) -> Middle Age
A25: CUST1023 | B25: Jonathan Steele | C25: 52 | D25: Female | E25: Molinabury | F25: Oregon | G25: USA | H25: Silver | I25: =IF(ISBLANK(Customer_Dim[[#This Row],[Loyalty_Level]]),"Platinum",Customer_Dim[[#This Row],[Loyalty_Level]]) -> Silver | J25: =PROPER(TRIM(Customer_Dim[[#This Row],[Name]])) -> Jonathan Steele | K25: =PROPER(TRIM(Customer_Dim[[#This Row],[City]])) -> Molinabury | L25: =IF(Customer_Dim[[#This Row],[Age]]<30,"Young",IF(Customer_Dim[[#This Row],[Age]]<50,"Middle Age","Senior")) -> Senior
A26: CUST1024 | B26: Heather Collins | C26: 40 | D26: Male | E26: Rogerschester | F26: Idaho | G26: USA | H26: Platinum | I26: =IF(ISBLANK(Customer_Dim[[#This Row],[Loyalty_Level]]),"Platinum",Customer_Dim[[#This Row],[Loyalty_Level]]) -> Platinum | J26: =PROPER(TRIM(Customer_Dim[[#This Row],[Name]])) -> Heather Collins | K26: =PROPER(TRIM(Customer_Dim[[#This Row],[City]])) -> Rogerschester | L26: =IF(Customer_Dim[[#This Row],[Age]]<30,"Young",IF(Customer_Dim[[#This Row],[Age]]<50,"Middle Age","Senior")) -> Middle Age
A27: CUST1025 | B27: Diana Taylor | C27: 59 | D27: Female | E27: Vasqueztown | F27: California | G27: USA | H27: Bronze | I27: =IF(ISBLANK(Customer_Dim[[#This Row],[Loyalty_Level]]),"Platinum",Customer_Dim[[#This Row],[Loyalty_Level]]) -> Bronze | J27: =PROPER(TRIM(Customer_Dim[[#This Row],[Name]])) -> Diana Taylor | K27: =PROPER(TRIM(Customer_Dim[[#This Row],[City]])) -> Vasqueztown | L27: =IF(Customer_Dim[[#This Row],[Age]]<30,"Young",IF(Customer_Dim[[#This Row],[Age]]<50,"Middle Age","Senior")) -> Senior
A28: CUST1026 | B28: Amber Carlson | C28: 18 | D28: Female | E28: East Michellemouth | F28: Missouri | G28: USA | H28: Gold | I28: =IF(ISBLANK(Customer_Dim[[#This Row],[Loyalty_Level]]),"Platinum",Customer_Dim[[#This Row],[Loyalty_Level]]) -> Gold | J28: =PROPER(TRIM(Customer_Dim[[#This Row],[Name]])) -> Amber Carlson | K28: =PROPER(TRIM(Customer_Dim[[#This Row],[City]])) -> East Michellemouth | L28: =IF(Customer_Dim[[#This Row],[Age]]<30,"Young",IF(Customer_Dim[[#This Row],[Age]]<50,"Middle Age","Senior")) -> Young
A29: CUST1027 | B29: Leslie Johnson | C29: 31 | D29: Male | E29: Mollyshire | F29: Utah | G29: USA | I29: =IF(ISBLANK(Customer_Dim[[#This Row],[Loyalty_Level]]),"Platinum",Customer_Dim[[#This Row],[Loyalty_Level]]) -> Platinum | J29: =PROPER(TRIM(Customer_Dim[[#This Row],[Name]])) -> Leslie Johnson | K29: =PROPER(TRIM(Customer_Dim[[#This Row],[City]])) -> Mollyshire | L29: =IF(Customer_Dim[[#This Row],[Age]]<30,"Young",IF(Customer_Dim[[#This Row],[Age]]<50,"Middle Age","Senior")) -> Middle Age
A30: CUST1028 | B30: Joshua Ryan | C30: 27 | D30: Female | E30: New David | F30: New Jersey | G30: USA | H30: Platinum | I30: =IF(ISBLANK(Customer_Dim[[#This Row],[Loyalty_Level]]),"Platinum",Customer_Dim[[#This Row],[Loyalty_Level]]) -> Platinum | J30: =PROPER(TRIM(Customer_Dim[[#This Row],[Name]])) -> Joshua Ryan | K30: =PROPER(TRIM(Customer_Dim[[#This Row],[City]])) -> New David | L30: =IF(Customer_Dim[[#This Row],[Age]]<30,"Young",IF(Customer_Dim[[#This Row],[Age]]<50,"Middle Age","Senior")) -> Young
A31: CUST1029 | B31: David Arnold | C31: 54 | D31: Female | E31: East Jennifer | F31: California | G31: USA | H31: Silver | I31: =IF(ISBLANK(Customer_Dim[[#This Row],[Loyalty_Level]]),"Platinum",Customer_Dim[[#This Row],[Loyalty_Level]]) -> Silver | J31: =PROPER(TRIM(Customer_Dim[[#This Row],[Name]])) -> David Arnold | K31: =PROPER(TRIM(Customer_Dim[[#This Row],[City]])) -> East Jennifer | L31: =IF(Customer_Dim[[#This Row],[Age]]<30,"Young",IF(Customer_Dim[[#This Row],[Age]]<50,"Middle Age","Senior")) -> Senior
A32: CUST1030 | B32: Jessica Acevedo | C32: 64 | D32: Female | E32: Amybury | F32: Pennsylvania | G32: USA | H32: Bronze | I32: =IF(ISBLANK(Customer_Dim[[#This Row],[Loyalty_Level]]),"Platinum",Customer_Dim[[#This Row],[Loyalty_Level]]) -> Bronze | J32: =PROPER(TRIM(Customer_Dim[[#This Row],[Name]])) -> Jessica Acevedo | K32: =PROPER(TRIM(Customer_Dim[[#This Row],[City]])) -> Amybury | L32: =IF(Customer_Dim[[#This Row],[Age]]<30,"Young",IF(Customer_Dim[[#This Row],[Age]]<50,"Middle Age","Senior")) -> Senior
A33: CUST1031 | B33: Sarah Vance | C33: 41 | D33: Male | E33: Johnsonville | F33: Oregon | G33: USA | H33: Silver | I33: =IF(ISBLANK(Customer_Dim[[#This Row],[Loyalty_Level]]),"Platinum",Customer_Dim[[#This Row],[Loyalty_Level]]) -> Silver | J33: =PROPER(TRIM(Customer_Dim[[#This Row],[Name]])) -> Sarah Vance | K33: =PROPER(TRIM(Customer_Dim[[#This Row],[City]])) -> Johnsonville | L33: =IF(Customer_Dim[[#This Row],[Age]]<30,"Young",IF(Customer_Dim[[#This Row],[Age]]<50,"Middle Age","Senior")) -> Middle Age
A34: CUST1032 | B34: Mike Jennings | C34: 48 | D34: Female | E34: Fostermouth | F34: Arizona | G34: USA | H34: Gold | I34: =IF(ISBLANK(Customer_Dim[[#This Row],[Loyalty_Level]]),"Platinum",Customer_Dim[[#This Row],[Loyalty_Level]]) -> Gold | J34: =PROPER(TRIM(Customer_Dim[[#This Row],[Name]])) -> Mike Jennings | K34: =PROPER(TRIM(Customer_Dim[[#This Row],[City]])) -> Fostermouth | L34: =IF(Customer_Dim[[#This Row],[Age]]<30,"Young",IF(Customer_Dim[[#This Row],[Age]]<50,"Middle Age","Senior")) -> Middle Age
A35: CUST1033 | B35: Robert Jones DDS | C35: 25 | D35: Male | E35: Tristanton | F35: Oklahoma | G35: USA | H35: Platinum | I35: =IF(ISBLANK(Customer_Dim[[#This Row],[Loyalty_Level]]),"Platinum",Customer_Dim[[#This Row],[Loyalty_Level]]) -> Platinum | J35: =PROPER(TRIM(Customer_Dim[[#This Row],[Name]])) -> Robert Jones Dds | K35: =PROPER(TRIM(Customer_Dim[[#This Row],[City]])) -> Tristanton | L35: =IF(Customer_Dim[[#This Row],[Age]]<30,"Young",IF(Customer_Dim[[#This Row],[Age]]<50,"Middle Age","Senior")) -> Young
A36: CUST1034 | B36: Christopher Olson | C36: 27 | D36: Female | E36: West Richard | F36: Maryland | G36: USA | H36: Platinum | I36: =IF(ISBLANK(Customer_Dim[[#This Row],[Loyalty_Level]]),"Platinum",Customer_Dim[[#This Row],[Loyalty_Level]]) -> Platinum | J36: =PROPER(TRIM(Customer_Dim[[#This Row],[Name]])) -> Christopher Olson | K36: =PROPER(TRIM(Customer_Dim[[#This Row],[City]])) -> West Richard | L36: =IF(Customer_Dim[[#This Row],[Age]]<30,"Young",IF(Customer_Dim[[#This Row],[Age]]<50,"Middle Age","Senior")) -> Young
A37: CUST1035 | B37: Rachel Myers | C37: 52 | D37: Male | E37: Robertberg | F37: North Dakota | G37: USA | H37: Silver | I37: =IF(ISBLANK(Customer_Dim[[#This Row],[Loyalty_Level]]),"Platinum",Customer_Dim[[#This Row],[Loyalty_Level]]) -> Silver | J37: =PROPER(TRIM(Customer_Dim[[#This Row],[Name]])) -> Rachel Myers | K37: =PROPER(TRIM(Customer_Dim[[#This Row],[City]])) -> Robertberg | L37: =IF(Customer_Dim[[#This Row],[Age]]<30,"Young",IF(Customer_Dim[[#This Row],[Age]]<50,"Middle Age","Senior")) -> Senior
A38: CUST1036 | B38: Thomas Phillips | C38: 20 | D38: Female | E38: Luisfurt | F38: Georgia | G38: USA | H38: Gold | I38: =IF(ISBLANK(Customer_Dim[[#This Row],[Loyalty_Level]]),"Platinum",Customer_Dim[[#This Row],[Loyalty_Level]]) -> Gold | J38: =PROPER(TRIM(Customer_Dim[[#This Row],[Name]])) -> Thomas Phillips | K38: =PROPER(TRIM(Customer_Dim[[#This Row],[City]])) -> Luisfurt | L38: =IF(Customer_Dim[[#This Row],[Age]]<30,"Young",IF(Customer_Dim[[#This Row],[Age]]<50,"Middle Age","Senior")) -> Young
A39: CUST1037 | B39: Christopher Carter | C39: 27 | D39: Female | E39: Brendastad | F39: South Dakota | G39: USA | I39: =IF(ISBLANK(Customer_Dim[[#This Row],[Loyalty_Level]]),"Platinum",Customer_Dim[[#This Row],[Loyalty_Level]]) -> Platinum | J39: =PROPER(TRIM(Customer_Dim[[#This Row],[Name]])) -> Christopher Carter | K39: =PROPER(TRIM(Customer_Dim[[#This Row],[City]])) -> Brendastad | L39: =IF(Customer_Dim[[#This Row],[Age]]<30,"Young",IF(Customer_Dim[[#This Row],[Age]]<50,"Middle Age","Senior")) -> Young
A40: CUST1038 | B40: Deanna Simpson | C40: 35 | D40: Female | E40: Brownport | F40: North Dakota | G40: USA | H40: Bronze | I40: =IF(ISBLANK(Customer_Dim[[#This Row],[Loyalty_Level]]),"Platinum",Customer_Dim[[#This Row],[Loyalty_Level]]) -> Bronze | J40: =PROPER(TRIM(Customer_Dim[[#This Row],[Name]])) -> Deanna Simpson | K40: =PROPER(TRIM(Customer_Dim[[#This Row],[City]])) -> Brownport | L40: =IF(Customer_Dim[[#This Row],[Age]]<30,"Young",IF(Customer_Dim[[#This Row],[Age]]<50,"Middle Age","Senior")) -> Middle Age
A41: CUST1039 | B41: Tonya Reynolds | C41: 55 | D41: Female | E41: Darleneton | F41: Michigan | G41: USA | H41: Gold | I41: =IF(ISBLANK(Customer_Dim[[#This Row],[Loyalty_Level]]),"Platinum",Customer_Dim[[#This Row],[Loyalty_Level]]) -> Gold | J41: =PROPER(TRIM(Customer_Dim[[#This Row],[Name]])) -> Tonya Reynolds | K41: =PROPER(TRIM(Customer_Dim[[#This Row],[City]])) -> Darleneton | L41: =IF(Customer_Dim[[#This Row],[Age]]<30,"Young",IF(Customer_Dim[[#This Row],[Age]]<50,"Middle Age","Senior")) -> Senior
A42: CUST1040 | B42: Eric Vega | C42: 50 | D42: Male | E42: Williamsonland | F42: Kansas | G42: USA | H42: Gold | I42: =IF(ISBLANK(Customer_Dim[[#This Row],[Loyalty_Level]]),"Platinum",Customer_Dim[[#This Row],[Loyalty_Level]]) -> Gold | J42: =PROPER(TRIM(Customer_Dim[[#This Row],[Name]])) -> Eric Vega | K42: =PROPER(TRIM(Customer_Dim[[#This Row],[City]])) -> Williamsonland | L42: =IF(Customer_Dim[[#This Row],[Age]]<30,"Young",IF(Customer_Dim[[#This Row],[Age]]<50,"Middle Age","Senior")) -> Senior
A43: CUST1041 | B43: James Gibbs | C43: 21 | D43: Male | E43: Mooneyshire | F43: Alaska | G43: USA | H43: Platinum | I43: =IF(ISBLANK(Customer_Dim[[#This Row],[Loyalty_Level]]),"Platinum",Customer_Dim[[#This Row],[Loyalty_Level]]) -> Platinum | J43: =PROPER(TRIM(Customer_Dim[[#This Row],[Name]])) -> James Gibbs | K43: =PROPER(TRIM(Customer_Dim[[#This Row],[City]])) -> Mooneyshire | L43: =IF(Customer_Dim[[#This Row],[Age]]<30,"Young",IF(Customer_Dim[[#This Row],[Age]]<50,"Middle Age","Senior")) -> Young
A44: CUST1042 | B44: William Martin | C44: 19 | D44: Male | E44: Ryanburgh | F44: Connecticut | G44: USA | H44: Platinum | I44: =IF(ISBLANK(Customer_Dim[[#This Row],[Loyalty_Level]]),"Platinum",Customer_Dim[[#This Row],[Loyalty_Level]]) -> Platinum | J44: =PROPER(TRIM(Customer_Dim[[#This Row],[Name]])) -> William Martin | K44: =PROPER(TRIM(Customer_Dim[[#This Row],[City]])) -> Ryanburgh | L44: =IF(Customer_Dim[[#This Row],[Age]]<30,"Young",IF(Customer_Dim[[#This Row],[Age]]<50,"Middle Age","Senior")) -> Young
A45: CUST1043 | B45: Joseph Snow | C45: 45 | D45: Male | E45: South Michaelfort | F45: Vermont | G45: USA | H45: Gold | I45: =IF(ISBLANK(Customer_Dim[[#This Row],[Loyalty_Level]]),"Platinum",Customer_Dim[[#This Row],[Loyalty_Level]]) -> Gold | J45: =PROPER(TRIM(Customer_Dim[[#This Row],[Name]])) -> Joseph Snow | K45: =PROPER(TRIM(Customer_Dim[[#This Row],[City]])) -> South Michaelfort | L45: =IF(Customer_Dim[[#This Row],[Age]]<30,"Young",IF(Customer_Dim[[#This Row],[Age]]<50,"Middle Age","Senior")) -> Middle Age
A46: CUST1044 | B46: Denise Williams | C46: 34 | D46: Male | E46: Christianstad | F46: Hawaii | G46: USA | H46: Bronze | I46: =IF(ISBLANK(Customer_Dim[[#This Row],[Loyalty_Level]]),"Platinum",Customer_Dim[[#This Row],[Loyalty_Level]]) -> Bronze | J46: =PROPER(TRIM(Customer_Dim[[#This Row],[Name]])) -> Denise Williams | K46: =PROPER(TRIM(Customer_Dim[[#This Row],[City]])) -> Christianstad | L46: =IF(Customer_Dim[[#This Row],[Age]]<30,"Young",IF(Customer_Dim[[#This Row],[Age]]<50,"Middle Age","Senior")) -> Middle Age
A47: CUST1045 | B47: Jordan Jackson DDS | C47: 54 | D47: Male | E47: North Johnview | F47: Arizona | G47: USA | H47: Gold | I47: =IF(ISBLANK(Customer_Dim[[#This Row],[Loyalty_Level]]),"Platinum",Customer_Dim[[#This Row],[Loyalty_Level]]) -> Gold | J47: =PROPER(TRIM(Customer_Dim[[#This Row],[Name]])) -> Jordan Jackson Dds | K47: =PROPER(TRIM(Customer_Dim[[#This Row],[City]])) -> North Johnview | L47: =IF(Customer_Dim[[#This Row],[Age]]<30,"Young",IF(Customer_Dim[[#This Row],[Age]]<50,"Middle Age","Senior")) -> Senior
A48: CUST1046 | B48: Michelle Garcia DDS | C48: 55 | D48: Female | E48: Perezbury | F48: Ohio | G48: USA | H48: Platinum | I48: =IF(ISBLANK(Customer_Dim[[#This Row],[Loyalty_Level]]),"Platinum",Customer_Dim[[#This Row],[Loyalty_Level]]) -> Platinum | J48: =PROPER(TRIM(Customer_Dim[[#This Row],[Name]])) -> Michelle Garcia Dds | K48: =PROPER(TRIM(Customer_Dim[[#This Row],[City]])) -> Perezbury | L48: =IF(Customer_Dim[[#This Row],[Age]]<30,"Young",IF(Customer_Dim[[#This Row],[Age]]<50,"Middle Age","Senior")) -> Senior
A49: CUST1047 | B49: Gina Knight | C49: 54 | D49: Female | E49: Lake Roberthaven | F49: Nevada | G49: USA | H49: Silver | I49: =IF(ISBLANK(Customer_Dim[[#This Row],[Loyalty_Level]]),"Platinum",Customer_Dim[[#This Row],[Loyalty_Level]]) -> Silver | J49: =PROPER(TRIM(Customer_Dim[[#This Row],[Name]])) -> Gina Knight | K49: =PROPER(TRIM(Customer_Dim[[#This Row],[City]])) -> Lake Roberthaven | L49: =IF(Customer_Dim[[#This Row],[Age]]<30,"Young",IF(Customer_Dim[[#This Row],[Age]]<50,"Middle Age","Senior")) -> Senior
A50: CUST1048 | B50: April Mullins | C50: 54 | D50: Male | E50: Dawsonbury | F50: North Carolina | G50: USA | H50: Platinum | I50: =IF(ISBLANK(Customer_Dim[[#This Row],[Loyalty_Level]]),"Platinum",Customer_Dim[[#This Row],[Loyalty_Level]]) -> Platinum | J50: =PROPER(TRIM(Customer_Dim[[#This Row],[Name]])) -> April Mullins | K50: =PROPER(TRIM(Customer_Dim[[#This Row],[City]])) -> Dawsonbury | L50: =IF(Customer_Dim[[#This Row],[Age]]<30,"Young",IF(Customer_Dim[[#This Row],[Age]]<50,"Middle Age","Senior")) -> Senior
A51: CUST1049 | B51: Timothy Weaver | C51: 45 | D51: Female | E51: New Amy | F51: Ohio | G51: USA | H51: Gold | I51: =IF(ISBLANK(Customer_Dim[[#This Row],[Loyalty_Level]]),"Platinum",Customer_Dim[[#This Row],[Loyalty_Level]]) -> Gold | J51: =PROPER(TRIM(Customer_Dim[[#This Row],[Name]])) -> Timothy Weaver | K51: =PROPER(TRIM(Customer_Dim[[#This Row],[City]])) -> New Amy | L51: =IF(Customer_Dim[[#This Row],[Age]]<30,"Young",IF(Customer_Dim[[#This Row],[Age]]<50,"Middle Age","Senior")) -> Middle Age
... A501: CUST1499 | B501: Philip Pennington | C501: 27 | D501: Female | E501: East Valerieview | F501: Oregon | G501: USA | H501: Platinum | I501: =IF(ISBLANK(Customer_Dim[[#This Row],[Loyalty_Level]]),"Platinum",Customer_Dim[[#This Row],[Loyalty_Level]]) -> Platinum | J501: =PROPER(TRIM(Customer_Dim[[#This Row],[Name]])) -> Philip Pennington | K501: =PROPER(TRIM(Customer_Dim[[#This Row],[City]])) -> East Valerieview | L501: =IF(Customer_Dim[[#This Row],[Age]]<30,"Young",IF(Customer_Dim[[#This Row],[Age]]<50,"Middle Age","Senior")) -> Young

Sheet Product_Dim
A1: Product_ID | B1: Product_Name | C1: Category | D1: Sub_Category | E1: Brand | F1: Cost | G1: Stock | H1: Cost2 | I1: Stock2 | J1: Inventory Value | K1: Stock Status | L1: =COUNTBLANK(Product_Dim[Cost]) -> 6
A2: PROD0 | B2: Brother Laser Printer | C2: Electronics | D2: Computer | E2: Hunt Inc | F2: 112.42 | G2: 416 | H2: =IF(ISBLANK(Product_Dim[[#This Row],[Cost]]),MEDIAN(Product_Dim[Cost]),Product_Dim[[#This Row],[Cost]]) -> 112.42 | I2: =IF(ISBLANK(Product_Dim[[#This Row],[Stock]]),MEDIAN(Product_Dim[Stock]),Product_Dim[[#This Row],[Stock]]) -> 416 | J2: =Product_Dim[[#This Row],[Cost2]]*Product_Dim[[#This Row],[Stock2]] -> 46766.72 | K2: =IF(Product_Dim[[#This Row],[Stock2]]<100,"Low Stock",IF(Product_Dim[[#This Row],[Stock2]]<300,"Medium Stock","High Stock")) -> High Stock | L2: =COUNTBLANK(Product_Dim[Stock]) -> 3
A3: PROD1 | B3: Men's Graphic T-Shirt | C3: Clothing | D3: Tops | E3: Terry-Moore | F3: 342.56 | G3: 181 | H3: =IF(ISBLANK(Product_Dim[[#This Row],[Cost]]),MEDIAN(Product_Dim[Cost]),Product_Dim[[#This Row],[Cost]]) -> 342.56 | I3: =IF(ISBLANK(Product_Dim[[#This Row],[Stock]]),MEDIAN(Product_Dim[Stock]),Product_Dim[[#This Row],[Stock]]) -> 181 | J3: =Product_Dim[[#This Row],[Cost2]]*Product_Dim[[#This Row],[Stock2]] -> 62003.36 | K3: =IF(Product_Dim[[#This Row],[Stock2]]<100,"Low Stock",IF(Product_Dim[[#This Row],[Stock2]]<300,"Medium Stock","High Stock")) -> Medium Stock
A4: PROD2 | B4: Women's Casual Hoodie | C4: Clothing | D4: Outerwear | E4: Sims Inc | G4: 352 | H4: =IF(ISBLANK(Product_Dim[[#This Row],[Cost]]),MEDIAN(Product_Dim[Cost]),Product_Dim[[#This Row],[Cost]]) -> 242.965 | I4: =IF(ISBLANK(Product_Dim[[#This Row],[Stock]]),MEDIAN(Product_Dim[Stock]),Product_Dim[[#This Row],[Stock]]) -> 352 | J4: =Product_Dim[[#This Row],[Cost2]]*Product_Dim[[#This Row],[Stock2]] -> 85523.68 | K4: =IF(Product_Dim[[#This Row],[Stock2]]<100,"Low Stock",IF(Product_Dim[[#This Row],[Stock2]]<300,"Medium Stock","High Stock")) -> High Stock
A5: PROD3 | B5: Men's Running Jacket | C5: Clothing | D5: Outerwear | E5: Pineda Ltd | F5: 364.67 | G5: 452 | H5: =IF(ISBLANK(Product_Dim[[#This Row],[Cost]]),MEDIAN(Product_Dim[Cost]),Product_Dim[[#This Row],[Cost]]) -> 364.67 | I5: =IF(ISBLANK(Product_Dim[[#This Row],[Stock]]),MEDIAN(Product_Dim[Stock]),Product_Dim[[#This Row],[Stock]]) -> 452 | J5: =Product_Dim[[#This Row],[Cost2]]*Product_Dim[[#This Row],[Stock2]] -> 164830.84 | K5: =IF(Product_Dim[[#This Row],[Stock2]]<100,"Low Stock",IF(Product_Dim[[#This Row],[Stock2]]<300,"Medium Stock","High Stock")) -> High Stock
A6: PROD4 | B6: Women's Yoga Pants | C6: Clothing | D6: Bottoms | E6: Gonzales-Davis | F6: 306.46 | G6: 487 | H6: =IF(ISBLANK(Product_Dim[[#This Row],[Cost]]),MEDIAN(Product_Dim[Cost]),Product_Dim[[#This Row],[Cost]]) -> 306.46 | I6: =IF(ISBLANK(Product_Dim[[#This Row],[Stock]]),MEDIAN(Product_Dim[Stock]),Product_Dim[[#This Row],[Stock]]) -> 487 | J6: =Product_Dim[[#This Row],[Cost2]]*Product_Dim[[#This Row],[Stock2]] -> 149246.02 | K6: =IF(Product_Dim[[#This Row],[Stock2]]<100,"Low Stock",IF(Product_Dim[[#This Row],[Stock2]]<300,"Medium Stock","High Stock")) -> High Stock
A7: PROD5 | B7: Men's Leather Belt | C7: Clothing | D7: Accessories | E7: Baldwin, Garza and Gonzalez | F7: 261 | G7: 59 | H7: =IF(ISBLANK(Product_Dim[[#This Row],[Cost]]),MEDIAN(Product_Dim[Cost]),Product_Dim[[#This Row],[Cost]]) -> 261 | I7: =IF(ISBLANK(Product_Dim[[#This Row],[Stock]]),MEDIAN(Product_Dim[Stock]),Product_Dim[[#This Row],[Stock]]) -> 59 | J7: =Product_Dim[[#This Row],[Cost2]]*Product_Dim[[#This Row],[Stock2]] -> 15399 | K7: =IF(Product_Dim[[#This Row],[Stock2]]<100,"Low Stock",IF(Product_Dim[[#This Row],[Stock2]]<300,"Medium Stock","High Stock")) -> Low Stock
A8: PROD6 | B8: Herbal Face Moisturizer | C8: Beauty | D8: Skincare | E8: Davidson PLC | F8: 312.8 | G8: 350 | H8: =IF(ISBLANK(Product_Dim[[#This Row],[Cost]]),MEDIAN(Product_Dim[Cost]),Product_Dim[[#This Row],[Cost]]) -> 312.8 | I8: =IF(ISBLANK(Product_Dim[[#This Row],[Stock]]),MEDIAN(Product_Dim[Stock]),Product_Dim[[#This Row],[Stock]]) -> 350 | J8: =Product_Dim[[#This Row],[Cost2]]*Product_Dim[[#This Row],[Stock2]] -> 109480 | K8: =IF(Product_Dim[[#This Row],[Stock2]]<100,"Low Stock",IF(Product_Dim[[#This Row],[Stock2]]<300,"Medium Stock","High Stock")) -> High Stock
A9: PROD7 | B9: LED Table Lamp | C9: Home | D9: Lighting | E9: Harrell LLC | F9: 218.86 | G9: 170 | H9: =IF(ISBLANK(Product_Dim[[#This Row],[Cost]]),MEDIAN(Product_Dim[Cost]),Product_Dim[[#This Row],[Cost]]) -> 218.86 | I9: =IF(ISBLANK(Product_Dim[[#This Row],[Stock]]),MEDIAN(Product_Dim[Stock]),Product_Dim[[#This Row],[Stock]]) -> 170 | J9: =Product_Dim[[#This Row],[Cost2]]*Product_Dim[[#This Row],[Stock2]] -> 37206.2 | K9: =IF(Product_Dim[[#This Row],[Stock2]]<100,"Low Stock",IF(Product_Dim[[#This Row],[Stock2]]<300,"Medium Stock","High Stock")) -> Medium Stock
A10: PROD8 | B10: Wireless Bluetooth Earbuds | C10: Electronics | D10: Audio | E10: Perez-Johnston | F10: 439.07 | G10: 142 | H10: =IF(ISBLANK(Product_Dim[[#This Row],[Cost]]),MEDIAN(Product_Dim[Cost]),Product_Dim[[#This Row],[Cost]]) -> 439.07 | I10: =IF(ISBLANK(Product_Dim[[#This Row],[Stock]]),MEDIAN(Product_Dim[Stock]),Product_Dim[[#This Row],[Stock]]) -> 142 | J10: =Product_Dim[[#This Row],[Cost2]]*Product_Dim[[#This Row],[Stock2]] -> 62347.94 | K10: =IF(Product_Dim[[#This Row],[Stock2]]<100,"Low Stock",IF(Product_Dim[[#This Row],[Stock2]]<300,"Medium Stock","High Stock")) -> Medium Stock
A11: PROD9 | B11: Adjustable Dumbbell Set | C11: Sports | D11: Fitness | E11: Hill PLC | F11: 495.72 | G11: 323 | H11: =IF(ISBLANK(Product_Dim[[#This Row],[Cost]]),MEDIAN(Product_Dim[Cost]),Product_Dim[[#This Row],[Cost]]) -> 495.72 | I11: =IF(ISBLANK(Product_Dim[[#This Row],[Stock]]),MEDIAN(Product_Dim[Stock]),Product_Dim[[#This Row],[Stock]]) -> 323 | J11: =Product_Dim[[#This Row],[Cost2]]*Product_Dim[[#This Row],[Stock2]] -> 160117.56 | K11: =IF(Product_Dim[[#This Row],[Stock2]]<100,"Low Stock",IF(Product_Dim[[#This Row],[Stock2]]<300,"Medium Stock","High Stock")) -> High Stock
A12: PROD10 | B12: Ceramic Kitchen Bowl Set | C12: Home | D12: Kitchen | E12: Hamilton Group | F12: 298.86 | G12: 308 | H12: =IF(ISBLANK(Product_Dim[[#This Row],[Cost]]),MEDIAN(Product_Dim[Cost]),Product_Dim[[#This Row],[Cost]]) -> 298.86 | I12: =IF(ISBLANK(Product_Dim[[#This Row],[Stock]]),MEDIAN(Product_Dim[Stock]),Product_Dim[[#This Row],[Stock]]) -> 308 | J12: =Product_Dim[[#This Row],[Cost2]]*Product_Dim[[#This Row],[Stock2]] -> 92048.88 | K12: =IF(Product_Dim[[#This Row],[Stock2]]<100,"Low Stock",IF(Product_Dim[[#This Row],[Stock2]]<300,"Medium Stock","High Stock")) -> High Stock
A13: PROD11 | B13: HD Smart TV Stick | C13: Electronics | D13: Accessories | E13: Gibson, Hobbs and Weaver | F13: 449.4 | H13: =IF(ISBLANK(Product_Dim[[#This Row],[Cost]]),MEDIAN(Product_Dim[Cost]),Product_Dim[[#This Row],[Cost]]) -> 449.4 | I13: =IF(ISBLANK(Product_Dim[[#This Row],[Stock]]),MEDIAN(Product_Dim[Stock]),Product_Dim[[#This Row],[Stock]]) -> 276 | J13: =Product_Dim[[#This Row],[Cost2]]*Product_Dim[[#This Row],[Stock2]] -> 124034.4 | K13: =IF(Product_Dim[[#This Row],[Stock2]]<100,"Low Stock",IF(Product_Dim[[#This Row],[Stock2]]<300,"Medium Stock","High Stock")) -> Medium Stock
A14: PROD12 | B14: Hair Strengthening Shampoo | C14: Beauty | D14: Haircare | E14: Rice LLC | F14: 115.82 | G14: 460 | H14: =IF(ISBLANK(Product_Dim[[#This Row],[Cost]]),MEDIAN(Product_Dim[Cost]),Product_Dim[[#This Row],[Cost]]) -> 115.82 | I14: =IF(ISBLANK(Product_Dim[[#This Row],[Stock]]),MEDIAN(Product_Dim[Stock]),Product_Dim[[#This Row],[Stock]]) -> 460 | J14: =Product_Dim[[#This Row],[Cost2]]*Product_Dim[[#This Row],[Stock2]] -> 53277.2 | K14: =IF(Product_Dim[[#This Row],[Stock2]]<100,"Low Stock",IF(Product_Dim[[#This Row],[Stock2]]<300,"Medium Stock","High Stock")) -> High Stock
A15: PROD13 | B15: USB-C Fast Charger | C15: Electronics | D15: Accessories | E15: Dawson-Perkins | F15: 242.23 | G15: 453 | H15: =IF(ISBLANK(Product_Dim[[#This Row],[Cost]]),MEDIAN(Product_Dim[Cost]),Product_Dim[[#This Row],[Cost]]) -> 242.23 | I15: =IF(ISBLANK(Product_Dim[[#This Row],[Stock]]),MEDIAN(Product_Dim[Stock]),Product_Dim[[#This Row],[Stock]]) -> 453 | J15: =Product_Dim[[#This Row],[Cost2]]*Product_Dim[[#This Row],[Stock2]] -> 109730.19 | K15: =IF(Product_Dim[[#This Row],[Stock2]]<100,"Low Stock",IF(Product_Dim[[#This Row],[Stock2]]<300,"Medium Stock","High Stock")) -> High Stock
A16: PROD14 | B16: Decorative Wall Mirror | C16: Home | D16: Decor | E16: Luna, Anderson and Bowman | F16: 48.01 | G16: 439 | H16: =IF(ISBLANK(Product_Dim[[#This Row],[Cost]]),MEDIAN(Product_Dim[Cost]),Product_Dim[[#This Row],[Cost]]) -> 48.01 | I16: =IF(ISBLANK(Product_Dim[[#This Row],[Stock]]),MEDIAN(Product_Dim[Stock]),Product_Dim[[#This Row],[Stock]]) -> 439 | J16: =Product_Dim[[#This Row],[Cost2]]*Product_Dim[[#This Row],[Stock2]] -> 21076.39 | K16: =IF(Product_Dim[[#This Row],[Stock2]]<100,"Low Stock",IF(Product_Dim[[#This Row],[Stock2]]<300,"Medium Stock","High Stock")) -> High Stock
A17: PROD15 | B17: 4K Home Projector | C17: Electronics | D17: Appliances | E17: Thomas LLC | F17: 465.34 | G17: 301 | H17: =IF(ISBLANK(Product_Dim[[#This Row],[Cost]]),MEDIAN(Product_Dim[Cost]),Product_Dim[[#This Row],[Cost]]) -> 465.34 | I17: =IF(ISBLANK(Product_Dim[[#This Row],[Stock]]),MEDIAN(Product_Dim[Stock]),Product_Dim[[#This Row],[Stock]]) -> 301 | J17: =Product_Dim[[#This Row],[Cost2]]*Product_Dim[[#This Row],[Stock2]] -> 140067.34 | K17: =IF(Product_Dim[[#This Row],[Stock2]]<100,"Low Stock",IF(Product_Dim[[#This Row],[Stock2]]<300,"Medium Stock","High Stock")) -> High Stock
A18: PROD16 | B18: Beard Grooming Kit | C18: Beauty | D18: Grooming | E18: Erickson-Green | F18: 337.42 | G18: 256 | H18: =IF(ISBLANK(Product_Dim[[#This Row],[Cost]]),MEDIAN(Product_Dim[Cost]),Product_Dim[[#This Row],[Cost]]) -> 337.42 | I18: =IF(ISBLANK(Product_Dim[[#This Row],[Stock]]),MEDIAN(Product_Dim[Stock]),Product_Dim[[#This Row],[Stock]]) -> 256 | J18: =Product_Dim[[#This Row],[Cost2]]*Product_Dim[[#This Row],[Stock2]] -> 86379.52 | K18: =IF(Product_Dim[[#This Row],[Stock2]]<100,"Low Stock",IF(Product_Dim[[#This Row],[Stock2]]<300,"Medium Stock","High Stock")) -> Medium Stock
A19: PROD17 | B19: Soccer Training Cone Set | C19: Sports | D19: Accessories | E19: Ford, Murphy and Wilson | F19: 144.53 | G19: 367 | H19: =IF(ISBLANK(Product_Dim[[#This Row],[Cost]]),MEDIAN(Product_Dim[Cost]),Product_Dim[[#This Row],[Cost]]) -> 144.53 | I19: =IF(ISBLANK(Product_Dim[[#This Row],[Stock]]),MEDIAN(Product_Dim[Stock]),Product_Dim[[#This Row],[Stock]]) -> 367 | J19: =Product_Dim[[#This Row],[Cost2]]*Product_Dim[[#This Row],[Stock2]] -> 53042.51 | K19: =IF(Product_Dim[[#This Row],[Stock2]]<100,"Low Stock",IF(Product_Dim[[#This Row],[Stock2]]<300,"Medium Stock","High Stock")) -> High Stock
A20: PROD18 | B20: Women's Denim Jeans | C20: Clothing | D20: Bottoms | E20: Guerra-Hendrix | G20: 343 | H20: =IF(ISBLANK(Product_Dim[[#This Row],[Cost]]),MEDIAN(Product_Dim[Cost]),Product_Dim[[#This Row],[Cost]]) -> 242.965 | I20: =IF(ISBLANK(Product_Dim[[#This Row],[Stock]]),MEDIAN(Product_Dim[Stock]),Product_Dim[[#This Row],[Stock]]) -> 343 | J20: =Product_Dim[[#This Row],[Cost2]]*Product_Dim[[#This Row],[Stock2]] -> 83336.995 | K20: =IF(Product_Dim[[#This Row],[Stock2]]<100,"Low Stock",IF(Product_Dim[[#This Row],[Stock2]]<300,"Medium Stock","High Stock")) -> High Stock
A21: PROD19 | B21: Knee Support Brace | C21: Sports | D21: Equipment | E21: May-Reese | F21: 21.34 | G21: 65 | H21: =IF(ISBLANK(Product_Dim[[#This Row],[Cost]]),MEDIAN(Product_Dim[Cost]),Product_Dim[[#This Row],[Cost]]) -> 21.34 | I21: =IF(ISBLANK(Product_Dim[[#This Row],[Stock]]),MEDIAN(Product_Dim[Stock]),Product_Dim[[#This Row],[Stock]]) -> 65 | J21: =Product_Dim[[#This Row],[Cost2]]*Product_Dim[[#This Row],[Stock2]] -> 1387.1 | K21: =IF(Product_Dim[[#This Row],[Stock2]]<100,"Low Stock",IF(Product_Dim[[#This Row],[Stock2]]<300,"Medium Stock","High Stock")) -> Low Stock
A22: PROD20 | B22: Outdoor Sports Water Bottle | C22: Sports | D22: Accessories | E22: Soto-Ellis | F22: 131.51 | H22: =IF(ISBLANK(Product_Dim[[#This Row],[Cost]]),MEDIAN(Product_Dim[Cost]),Product_Dim[[#This Row],[Cost]]) -> 131.51 | I22: =IF(ISBLANK(Product_Dim[[#This Row],[Stock]]),MEDIAN(Product_Dim[Stock]),Product_Dim[[#This Row],[Stock]]) -> 276 | J22: =Product_Dim[[#This Row],[Cost2]]*Product_Dim[[#This Row],[Stock2]] -> 36296.76 | K22: =IF(Product_Dim[[#This Row],[Stock2]]<100,"Low Stock",IF(Product_Dim[[#This Row],[Stock2]]<300,"Medium Stock","High Stock")) -> Medium Stock
A23: PROD21 | B23: Multi-Purpose Storage Box | C23: Home | D23: Storage | E23: Gardner-Montes | F23: 123.46 | G23: 76 | H23: =IF(ISBLANK(Product_Dim[[#This Row],[Cost]]),MEDIAN(Product_Dim[Cost]),Product_Dim[[#This Row],[Cost]]) -> 123.46 | I23: =IF(ISBLANK(Product_Dim[[#This Row],[Stock]]),MEDIAN(Product_Dim[Stock]),Product_Dim[[#This Row],[Stock]]) -> 76 | J23: =Product_Dim[[#This Row],[Cost2]]*Product_Dim[[#This Row],[Stock2]] -> 9382.96 | K23: =IF(Product_Dim[[#This Row],[Stock2]]<100,"Low Stock",IF(Product_Dim[[#This Row],[Stock2]]<300,"Medium Stock","High Stock")) -> Low Stock
A24: PROD22 | B24: Carbon Fiber Tennis Racket | C24: Sports | D24: Equipment | E24: Flores, Pineda and Rodriguez | F24: 484.62 | G24: 432 | H24: =IF(ISBLANK(Product_Dim[[#This Row],[Cost]]),MEDIAN(Product_Dim[Cost]),Product_Dim[[#This Row],[Cost]]) -> 484.62 | I24: =IF(ISBLANK(Product_Dim[[#This Row],[Stock]]),MEDIAN(Product_Dim[Stock]),Product_Dim[[#This Row],[Stock]]) -> 432 | J24: =Product_Dim[[#This Row],[Cost2]]*Product_Dim[[#This Row],[Stock2]] -> 209355.84 | K24: =IF(Product_Dim[[#This Row],[Stock2]]<100,"Low Stock",IF(Product_Dim[[#This Row],[Stock2]]<300,"Medium Stock","High Stock")) -> High Stock
A25: PROD23 | B25: Men's Formal Shirt | C25: Clothing | D25: Tops | E25: Moon, Mora and Santos | G25: 360 | H25: =IF(ISBLANK(Product_Dim[[#This Row],[Cost]]),MEDIAN(Product_Dim[Cost]),Product_Dim[[#This Row],[Cost]]) -> 242.965 | I25: =IF(ISBLANK(Product_Dim[[#This Row],[Stock]]),MEDIAN(Product_Dim[Stock]),Product_Dim[[#This Row],[Stock]]) -> 360 | J25: =Product_Dim[[#This Row],[Cost2]]*Product_Dim[[#This Row],[Stock2]] -> 87467.4 | K25: =IF(Product_Dim[[#This Row],[Stock2]]<100,"Low Stock",IF(Product_Dim[[#This Row],[Stock2]]<300,"Medium Stock","High Stock")) -> High Stock
A26: PROD24 | B26: Foldable Camping Chair | C26: Sports | D26: Outdoor | E26: Cook Ltd | F26: 166.06 | G26: 340 | H26: =IF(ISBLANK(Product_Dim[[#This Row],[Cost]]),MEDIAN(Product_Dim[Cost]),Product_Dim[[#This Row],[Cost]]) -> 166.06 | I26: =IF(ISBLANK(Product_Dim[[#This Row],[Stock]]),MEDIAN(Product_Dim[Stock]),Product_Dim[[#This Row],[Stock]]) -> 340 | J26: =Product_Dim[[#This Row],[Cost2]]*Product_Dim[[#This Row],[Stock2]] -> 56460.4 | K26: =IF(Product_Dim[[#This Row],[Stock2]]<100,"Low Stock",IF(Product_Dim[[#This Row],[Stock2]]<300,"Medium Stock","High Stock")) -> High Stock
A27: PROD25 | B27: Women's Scarf Set | C27: Clothing | D27: Accessories | E27: Brown and Sons | F27: 174.02 | G27: 268 | H27: =IF(ISBLANK(Product_Dim[[#This Row],[Cost]]),MEDIAN(Product_Dim[Cost]),Product_Dim[[#This Row],[Cost]]) -> 174.02 | I27: =IF(ISBLANK(Product_Dim[[#This Row],[Stock]]),MEDIAN(Product_Dim[Stock]),Product_Dim[[#This Row],[Stock]]) -> 268 | J27: =Product_Dim[[#This Row],[Cost2]]*Product_Dim[[#This Row],[Stock2]] -> 46637.36 | K27: =IF(Product_Dim[[#This Row],[Stock2]]<100,"Low Stock",IF(Product_Dim[[#This Row],[Stock2]]<300,"Medium Stock","High Stock")) -> Medium Stock
A28: PROD26 | B28: Wireless Bluetooth Speaker | C28: Electronics | D28: Audio | E28: Reed-Schmidt | F28: 322.41 | G28: 213 | H28: =IF(ISBLANK(Product_Dim[[#This Row],[Cost]]),MEDIAN(Product_Dim[Cost]),Product_Dim[[#This Row],[Cost]]) -> 322.41 | I28: =IF(ISBLANK(Product_Dim[[#This Row],[Stock]]),MEDIAN(Product_Dim[Stock]),Product_Dim[[#This Row],[Stock]]) -> 213 | J28: =Product_Dim[[#This Row],[Cost2]]*Product_Dim[[#This Row],[Stock2]] -> 68673.33 | K28: =IF(Product_Dim[[#This Row],[Stock2]]<100,"Low Stock",IF(Product_Dim[[#This Row],[Stock2]]<300,"Medium Stock","High Stock")) -> Medium Stock
A29: PROD27 | B29: Decorative Floor Vase | C29: Home | D29: Decor | E29: Khan, Jones and Paul | G29: 378 | H29: =IF(ISBLANK(Product_Dim[[#This Row],[Cost]]),MEDIAN(Product_Dim[Cost]),Product_Dim[[#This Row],[Cost]]) -> 242.965 | I29: =IF(ISBLANK(Product_Dim[[#This Row],[Stock]]),MEDIAN(Product_Dim[Stock]),Product_Dim[[#This Row],[Stock]]) -> 378 | J29: =Product_Dim[[#This Row],[Cost2]]*Product_Dim[[#This Row],[Stock2]] -> 91840.77 | K29: =IF(Product_Dim[[#This Row],[Stock2]]<100,"Low Stock",IF(Product_Dim[[#This Row],[Stock2]]<300,"Medium Stock","High Stock")) -> High Stock
A30: PROD28 | B30: Sports Stopwatch Timer | C30: Sports | D30: Accessories | E30: Burns-Hansen | F30: 38.76 | G30: 137 | H30: =IF(ISBLANK(Product_Dim[[#This Row],[Cost]]),MEDIAN(Product_Dim[Cost]),Product_Dim[[#This Row],[Cost]]) -> 38.76 | I30: =IF(ISBLANK(Product_Dim[[#This Row],[Stock]]),MEDIAN(Product_Dim[Stock]),Product_Dim[[#This Row],[Stock]]) -> 137 | J30: =Product_Dim[[#This Row],[Cost2]]*Product_Dim[[#This Row],[Stock2]] -> 5310.12 | K30: =IF(Product_Dim[[#This Row],[Stock2]]<100,"Low Stock",IF(Product_Dim[[#This Row],[Stock2]]<300,"Medium Stock","High Stock")) -> Medium Stock
A31: PROD29 | B31: Fabric Sofa Throw Blanket | C31: Home | D31: Decor | E31: Hoffman Group | F31: 218.48 | G31: 276 | H31: =IF(ISBLANK(Product_Dim[[#This Row],[Cost]]),MEDIAN(Product_Dim[Cost]),Product_Dim[[#This Row],[Cost]]) -> 218.48 | I31: =IF(ISBLANK(Product_Dim[[#This Row],[Stock]]),MEDIAN(Product_Dim[Stock]),Product_Dim[[#This Row],[Stock]]) -> 276 | J31: =Product_Dim[[#This Row],[Cost2]]*Product_Dim[[#This Row],[Stock2]] -> 60300.48 | K31: =IF(Product_Dim[[#This Row],[Stock2]]<100,"Low Stock",IF(Product_Dim[[#This Row],[Stock2]]<300,"Medium Stock","High Stock")) -> Medium Stock
A32: PROD30 | B32: Stainless Steel Cutlery Set | C32: Home | D32: Kitchen | E32: Stevens, Fernandez and Martin | F32: 19.52 | G32: 57 | H32: =IF(ISBLANK(Product_Dim[[#This Row],[Cost]]),MEDIAN(Product_Dim[Cost]),Product_Dim[[#This Row],[Cost]]) -> 19.52 | I32: =IF(ISBLANK(Product_Dim[[#This Row],[Stock]]),MEDIAN(Product_Dim[Stock]),Product_Dim[[#This Row],[Stock]]) -> 57 | J32: =Product_Dim[[#This Row],[Cost2]]*Product_Dim[[#This Row],[Stock2]] -> 1112.64 | K32: =IF(Product_Dim[[#This Row],[Stock2]]<100,"Low Stock",IF(Product_Dim[[#This Row],[Stock2]]<300,"Medium Stock","High Stock")) -> Low Stock
A33: PROD31 | B33: Basketball | C33: Sports | D33: Team Sports | E33: Nolan-Snow | F33: 204.39 | G33: 281 | H33: =IF(ISBLANK(Product_Dim[[#This Row],[Cost]]),MEDIAN(Product_Dim[Cost]),Product_Dim[[#This Row],[Cost]]) -> 204.39 | I33: =IF(ISBLANK(Product_Dim[[#This Row],[Stock]]),MEDIAN(Product_Dim[Stock]),Product_Dim[[#This Row],[Stock]]) -> 281 | J33: =Product_Dim[[#This Row],[Cost2]]*Product_Dim[[#This Row],[Stock2]] -> 57433.59 | K33: =IF(Product_Dim[[#This Row],[Stock2]]<100,"Low Stock",IF(Product_Dim[[#This Row],[Stock2]]<300,"Medium Stock","High Stock")) -> Medium Stock
A34: PROD32 | B34: Vitamin C Face Serum | C34: Beauty | D34: Skincare | E34: Griffin Ltd | F34: 283.83 | G34: 244 | H34: =IF(ISBLANK(Product_Dim[[#This Row],[Cost]]),MEDIAN(Product_Dim[Cost]),Product_Dim[[#This Row],[Cost]]) -> 283.83 | I34: =IF(ISBLANK(Product_Dim[[#This Row],[Stock]]),MEDIAN(Product_Dim[Stock]),Product_Dim[[#This Row],[Stock]]) -> 244 | J34: =Product_Dim[[#This Row],[Cost2]]*Product_Dim[[#This Row],[Stock2]] -> 69254.52 | K34: =IF(Product_Dim[[#This Row],[Stock2]]<100,"Low Stock",IF(Product_Dim[[#This Row],[Stock2]]<300,"Medium Stock","High Stock")) -> Medium Stock
A35: PROD33 | B35: Modern Wall Clock | C35: Home | D35: Decor | E35: Weiss-Watson | F35: 179.77 | G35: 305 | H35: =IF(ISBLANK(Product_Dim[[#This Row],[Cost]]),MEDIAN(Product_Dim[Cost]),Product_Dim[[#This Row],[Cost]]) -> 179.77 | I35: =IF(ISBLANK(Product_Dim[[#This Row],[Stock]]),MEDIAN(Product_Dim[Stock]),Product_Dim[[#This Row],[Stock]]) -> 305 | J35: =Product_Dim[[#This Row],[Cost2]]*Product_Dim[[#This Row],[Stock2]] -> 54829.85 | K35: =IF(Product_Dim[[#This Row],[Stock2]]<100,"Low Stock",IF(Product_Dim[[#This Row],[Stock2]]<300,"Medium Stock","High Stock")) -> High Stock
A36: PROD34 | B36: Gaming Mechanical Keyboard | C36: Electronics | D36: Computer | E36: Lucero LLC | F36: 419.28 | G36: 86 | H36: =IF(ISBLANK(Product_Dim[[#This Row],[Cost]]),MEDIAN(Product_Dim[Cost]),Product_Dim[[#This Row],[Cost]]) -> 419.28 | I36: =IF(ISBLANK(Product_Dim[[#This Row],[Stock]]),MEDIAN(Product_Dim[Stock]),Product_Dim[[#This Row],[Stock]]) -> 86 | J36: =Product_Dim[[#This Row],[Cost2]]*Product_Dim[[#This Row],[Stock2]] -> 36058.08 | K36: =IF(Product_Dim[[#This Row],[Stock2]]<100,"Low Stock",IF(Product_Dim[[#This Row],[Stock2]]<300,"Medium Stock","High Stock")) -> Low Stock
A37: PROD35 | B37: Bedroom Table Lamp | C37: Home | D37: Lighting | E37: Jones LLC | F37: 382.22 | G37: 329 | H37: =IF(ISBLANK(Product_Dim[[#This Row],[Cost]]),MEDIAN(Product_Dim[Cost]),Product_Dim[[#This Row],[Cost]]) -> 382.22 | I37: =IF(ISBLANK(Product_Dim[[#This Row],[Stock]]),MEDIAN(Product_Dim[Stock]),Product_Dim[[#This Row],[Stock]]) -> 329 | J37: =Product_Dim[[#This Row],[Cost2]]*Product_Dim[[#This Row],[Stock2]] -> 125750.38 | K37: =IF(Product_Dim[[#This Row],[Stock2]]<100,"Low Stock",IF(Product_Dim[[#This Row],[Stock2]]<300,"Medium Stock","High Stock")) -> High Stock
A38: PROD36 | B38: Women's Summer Dress | C38: Clothing | D38: Tops | E38: Smith-Mills | F38: 223.43 | G38: 154 | H38: =IF(ISBLANK(Product_Dim[[#This Row],[Cost]]),MEDIAN(Product_Dim[Cost]),Product_Dim[[#This Row],[Cost]]) -> 223.43 | I38: =IF(ISBLANK(Product_Dim[[#This Row],[Stock]]),MEDIAN(Product_Dim[Stock]),Product_Dim[[#This Row],[Stock]]) -> 154 | J38: =Product_Dim[[#This Row],[Cost2]]*Product_Dim[[#This Row],[Stock2]] -> 34408.22 | K38: =IF(Product_Dim[[#This Row],[Stock2]]<100,"Low Stock",IF(Product_Dim[[#This Row],[Stock2]]<300,"Medium Stock","High Stock")) -> Medium Stock
A39: PROD37 | B39: Men's Casual Sneakers | C39: Clothing | D39: Footwear | E39: Hogan-Lee | F39: 353.47 | G39: 214 | H39: =IF(ISBLANK(Product_Dim[[#This Row],[Cost]]),MEDIAN(Product_Dim[Cost]),Product_Dim[[#This Row],[Cost]]) -> 353.47 | I39: =IF(ISBLANK(Product_Dim[[#This Row],[Stock]]),MEDIAN(Product_Dim[Stock]),Product_Dim[[#This Row],[Stock]]) -> 214 | J39: =Product_Dim[[#This Row],[Cost2]]*Product_Dim[[#This Row],[Stock2]] -> 75642.58 | K39: =IF(Product_Dim[[#This Row],[Stock2]]<100,"Low Stock",IF(Product_Dim[[#This Row],[Stock2]]<300,"Medium Stock","High Stock")) -> Medium Stock
A40: PROD38 | B40: Sports Water Hydration Pack | C40: Sports | D40: Outdoor | E40: Sims-Smith | F40: 135.61 | G40: 394 | H40: =IF(ISBLANK(Product_Dim[[#This Row],[Cost]]),MEDIAN(Product_Dim[Cost]),Product_Dim[[#This Row],[Cost]]) -> 135.61 | I40: =IF(ISBLANK(Product_Dim[[#This Row],[Stock]]),MEDIAN(Product_Dim[Stock]),Product_Dim[[#This Row],[Stock]]) -> 394 | J40: =Product_Dim[[#This Row],[Cost2]]*Product_Dim[[#This Row],[Stock2]] -> 53430.34 | K40: =IF(Product_Dim[[#This Row],[Stock2]]<100,"Low Stock",IF(Product_Dim[[#This Row],[Stock2]]<300,"Medium Stock","High Stock")) -> High Stock
A41: PROD39 | B41: Portable Power Bank | C41: Electronics | D41: Mobile | E41: Cummings and Sons | F41: 326.06 | G41: 301 | H41: =IF(ISBLANK(Product_Dim[[#This Row],[Cost]]),MEDIAN(Product_Dim[Cost]),Product_Dim[[#This Row],[Cost]]) -> 326.06 | I41: =IF(ISBLANK(Product_Dim[[#This Row],[Stock]]),MEDIAN(Product_Dim[Stock]),Product_Dim[[#This Row],[Stock]]) -> 301 | J41: =Product_Dim[[#This Row],[Cost2]]*Product_Dim[[#This Row],[Stock2]] -> 98144.06 | K41: =IF(Product_Dim[[#This Row],[Stock2]]<100,"Low Stock",IF(Product_Dim[[#This Row],[Stock2]]<300,"Medium Stock","High Stock")) -> High Stock
... A48: PROD46 | B48: Men's Winter Jacket | C48: Clothing | D48: Outerwear | E48: Kelly, Smith and Perez | F48: 167.34 | G48: 296 | H48: =IF(ISBLANK(Product_Dim[[#This Row],[Cost]]),MEDIAN(Product_Dim[Cost]),Product_Dim[[#This Row],[Cost]]) -> 167.34 | I48: =IF(ISBLANK(Product_Dim[[#This Row],[Stock]]),MEDIAN(Product_Dim[Stock]),Product_Dim[[#This Row],[Stock]]) -> 296 | J48: =Product_Dim[[#This Row],[Cost2]]*Product_Dim[[#This Row],[Stock2]] -> 49532.64 | K48: =IF(Product_Dim[[#This Row],[Stock2]]<100,"Low Stock",IF(Product_Dim[[#This Row],[Stock2]]<300,"Medium Stock","High Stock")) -> Medium Stock
A49: PROD47 | B49: Makeup Brush Set | C49: Beauty | D49: Makeup | E49: Cook Inc | G49: 431 | H49: =IF(ISBLANK(Product_Dim[[#This Row],[Cost]]),MEDIAN(Product_Dim[Cost]),Product_Dim[[#This Row],[Cost]]) -> 242.965 | I49: =IF(ISBLANK(Product_Dim[[#This Row],[Stock]]),MEDIAN(Product_Dim[Stock]),Product_Dim[[#This Row],[Stock]]) -> 431 | J49: =Product_Dim[[#This Row],[Cost2]]*Product_Dim[[#This Row],[Stock2]] -> 104717.91 | K49: =IF(Product_Dim[[#This Row],[Stock2]]<100,"Low Stock",IF(Product_Dim[[#This Row],[Stock2]]<300,"Medium Stock","High Stock")) -> High Stock
A50: PROD48 | B50: Car Dashboard Phone Holder | C50: Electronics | D50: Accessories | E50: Byrd, Stewart and Valdez | F50: 177.98 | G50: 103 | H50: =IF(ISBLANK(Product_Dim[[#This Row],[Cost]]),MEDIAN(Product_Dim[Cost]),Product_Dim[[#This Row],[Cost]]) -> 177.98 | I50: =IF(ISBLANK(Product_Dim[[#This Row],[Stock]]),MEDIAN(Product_Dim[Stock]),Product_Dim[[#This Row],[Stock]]) -> 103 | J50: =Product_Dim[[#This Row],[Cost2]]*Product_Dim[[#This Row],[Stock2]] -> 18331.94 | K50: =IF(Product_Dim[[#This Row],[Stock2]]<100,"Low Stock",IF(Product_Dim[[#This Row],[Stock2]]<300,"Medium Stock","High Stock")) -> Medium Stock
A51: PROD49 | B51: Men's Roll-On Perfume | C51: Beauty | D51: Fragrance | E51: Sullivan and Sons | F51: 43.29 | G51: 267 | H51: =IF(ISBLANK(Product_Dim[[#This Row],[Cost]]),MEDIAN(Product_Dim[Cost]),Product_Dim[[#This Row],[Cost]]) -> 43.29 | I51: =IF(ISBLANK(Product_Dim[[#This Row],[Stock]]),MEDIAN(Product_Dim[Stock]),Product_Dim[[#This Row],[Stock]]) -> 267 | J51: =Product_Dim[[#This Row],[Cost2]]*Product_Dim[[#This Row],[Stock2]] -> 11558.43 | K51: =IF(Product_Dim[[#This Row],[Stock2]]<100,"Low Stock",IF(Product_Dim[[#This Row],[Stock2]]<300,"Medium Stock","High Stock")) -> Medium Stock
A52: PROD50 | B52: Boxing Hand Wraps | C52: Sports | D52: Fitness | E52: Smith-King | F52: 190.29 | G52: 260 | H52: =IF(ISBLANK(Product_Dim[[#This Row],[Cost]]),MEDIAN(Product_Dim[Cost]),Product_Dim[[#This Row],[Cost]]) -> 190.29 | I52: =IF(ISBLANK(Product_Dim[[#This Row],[Stock]]),MEDIAN(Product_Dim[Stock]),Product_Dim[[#This Row],[Stock]]) -> 260 | J52: =Product_Dim[[#This Row],[Cost2]]*Product_Dim[[#This Row],[Stock2]] -> 49475.4 | K52: =IF(Product_Dim[[#This Row],[Stock2]]<100,"Low Stock",IF(Product_Dim[[#This Row],[Stock2]]<300,"Medium Stock","High Stock")) -> Medium Stock
A53: PROD51 | B53: HDMI Cable – 2m | C53: Electronics | D53: Accessories | E53: Bautista, Green and Hale | F53: 88.49 | G53: 246 | H53: =IF(ISBLANK(Product_Dim[[#This Row],[Cost]]),MEDIAN(Product_Dim[Cost]),Product_Dim[[#This Row],[Cost]]) -> 88.49 | I53: =IF(ISBLANK(Product_Dim[[#This Row],[Stock]]),MEDIAN(Product_Dim[Stock]),Product_Dim[[#This Row],[Stock]]) -> 246 | J53: =Product_Dim[[#This Row],[Cost2]]*Product_Dim[[#This Row],[Stock2]] -> 21768.54 | K53: =IF(Product_Dim[[#This Row],[Stock2]]<100,"Low Stock",IF(Product_Dim[[#This Row],[Stock2]]<300,"Medium Stock","High Stock")) -> Medium Stock
A54: PROD52 | B54: Rugby Ball | C54: Sports | D54: Team Sports | E54: Harris Inc | F54: 212.26 | G54: 82 | H54: =IF(ISBLANK(Product_Dim[[#This Row],[Cost]]),MEDIAN(Product_Dim[Cost]),Product_Dim[[#This Row],[Cost]]) -> 212.26 | I54: =IF(ISBLANK(Product_Dim[[#This Row],[Stock]]),MEDIAN(Product_Dim[Stock]),Product_Dim[[#This Row],[Stock]]) -> 82 | J54: =Product_Dim[[#This Row],[Cost2]]*Product_Dim[[#This Row],[Stock2]] -> 17405.32 | K54: =IF(Product_Dim[[#This Row],[Stock2]]<100,"Low Stock",IF(Product_Dim[[#This Row],[Stock2]]<300,"Medium Stock","High Stock")) -> Low Stock
A55: PROD53 | B55: Men's Track Pants | C55: Clothing | D55: Bottoms | E55: Hamilton, Woods and Walker | F55: 386.56 | G55: 125 | H55: =IF(ISBLANK(Product_Dim[[#This Row],[Cost]]),MEDIAN(Product_Dim[Cost]),Product_Dim[[#This Row],[Cost]]) -> 386.56 | I55: =IF(ISBLANK(Product_Dim[[#This Row],[Stock]]),MEDIAN(Product_Dim[Stock]),Product_Dim[[#This Row],[Stock]]) -> 125 | J55: =Product_Dim[[#This Row],[Cost2]]*Product_Dim[[#This Row],[Stock2]] -> 48320 | K55: =IF(Product_Dim[[#This Row],[Stock2]]<100,"Low Stock",IF(Product_Dim[[#This Row],[Stock2]]<300,"Medium Stock","High Stock")) -> Medium Stock
A56: PROD54 | B56: Sports Stopwatch Pro | C56: Sports | D56: Accessories | E56: Thompson-French | F56: 434.84 | G56: 185 | H56: =IF(ISBLANK(Product_Dim[[#This Row],[Cost]]),MEDIAN(Product_Dim[Cost]),Product_Dim[[#This Row],[Cost]]) -> 434.84 | I56: =IF(ISBLANK(Product_Dim[[#This Row],[Stock]]),MEDIAN(Product_Dim[Stock]),Product_Dim[[#This Row],[Stock]]) -> 185 | J56: =Product_Dim[[#This Row],[Cost2]]*Product_Dim[[#This Row],[Stock2]] -> 80445.4 | K56: =IF(Product_Dim[[#This Row],[Stock2]]<100,"Low Stock",IF(Product_Dim[[#This Row],[Stock2]]<300,"Medium Stock","High Stock")) -> Medium Stock
A57: PROD55 | B57: Ceramic Plant Pot | C57: Home | D57: Decor | E57: Hatfield, Baird and Torres | F57: 81.75 | H57: =IF(ISBLANK(Product_Dim[[#This Row],[Cost]]),MEDIAN(Product_Dim[Cost]),Product_Dim[[#This Row],[Cost]]) -> 81.75 | I57: =IF(ISBLANK(Product_Dim[[#This Row],[Stock]]),MEDIAN(Product_Dim[Stock]),Product_Dim[[#This Row],[Stock]]) -> 276 | J57: =Product_Dim[[#This Row],[Cost2]]*Product_Dim[[#This Row],[Stock2]] -> 22563 | K57: =IF(Product_Dim[[#This Row],[Stock2]]<100,"Low Stock",IF(Product_Dim[[#This Row],[Stock2]]<300,"Medium Stock","High Stock")) -> Medium Stock
A58: PROD56 | B58: Premium Blanket Throw | C58: Home | D58: Decor | E58: Hernandez, Kennedy and Porter | F58: 461.47 | G58: 190 | H58: =IF(ISBLANK(Product_Dim[[#This Row],[Cost]]),MEDIAN(Product_Dim[Cost]),Product_Dim[[#This Row],[Cost]]) -> 461.47 | I58: =IF(ISBLANK(Product_Dim[[#This Row],[Stock]]),MEDIAN(Product_Dim[Stock]),Product_Dim[[#This Row],[Stock]]) -> 190 | J58: =Product_Dim[[#This Row],[Cost2]]*Product_Dim[[#This Row],[Stock2]] -> 87679.3 | K58: =IF(Product_Dim[[#This Row],[Stock2]]<100,"Low Stock",IF(Product_Dim[[#This Row],[Stock2]]<300,"Medium Stock","High Stock")) -> Medium Stock
A59: PROD57 | B59: Foam Roller | C59: Sports | D59: Fitness | E59: Atkinson, Camacho and Oliver | F59: 30.62 | G59: 138 | H59: =IF(ISBLANK(Product_Dim[[#This Row],[Cost]]),MEDIAN(Product_Dim[Cost]),Product_Dim[[#This Row],[Cost]]) -> 30.62 | I59: =IF(ISBLANK(Product_Dim[[#This Row],[Stock]]),MEDIAN(Product_Dim[Stock]),Product_Dim[[#This Row],[Stock]]) -> 138 | J59: =Product_Dim[[#This Row],[Cost2]]*Product_Dim[[#This Row],[Stock2]] -> 4225.56 | K59: =IF(Product_Dim[[#This Row],[Stock2]]<100,"Low Stock",IF(Product_Dim[[#This Row],[Stock2]]<300,"Medium Stock","High Stock")) -> Medium Stock
A60: PROD58 | B60: Womens Cotton Scarf | C60: Clothing | D60: Accessories | E60: Shepherd-Gould | F60: 113.83 | G60: 485 | H60: =IF(ISBLANK(Product_Dim[[#This Row],[Cost]]),MEDIAN(Product_Dim[Cost]),Product_Dim[[#This Row],[Cost]]) -> 113.83 | I60: =IF(ISBLANK(Product_Dim[[#This Row],[Stock]]),MEDIAN(Product_Dim[Stock]),Product_Dim[[#This Row],[Stock]]) -> 485 | J60: =Product_Dim[[#This Row],[Cost2]]*Product_Dim[[#This Row],[Stock2]] -> 55207.55 | K60: =IF(Product_Dim[[#This Row],[Stock2]]<100,"Low Stock",IF(Product_Dim[[#This Row],[Stock2]]<300,"Medium Stock","High Stock")) -> High Stock
A61: PROD59 | B61: Men's Hair Styling Gel | C61: Beauty | D61: Haircare | E61: Cline-Mccarthy | F61: 17.31 | G61: 399 | H61: =IF(ISBLANK(Product_Dim[[#This Row],[Cost]]),MEDIAN(Product_Dim[Cost]),Product_Dim[[#This Row],[Cost]]) -> 17.31 | I61: =IF(ISBLANK(Product_Dim[[#This Row],[Stock]]),MEDIAN(Product_Dim[Stock]),Product_Dim[[#This Row],[Stock]]) -> 399 | J61: =Product_Dim[[#This Row],[Cost2]]*Product_Dim[[#This Row],[Stock2]] -> 6906.69 | K61: =IF(Product_Dim[[#This Row],[Stock2]]<100,"Low Stock",IF(Product_Dim[[#This Row],[Stock2]]<300,"Medium Stock","High Stock")) -> High Stock
A62: PROD60 | B62: Luxury Perfume Spray | C62: Beauty | D62: Fragrance | E62: Gibson, Green and Lopez | F62: 482.75 | G62: 444 | H62: =IF(ISBLANK(Product_Dim[[#This Row],[Cost]]),MEDIAN(Product_Dim[Cost]),Product_Dim[[#This Row],[Cost]]) -> 482.75 | I62: =IF(ISBLANK(Product_Dim[[#This Row],[Stock]]),MEDIAN(Product_Dim[Stock]),Product_Dim[[#This Row],[Stock]]) -> 444 | J62: =Product_Dim[[#This Row],[Cost2]]*Product_Dim[[#This Row],[Stock2]] -> 214341 | K62: =IF(Product_Dim[[#This Row],[Stock2]]<100,"Low Stock",IF(Product_Dim[[#This Row],[Stock2]]<300,"Medium Stock","High Stock")) -> High Stock
A63: PROD61 | B63: Tennis Ball 3-Pack | C63: Sports | D63: Equipment | E63: Lopez LLC | F63: 103.45 | G63: 465 | H63: =IF(ISBLANK(Product_Dim[[#This Row],[Cost]]),MEDIAN(Product_Dim[Cost]),Product_Dim[[#This Row],[Cost]]) -> 103.45 | I63: =IF(ISBLANK(Product_Dim[[#This Row],[Stock]]),MEDIAN(Product_Dim[Stock]),Product_Dim[[#This Row],[Stock]]) -> 465 | J63: =Product_Dim[[#This Row],[Cost2]]*Product_Dim[[#This Row],[Stock2]] -> 48104.25 | K63: =IF(Product_Dim[[#This Row],[Stock2]]<100,"Low Stock",IF(Product_Dim[[#This Row],[Stock2]]<300,"Medium Stock","High Stock")) -> High Stock
A64: PROD62 | B64: Laptop Cooling Pad | C64: Electronics | D64: Computer | E64: Murray, Gould and Ware | F64: 86.42 | G64: 222 | H64: =IF(ISBLANK(Product_Dim[[#This Row],[Cost]]),MEDIAN(Product_Dim[Cost]),Product_Dim[[#This Row],[Cost]]) -> 86.42 | I64: =IF(ISBLANK(Product_Dim[[#This Row],[Stock]]),MEDIAN(Product_Dim[Stock]),Product_Dim[[#This Row],[Stock]]) -> 222 | J64: =Product_Dim[[#This Row],[Cost2]]*Product_Dim[[#This Row],[Stock2]] -> 19185.24 | K64: =IF(Product_Dim[[#This Row],[Stock2]]<100,"Low Stock",IF(Product_Dim[[#This Row],[Stock2]]<300,"Medium Stock","High Stock")) -> Medium Stock
A65: PROD63 | B65: Organic Sunscreen Lotion | C65: Beauty | D65: Skincare | E65: Anderson-Riley | F65: 266.86 | G65: 458 | H65: =IF(ISBLANK(Product_Dim[[#This Row],[Cost]]),MEDIAN(Product_Dim[Cost]),Product_Dim[[#This Row],[Cost]]) -> 266.86 | I65: =IF(ISBLANK(Product_Dim[[#This Row],[Stock]]),MEDIAN(Product_Dim[Stock]),Product_Dim[[#This Row],[Stock]]) -> 458 | J65: =Product_Dim[[#This Row],[Cost2]]*Product_Dim[[#This Row],[Stock2]] -> 122221.88 | K65: =IF(Product_Dim[[#This Row],[Stock2]]<100,"Low Stock",IF(Product_Dim[[#This Row],[Stock2]]<300,"Medium Stock","High Stock")) -> High Stock
A66: PROD64 | B66: Matte Lipstick Set | C66: Beauty | D66: Makeup | E66: Zhang Inc | F66: 299.11 | G66: 118 | H66: =IF(ISBLANK(Product_Dim[[#This Row],[Cost]]),MEDIAN(Product_Dim[Cost]),Product_Dim[[#This Row],[Cost]]) -> 299.11 | I66: =IF(ISBLANK(Product_Dim[[#This Row],[Stock]]),MEDIAN(Product_Dim[Stock]),Product_Dim[[#This Row],[Stock]]) -> 118 | J66: =Product_Dim[[#This Row],[Cost2]]*Product_Dim[[#This Row],[Stock2]] -> 35294.98 | K66: =IF(Product_Dim[[#This Row],[Stock2]]<100,"Low Stock",IF(Product_Dim[[#This Row],[Stock2]]<300,"Medium Stock","High Stock")) -> Medium Stock
A67: PROD65 | B67: Adjustable Dumbbells 20kg | C67: Sports | D67: Fitness | E67: Montgomery, Benton and Miller | F67: 240.63 | G67: 423 | H67: =IF(ISBLANK(Product_Dim[[#This Row],[Cost]]),MEDIAN(Product_Dim[Cost]),Product_Dim[[#This Row],[Cost]]) -> 240.63 | I67: =IF(ISBLANK(Product_Dim[[#This Row],[Stock]]),MEDIAN(Product_Dim[Stock]),Product_Dim[[#This Row],[Stock]]) -> 423 | J67: =Product_Dim[[#This Row],[Cost2]]*Product_Dim[[#This Row],[Stock2]] -> 101786.49 | K67: =IF(Product_Dim[[#This Row],[Stock2]]<100,"Low Stock",IF(Product_Dim[[#This Row],[Stock2]]<300,"Medium Stock","High Stock")) -> High Stock
A68: PROD66 | B68: Women's Hair Dryer Brush | C68: Beauty | D68: Haircare | E68: Torres, Spencer and Potter | F68: 340.39 | G68: 177 | H68: =IF(ISBLANK(Product_Dim[[#This Row],[Cost]]),MEDIAN(Product_Dim[Cost]),Product_Dim[[#This Row],[Cost]]) -> 340.39 | I68: =IF(ISBLANK(Product_Dim[[#This Row],[Stock]]),MEDIAN(Product_Dim[Stock]),Product_Dim[[#This Row],[Stock]]) -> 177 | J68: =Product_Dim[[#This Row],[Cost2]]*Product_Dim[[#This Row],[Stock2]] -> 60249.03 | K68: =IF(Product_Dim[[#This Row],[Stock2]]<100,"Low Stock",IF(Product_Dim[[#This Row],[Stock2]]<300,"Medium Stock","High Stock")) -> Medium Stock
A69: PROD67 | B69: Smart LED Light Strip | C69: Electronics | D69: Accessories | E69: Flores-Davis | F69: 349.17 | G69: 476 | H69: =IF(ISBLANK(Product_Dim[[#This Row],[Cost]]),MEDIAN(Product_Dim[Cost]),Product_Dim[[#This Row],[Cost]]) -> 349.17 | I69: =IF(ISBLANK(Product_Dim[[#This Row],[Stock]]),MEDIAN(Product_Dim[Stock]),Product_Dim[[#This Row],[Stock]]) -> 476 | J69: =Product_Dim[[#This Row],[Cost2]]*Product_Dim[[#This Row],[Stock2]] -> 166204.92 | K69: =IF(Product_Dim[[#This Row],[Stock2]]<100,"Low Stock",IF(Product_Dim[[#This Row],[Stock2]]<300,"Medium Stock","High Stock")) -> High Stock
... A84: PROD82 | B84: Fitness Resistance Bands | C84: Sports | D84: Fitness | E84: Reese-Watson | F84: 152.92 | G84: 281 | H84: =IF(ISBLANK(Product_Dim[[#This Row],[Cost]]),MEDIAN(Product_Dim[Cost]),Product_Dim[[#This Row],[Cost]]) -> 152.92 | I84: =IF(ISBLANK(Product_Dim[[#This Row],[Stock]]),MEDIAN(Product_Dim[Stock]),Product_Dim[[#This Row],[Stock]]) -> 281 | J84: =Product_Dim[[#This Row],[Cost2]]*Product_Dim[[#This Row],[Stock2]] -> 42970.52 | K84: =IF(Product_Dim[[#This Row],[Stock2]]<100,"Low Stock",IF(Product_Dim[[#This Row],[Stock2]]<300,"Medium Stock","High Stock")) -> Medium Stock
A85: PROD83 | B85: Hydrating Face Cleanser | C85: Beauty | D85: Skincare | E85: Butler Group | G85: 159 | H85: =IF(ISBLANK(Product_Dim[[#This Row],[Cost]]),MEDIAN(Product_Dim[Cost]),Product_Dim[[#This Row],[Cost]]) -> 242.965 | I85: =IF(ISBLANK(Product_Dim[[#This Row],[Stock]]),MEDIAN(Product_Dim[Stock]),Product_Dim[[#This Row],[Stock]]) -> 159 | J85: =Product_Dim[[#This Row],[Cost2]]*Product_Dim[[#This Row],[Stock2]] -> 38631.435 | K85: =IF(Product_Dim[[#This Row],[Stock2]]<100,"Low Stock",IF(Product_Dim[[#This Row],[Stock2]]<300,"Medium Stock","High Stock")) -> Medium Stock
A86: PROD84 | B86: Wooden Bookshelf | C86: Home | D86: Furniture | E86: Collins-Stephenson | F86: 388.46 | G86: 208 | H86: =IF(ISBLANK(Product_Dim[[#This Row],[Cost]]),MEDIAN(Product_Dim[Cost]),Product_Dim[[#This Row],[Cost]]) -> 388.46 | I86: =IF(ISBLANK(Product_Dim[[#This Row],[Stock]]),MEDIAN(Product_Dim[Stock]),Product_Dim[[#This Row],[Stock]]) -> 208 | J86: =Product_Dim[[#This Row],[Cost2]]*Product_Dim[[#This Row],[Stock2]] -> 80799.68 | K86: =IF(Product_Dim[[#This Row],[Stock2]]<100,"Low Stock",IF(Product_Dim[[#This Row],[Stock2]]<300,"Medium Stock","High Stock")) -> Medium Stock
A87: PROD85 | B87: Women's Beanie Hat | C87: Clothing | D87: Accessories | E87: Richardson-Carrillo | F87: 119.57 | G87: 210 | H87: =IF(ISBLANK(Product_Dim[[#This Row],[Cost]]),MEDIAN(Product_Dim[Cost]),Product_Dim[[#This Row],[Cost]]) -> 119.57 | I87: =IF(ISBLANK(Product_Dim[[#This Row],[Stock]]),MEDIAN(Product_Dim[Stock]),Product_Dim[[#This Row],[Stock]]) -> 210 | J87: =Product_Dim[[#This Row],[Cost2]]*Product_Dim[[#This Row],[Stock2]] -> 25109.7 | K87: =IF(Product_Dim[[#This Row],[Stock2]]<100,"Low Stock",IF(Product_Dim[[#This Row],[Stock2]]<300,"Medium Stock","High Stock")) -> Medium Stock
A88: PROD86 | B88: Kitchen Cutting Board | C88: Home | D88: Kitchen | E88: Taylor, Dodson and Johnston | F88: 176.07 | G88: 82 | H88: =IF(ISBLANK(Product_Dim[[#This Row],[Cost]]),MEDIAN(Product_Dim[Cost]),Product_Dim[[#This Row],[Cost]]) -> 176.07 | I88: =IF(ISBLANK(Product_Dim[[#This Row],[Stock]]),MEDIAN(Product_Dim[Stock]),Product_Dim[[#This Row],[Stock]]) -> 82 | J88: =Product_Dim[[#This Row],[Cost2]]*Product_Dim[[#This Row],[Stock2]] -> 14437.74 | K88: =IF(Product_Dim[[#This Row],[Stock2]]<100,"Low Stock",IF(Product_Dim[[#This Row],[Stock2]]<300,"Medium Stock","High Stock")) -> Low Stock
A89: PROD87 | B89: LED Bedside Lamp | C89: Home | D89: Lighting | E89: Aguilar, Horton and Lewis | F89: 371.38 | G89: 220 | H89: =IF(ISBLANK(Product_Dim[[#This Row],[Cost]]),MEDIAN(Product_Dim[Cost]),Product_Dim[[#This Row],[Cost]]) -> 371.38 | I89: =IF(ISBLANK(Product_Dim[[#This Row],[Stock]]),MEDIAN(Product_Dim[Stock]),Product_Dim[[#This Row],[Stock]]) -> 220 | J89: =Product_Dim[[#This Row],[Cost2]]*Product_Dim[[#This Row],[Stock2]] -> 81703.6 | K89: =IF(Product_Dim[[#This Row],[Stock2]]<100,"Low Stock",IF(Product_Dim[[#This Row],[Stock2]]<300,"Medium Stock","High Stock")) -> Medium Stock
A90: PROD88 | B90: Sports Wrist Sweatbands | C90: Sports | D90: Accessories | E90: Olsen-Daniels | F90: 131.24 | G90: 232 | H90: =IF(ISBLANK(Product_Dim[[#This Row],[Cost]]),MEDIAN(Product_Dim[Cost]),Product_Dim[[#This Row],[Cost]]) -> 131.24 | I90: =IF(ISBLANK(Product_Dim[[#This Row],[Stock]]),MEDIAN(Product_Dim[Stock]),Product_Dim[[#This Row],[Stock]]) -> 232 | J90: =Product_Dim[[#This Row],[Cost2]]*Product_Dim[[#This Row],[Stock2]] -> 30447.68 | K90: =IF(Product_Dim[[#This Row],[Stock2]]<100,"Low Stock",IF(Product_Dim[[#This Row],[Stock2]]<300,"Medium Stock","High Stock")) -> Medium Stock
A91: PROD89 | B91: Face Foundation Kit | C91: Beauty | D91: Makeup | E91: Taylor-Elliott | F91: 183.04 | G91: 457 | H91: =IF(ISBLANK(Product_Dim[[#This Row],[Cost]]),MEDIAN(Product_Dim[Cost]),Product_Dim[[#This Row],[Cost]]) -> 183.04 | I91: =IF(ISBLANK(Product_Dim[[#This Row],[Stock]]),MEDIAN(Product_Dim[Stock]),Product_Dim[[#This Row],[Stock]]) -> 457 | J91: =Product_Dim[[#This Row],[Cost2]]*Product_Dim[[#This Row],[Stock2]] -> 83649.28 | K91: =IF(Product_Dim[[#This Row],[Stock2]]<100,"Low Stock",IF(Product_Dim[[#This Row],[Stock2]]<300,"Medium Stock","High Stock")) -> High Stock
A92: PROD90 | B92: Gaming Mouse Pad XL | C92: Electronics | D92: Accessories | E92: Sharp, Taylor and Rodriguez | F92: 340.14 | G92: 361 | H92: =IF(ISBLANK(Product_Dim[[#This Row],[Cost]]),MEDIAN(Product_Dim[Cost]),Product_Dim[[#This Row],[Cost]]) -> 340.14 | I92: =IF(ISBLANK(Product_Dim[[#This Row],[Stock]]),MEDIAN(Product_Dim[Stock]),Product_Dim[[#This Row],[Stock]]) -> 361 | J92: =Product_Dim[[#This Row],[Cost2]]*Product_Dim[[#This Row],[Stock2]] -> 122790.54 | K92: =IF(Product_Dim[[#This Row],[Stock2]]<100,"Low Stock",IF(Product_Dim[[#This Row],[Stock2]]<300,"Medium Stock","High Stock")) -> High Stock
A93: PROD91 | B93: Women's High Heels | C93: Clothing | D93: Footwear | E93: Smith-Charles | F93: 438.25 | G93: 496 | H93: =IF(ISBLANK(Product_Dim[[#This Row],[Cost]]),MEDIAN(Product_Dim[Cost]),Product_Dim[[#This Row],[Cost]]) -> 438.25 | I93: =IF(ISBLANK(Product_Dim[[#This Row],[Stock]]),MEDIAN(Product_Dim[Stock]),Product_Dim[[#This Row],[Stock]]) -> 496 | J93: =Product_Dim[[#This Row],[Cost2]]*Product_Dim[[#This Row],[Stock2]] -> 217372 | K93: =IF(Product_Dim[[#This Row],[Stock2]]<100,"Low Stock",IF(Product_Dim[[#This Row],[Stock2]]<300,"Medium Stock","High Stock")) -> High Stock
A94: PROD92 | B94: Microwave Oven | C94: Home | D94: Appliances | E94: Green, Powell and Palmer | F94: 447.43 | G94: 191 | H94: =IF(ISBLANK(Product_Dim[[#This Row],[Cost]]),MEDIAN(Product_Dim[Cost]),Product_Dim[[#This Row],[Cost]]) -> 447.43 | I94: =IF(ISBLANK(Product_Dim[[#This Row],[Stock]]),MEDIAN(Product_Dim[Stock]),Product_Dim[[#This Row],[Stock]]) -> 191 | J94: =Product_Dim[[#This Row],[Cost2]]*Product_Dim[[#This Row],[Stock2]] -> 85459.13 | K94: =IF(Product_Dim[[#This Row],[Stock2]]<100,"Low Stock",IF(Product_Dim[[#This Row],[Stock2]]<300,"Medium Stock","High Stock")) -> Medium Stock
A95: PROD93 | B95: USB-C Laptop Charger | C95: Electronics | D95: Computer | E95: Martin LLC | F95: 377.52 | G95: 485 | H95: =IF(ISBLANK(Product_Dim[[#This Row],[Cost]]),MEDIAN(Product_Dim[Cost]),Product_Dim[[#This Row],[Cost]]) -> 377.52 | I95: =IF(ISBLANK(Product_Dim[[#This Row],[Stock]]),MEDIAN(Product_Dim[Stock]),Product_Dim[[#This Row],[Stock]]) -> 485 | J95: =Product_Dim[[#This Row],[Cost2]]*Product_Dim[[#This Row],[Stock2]] -> 183097.2 | K95: =IF(Product_Dim[[#This Row],[Stock2]]<100,"Low Stock",IF(Product_Dim[[#This Row],[Stock2]]<300,"Medium Stock","High Stock")) -> High Stock
A96: PROD94 | B96: Vitamin E Body Lotion | C96: Beauty | D96: Skincare | E96: Hoffman-Williams | F96: 358.47 | G96: 213 | H96: =IF(ISBLANK(Product_Dim[[#This Row],[Cost]]),MEDIAN(Product_Dim[Cost]),Product_Dim[[#This Row],[Cost]]) -> 358.47 | I96: =IF(ISBLANK(Product_Dim[[#This Row],[Stock]]),MEDIAN(Product_Dim[Stock]),Product_Dim[[#This Row],[Stock]]) -> 213 | J96: =Product_Dim[[#This Row],[Cost2]]*Product_Dim[[#This Row],[Stock2]] -> 76354.11 | K96: =IF(Product_Dim[[#This Row],[Stock2]]<100,"Low Stock",IF(Product_Dim[[#This Row],[Stock2]]<300,"Medium Stock","High Stock")) -> Medium Stock
A97: PROD95 | B97: Sports Stopwatch Basic | C97: Sports | D97: Accessories | E97: Wilson Group | F97: 60.65 | G97: 75 | H97: =IF(ISBLANK(Product_Dim[[#This Row],[Cost]]),MEDIAN(Product_Dim[Cost]),Product_Dim[[#This Row],[Cost]]) -> 60.65 | I97: =IF(ISBLANK(Product_Dim[[#This Row],[Stock]]),MEDIAN(Product_Dim[Stock]),Product_Dim[[#This Row],[Stock]]) -> 75 | J97: =Product_Dim[[#This Row],[Cost2]]*Product_Dim[[#This Row],[Stock2]] -> 4548.75 | K97: =IF(Product_Dim[[#This Row],[Stock2]]<100,"Low Stock",IF(Product_Dim[[#This Row],[Stock2]]<300,"Medium Stock","High Stock")) -> Low Stock
... A101: PROD99 | B101: Stainless Steel Cookware Set | C101: Home | D101: Kitchen | E101: Campbell Ltd | F101: 201.41 | G101: 146 | H101: =IF(ISBLANK(Product_Dim[[#This Row],[Cost]]),MEDIAN(Product_Dim[Cost]),Product_Dim[[#This Row],[Cost]]) -> 201.41 | I101: =IF(ISBLANK(Product_Dim[[#This Row],[Stock]]),MEDIAN(Product_Dim[Stock]),Product_Dim[[#This Row],[Stock]]) -> 146 | J101: =Product_Dim[[#This Row],[Cost2]]*Product_Dim[[#This Row],[Stock2]] -> 29405.86 | K101: =IF(Product_Dim[[#This Row],[Stock2]]<100,"Low Stock",IF(Product_Dim[[#This Row],[Stock2]]<300,"Medium Stock","High Stock")) -> Medium Stock

Sheet Summary 
A1: Summary | B1: Formula
A2: Total Sales | B2: =SUM(Sales_Fact[Total_Amount5]) -> 2173211.7
A3: Total Quantity Sold | B3: =SUM(Sales_Fact[Quantity2]) -> 4958
A4: Total Transactions | B4: =COUNTA(Sales_Fact[Sales_ID]) -> 2000
A5: Average Order Value | B5: =AVERAGE(Sales_Fact[Total_Amount]) -> 1087.629
A6: Minimum Order Value | B6: =MIN(Sales_Fact[Total_Amount]) -> 18.459
A7: Maximum Order Value | B7: =MAX(Sales_Fact[Total_Amount]) -> 3908.2428
A8: Total Sales by Payment Type - Creditcard | B8: =SUMIF(Sales_Fact[Payment_Type],"Credit Card",Sales_Fact[Total_Amount]) -> 713754.93
A9: Total Sales by Payment Type - Paypal | B9: =SUMIF(Sales_Fact[Payment_Type],"PayPal",Sales_Fact[Total_Amount]) -> 755627.24
A10: Total Sales by Payment Type - COD | B10: =SUMIF(Sales_Fact[Payment_Type],"COD",Sales_Fact[Total_Amount]) -> 701525.29
A11: No of Transactions by Payment Type -Creditcard | B11: =COUNTIF(Sales_Fact[Payment_Type],"Credit Card") -> 645
A12: No of Transactions by Payment Type-Paypal | B12: =COUNTIF(Sales_Fact[Payment_Type],"PayPal") -> 695
A13: No of Transactions by Payment Type- COD | B13: =COUNTIF(Sales_Fact[Payment_Type],"COD") -> 660
A14: Average Order Value by Payment Type - Creditcard | B14: =AVERAGEIF(Sales_Fact[Payment_Type],"Credit Card",Sales_Fact[Total_Amount]) -> 1108.3151
A15: Average Order Value by Payment Type - paypal | B15: =AVERAGEIF(Sales_Fact[Payment_Type],"PayPal",Sales_Fact[Total_Amount]) -> 1088.8001
A16: Average Order Value by Payment Type - COD | B16: =AVERAGEIF(Sales_Fact[Payment_Type],"COD",Sales_Fact[Total_Amount]) -> 1066.1479

Sheet LOOKUP DATA
A1: Sales_ID | B1: Order_Date | C1: Customer_ID | D1: Product_ID | E1: Store_ID | F1: Quantity | G1: Unit_Price | H1: Discount | I1: Payment_Type | J1: Total_Amount | K1: Gross Amount | L1: Discounted Amount | M1: Order Value Category | N1: Product_Name | O1: Category | P1: Cost | Q1: Loyalty_Level | R1: Gender | S1: Age Group | T1: Region | U1: Store_Type | V1: Total Cost | W1: Profit
A2: SALE388 | B2: 45780 | C2: CUST1000 | D2: PROD63 | E2: STORE16 | F2: =IF(ISBLANK(Sales_Fact[[#This Row],[Quantity]]),MEDIAN(Sales_Fact[Quantity]),Sales_Fact[[#This Row],[Quantity]]) -> 1 | G2: =IF(ISBLANK(Sales_Fact[[#This Row],[Unit_Price]]),MEDIAN(Sales_Fact[Unit_Price]),Sales_Fact[[#This Row],[Unit_Price]]) -> 218.04 | H2: =IF(ISBLANK(Sales_Fact[[#This Row],[Discount]]),MEDIAN(Sales_Fact[Discount]),Sales_Fact[[#This Row],[Discount]]) -> 0.09 | I2: PayPal | J2: =Sales_Fact[[#This Row],[Quantity2]]*Sales_Fact[[#This Row],[Unit_Price3]]*(1-Sales_Fact[[#This Row],[Discount4]]) -> 198.4164 | K2: =Sales_Fact[[#This Row],[Quantity2]]*Sales_Fact[[#This Row],[Unit_Price3]] -> 218.04 | L2: =Sales_Fact[[#This Row],[Gross Amount]]*Sales_Fact[[#This Row],[Discount4]] -> 19.6236 | M2: =IF(Sales_Fact[[#This Row],[Total_Amount5]]>1000,"High Value","Standard") -> Standard | N2: =_xlfn.XLOOKUP(D2,Product_Dim!$A$2:$A$101,Product_Dim!$B$2:$B$101,"Not Found") -> Organic Sunscreen Lotion | O2: =_xlfn.XLOOKUP(D2,Product_Dim!$A$2:$A$101,Product_Dim!$C$2:$C$101) -> Beauty | P2: =_xlfn.XLOOKUP(D2,Product_Dim!$A$2:$A$101,Product_Dim!$H$2:$H$101) -> 266.86 | Q2: =_xlfn.XLOOKUP(C2,'Customer_Dim'!$A$2:$A$501,'Customer_Dim'!$I$2:$I$501) -> Platinum | R2: =_xlfn.XLOOKUP(C2,'Customer_Dim'!$A$2:$A$501,'Customer_Dim'!$D$2:$D$501) -> Male | S2: =_xlfn.XLOOKUP(C2,'Customer_Dim'!$A$2:$A$501,'Customer_Dim'!$L$2:$L$501) -> Senior | T2: =_xlfn.XLOOKUP(E2,Store_Dim!$A$2:$A$21,Store_Dim!$C$2:$C$21) -> West | U2: =_xlfn.XLOOKUP(E2,Store_Dim!$A$2:$A$21,Store_Dim!$E$2:$E$21) -> Flagship | V2: =Table8[[#This Row],[Cost]]*Table8[[#This Row],[Quantity]] -> 266.86 | W2: =Table8[[#This Row],[Total_Amount]]-Table8[[#This Row],[Total Cost]] -> -68.4436
A3: SALE902 | B3: 45812 | C3: CUST1000 | D3: PROD56 | E3: STORE19 | F3: =IF(ISBLANK(Sales_Fact[[#This Row],[Quantity]]),MEDIAN(Sales_Fact[Quantity]),Sales_Fact[[#This Row],[Quantity]]) -> 3 | G3: =IF(ISBLANK(Sales_Fact[[#This Row],[Unit_Price]]),MEDIAN(Sales_Fact[Unit_Price]),Sales_Fact[[#This Row],[Unit_Price]]) -> 104.47 | H3: =IF(ISBLANK(Sales_Fact[[#This Row],[Discount]]),MEDIAN(Sales_Fact[Discount]),Sales_Fact[[#This Row],[Discount]]) -> 0.27 | I3: Credit Card | J3: =Sales_Fact[[#This Row],[Quantity2]]*Sales_Fact[[#This Row],[Unit_Price3]]*(1-Sales_Fact[[#This Row],[Discount4]]) -> 228.7893 | K3: =Sales_Fact[[#This Row],[Quantity2]]*Sales_Fact[[#This Row],[Unit_Price3]] -> 313.41 | L3: =Sales_Fact[[#This Row],[Gross Amount]]*Sales_Fact[[#This Row],[Discount4]] -> 84.6207 | M3: =IF(Sales_Fact[[#This Row],[Total_Amount5]]>1000,"High Value","Standard") -> Standard | N3: =_xlfn.XLOOKUP(D3,Product_Dim!$A$2:$A$101,Product_Dim!$B$2:$B$101,"Not Found") -> Premium Blanket Throw | O3: =_xlfn.XLOOKUP(D3,Product_Dim!$A$2:$A$101,Product_Dim!$C$2:$C$101) -> Home | P3: =_xlfn.XLOOKUP(D3,Product_Dim!$A$2:$A$101,Product_Dim!$H$2:$H$101) -> 461.47 | Q3: =_xlfn.XLOOKUP(C3,'Customer_Dim'!$A$2:$A$501,'Customer_Dim'!$I$2:$I$501) -> Platinum | R3: =_xlfn.XLOOKUP(C3,'Customer_Dim'!$A$2:$A$501,'Customer_Dim'!$D$2:$D$501) -> Male | S3: =_xlfn.XLOOKUP(C3,'Customer_Dim'!$A$2:$A$501,'Customer_Dim'!$L$2:$L$501) -> Senior | T3: =_xlfn.XLOOKUP(E3,Store_Dim!$A$2:$A$21,Store_Dim!$C$2:$C$21) -> East | U3: =_xlfn.XLOOKUP(E3,Store_Dim!$A$2:$A$21,Store_Dim!$E$2:$E$21) -> Online | V3: =Table8[[#This Row],[Cost]]*Table8[[#This Row],[Quantity]] -> 1384.41 | W3: =Table8[[#This Row],[Total_Amount]]-Table8[[#This Row],[Total Cost]] -> -1155.6207
A4: SALE992 | B4: 45575 | C4: CUST1000 | D4: PROD40 | E4: STORE7 | F4: =IF(ISBLANK(Sales_Fact[[#This Row],[Quantity]]),MEDIAN(Sales_Fact[Quantity]),Sales_Fact[[#This Row],[Quantity]]) -> 4 | G4: =IF(ISBLANK(Sales_Fact[[#This Row],[Unit_Price]]),MEDIAN(Sales_Fact[Unit_Price]),Sales_Fact[[#This Row],[Unit_Price]]) -> 914.05 | H4: =IF(ISBLANK(Sales_Fact[[#This Row],[Discount]]),MEDIAN(Sales_Fact[Discount]),Sales_Fact[[#This Row],[Discount]]) -> 0.25 | I4: Credit Card | J4: =Sales_Fact[[#This Row],[Quantity2]]*Sales_Fact[[#This Row],[Unit_Price3]]*(1-Sales_Fact[[#This Row],[Discount4]]) -> 2742.15 | K4: =Sales_Fact[[#This Row],[Quantity2]]*Sales_Fact[[#This Row],[Unit_Price3]] -> 3656.2 | L4: =Sales_Fact[[#This Row],[Gross Amount]]*Sales_Fact[[#This Row],[Discount4]] -> 914.05 | M4: =IF(Sales_Fact[[#This Row],[Total_Amount5]]>1000,"High Value","Standard") -> High Value | N4: =_xlfn.XLOOKUP(D4,Product_Dim!$A$2:$A$101,Product_Dim!$B$2:$B$101,"Not Found") -> Noise-Canceling Headphones | O4: =_xlfn.XLOOKUP(D4,Product_Dim!$A$2:$A$101,Product_Dim!$C$2:$C$101) -> Electronics | P4: =_xlfn.XLOOKUP(D4,Product_Dim!$A$2:$A$101,Product_Dim!$H$2:$H$101) -> 38.52 | Q4: =_xlfn.XLOOKUP(C4,'Customer_Dim'!$A$2:$A$501,'Customer_Dim'!$I$2:$I$501) -> Platinum | R4: =_xlfn.XLOOKUP(C4,'Customer_Dim'!$A$2:$A$501,'Customer_Dim'!$D$2:$D$501) -> Male | S4: =_xlfn.XLOOKUP(C4,'Customer_Dim'!$A$2:$A$501,'Customer_Dim'!$L$2:$L$501) -> Senior | T4: =_xlfn.XLOOKUP(E4,Store_Dim!$A$2:$A$21,Store_Dim!$C$2:$C$21) -> South | U4: =_xlfn.XLOOKUP(E4,Store_Dim!$A$2:$A$21,Store_Dim!$E$2:$E$21) -> Online | V4: =Table8[[#This Row],[Cost]]*Table8[[#This Row],[Quantity]] -> 154.08 | W4: =Table8[[#This Row],[Total_Amount]]-Table8[[#This Row],[Total Cost]] -> 2588.07
A5: SALE693 | B5: 45520 | C5: CUST1001 | D5: PROD48 | E5: STORE2 | F5: =IF(ISBLANK(Sales_Fact[[#This Row],[Quantity]]),MEDIAN(Sales_Fact[Quantity]),Sales_Fact[[#This Row],[Quantity]]) -> 1 | G5: =IF(ISBLANK(Sales_Fact[[#This Row],[Unit_Price]]),MEDIAN(Sales_Fact[Unit_Price]),Sales_Fact[[#This Row],[Unit_Price]]) -> 921.51 | H5: =IF(ISBLANK(Sales_Fact[[#This Row],[Discount]]),MEDIAN(Sales_Fact[Discount]),Sales_Fact[[#This Row],[Discount]]) -> 0.16 | I5: PayPal | J5: =Sales_Fact[[#This Row],[Quantity2]]*Sales_Fact[[#This Row],[Unit_Price3]]*(1-Sales_Fact[[#This Row],[Discount4]]) -> 774.0684 | K5: =Sales_Fact[[#This Row],[Quantity2]]*Sales_Fact[[#This Row],[Unit_Price3]] -> 921.51 | L5: =Sales_Fact[[#This Row],[Gross Amount]]*Sales_Fact[[#This Row],[Discount4]] -> 147.4416 | M5: =IF(Sales_Fact[[#This Row],[Total_Amount5]]>1000,"High Value","Standard") -> Standard | N5: =_xlfn.XLOOKUP(D5,Product_Dim!$A$2:$A$101,Product_Dim!$B$2:$B$101,"Not Found") -> Car Dashboard Phone Holder | O5: =_xlfn.XLOOKUP(D5,Product_Dim!$A$2:$A$101,Product_Dim!$C$2:$C$101) -> Electronics | P5: =_xlfn.XLOOKUP(D5,Product_Dim!$A$2:$A$101,Product_Dim!$H$2:$H$101) -> 177.98 | Q5: =_xlfn.XLOOKUP(C5,'Customer_Dim'!$A$2:$A$501,'Customer_Dim'!$I$2:$I$501) -> Platinum | R5: =_xlfn.XLOOKUP(C5,'Customer_Dim'!$A$2:$A$501,'Customer_Dim'!$D$2:$D$501) -> Female | S5: =_xlfn.XLOOKUP(C5,'Customer_Dim'!$A$2:$A$501,'Customer_Dim'!$L$2:$L$501) -> Young | T5: =_xlfn.XLOOKUP(E5,Store_Dim!$A$2:$A$21,Store_Dim!$C$2:$C$21) -> South | U5: =_xlfn.XLOOKUP(E5,Store_Dim!$A$2:$A$21,Store_Dim!$E$2:$E$21) -> Outlet | V5: =Table8[[#This Row],[Cost]]*Table8[[#This Row],[Quantity]] -> 177.98 | W5: =Table8[[#This Row],[Total_Amount]]-Table8[[#This Row],[Total Cost]] -> 596.0884
A6: SALE762 | B6: 45360 | C6: CUST1001 | D6: PROD67 | E6: STORE0 | F6: =IF(ISBLANK(Sales_Fact[[#This Row],[Quantity]]),MEDIAN(Sales_Fact[Quantity]),Sales_Fact[[#This Row],[Quantity]]) -> 3 | G6: =IF(ISBLANK(Sales_Fact[[#This Row],[Unit_Price]]),MEDIAN(Sales_Fact[Unit_Price]),Sales_Fact[[#This Row],[Unit_Price]]) -> 745.3 | H6: =IF(ISBLANK(Sales_Fact[[#This Row],[Discount]]),MEDIAN(Sales_Fact[Discount]),Sales_Fact[[#This Row],[Discount]]) -> 0.18 | I6: COD | J6: =Sales_Fact[[#This Row],[Quantity2]]*Sales_Fact[[#This Row],[Unit_Price3]]*(1-Sales_Fact[[#This Row],[Discount4]]) -> 1833.438 | K6: =Sales_Fact[[#This Row],[Quantity2]]*Sales_Fact[[#This Row],[Unit_Price3]] -> 2235.9 | L6: =Sales_Fact[[#This Row],[Gross Amount]]*Sales_Fact[[#This Row],[Discount4]] -> 402.462 | M6: =IF(Sales_Fact[[#This Row],[Total_Amount5]]>1000,"High Value","Standard") -> High Value | N6: =_xlfn.XLOOKUP(D6,Product_Dim!$A$2:$A$101,Product_Dim!$B$2:$B$101,"Not Found") -> Smart LED Light Strip | O6: =_xlfn.XLOOKUP(D6,Product_Dim!$A$2:$A$101,Product_Dim!$C$2:$C$101) -> Electronics | P6: =_xlfn.XLOOKUP(D6,Product_Dim!$A$2:$A$101,Product_Dim!$H$2:$H$101) -> 349.17 | Q6: =_xlfn.XLOOKUP(C6,'Customer_Dim'!$A$2:$A$501,'Customer_Dim'!$I$2:$I$501) -> Platinum | R6: =_xlfn.XLOOKUP(C6,'Customer_Dim'!$A$2:$A$501,'Customer_Dim'!$D$2:$D$501) -> Female | S6: =_xlfn.XLOOKUP(C6,'Customer_Dim'!$A$2:$A$501,'Customer_Dim'!$L$2:$L$501) -> Young | T6: =_xlfn.XLOOKUP(E6,Store_Dim!$A$2:$A$21,Store_Dim!$C$2:$C$21) -> East | U6: =_xlfn.XLOOKUP(E6,Store_Dim!$A$2:$A$21,Store_Dim!$E$2:$E$21) -> Flagship | V6: =Table8[[#This Row],[Cost]]*Table8[[#This Row],[Quantity]] -> 1047.51 | W6: =Table8[[#This Row],[Total_Amount]]-Table8[[#This Row],[Total Cost]] -> 785.928
A7: SALE430 | B7: 45445 | C7: CUST1001 | D7: PROD51 | E7: STORE14 | F7: =IF(ISBLANK(Sales_Fact[[#This Row],[Quantity]]),MEDIAN(Sales_Fact[Quantity]),Sales_Fact[[#This Row],[Quantity]]) -> 3 | G7: =IF(ISBLANK(Sales_Fact[[#This Row],[Unit_Price]]),MEDIAN(Sales_Fact[Unit_Price]),Sales_Fact[[#This Row],[Unit_Price]]) -> 147.01 | H7: =IF(ISBLANK(Sales_Fact[[#This Row],[Discount]]),MEDIAN(Sales_Fact[Discount]),Sales_Fact[[#This Row],[Discount]]) -> 0.19 | I7: COD | J7: =Sales_Fact[[#This Row],[Quantity2]]*Sales_Fact[[#This Row],[Unit_Price3]]*(1-Sales_Fact[[#This Row],[Discount4]]) -> 357.2343 | K7: =Sales_Fact[[#This Row],[Quantity2]]*Sales_Fact[[#This Row],[Unit_Price3]] -> 441.03 | L7: =Sales_Fact[[#This Row],[Gross Amount]]*Sales_Fact[[#This Row],[Discount4]] -> 83.7957 | M7: =IF(Sales_Fact[[#This Row],[Total_Amount5]]>1000,"High Value","Standard") -> Standard | N7: =_xlfn.XLOOKUP(D7,Product_Dim!$A$2:$A$101,Product_Dim!$B$2:$B$101,"Not Found") -> HDMI Cable – 2m | O7: =_xlfn.XLOOKUP(D7,Product_Dim!$A$2:$A$101,Product_Dim!$C$2:$C$101) -> Electronics | P7: =_xlfn.XLOOKUP(D7,Product_Dim!$A$2:$A$101,Product_Dim!$H$2:$H$101) -> 88.49 | Q7: =_xlfn.XLOOKUP(C7,'Customer_Dim'!$A$2:$A$501,'Customer_Dim'!$I$2:$I$501) -> Platinum | R7: =_xlfn.XLOOKUP(C7,'Customer_Dim'!$A$2:$A$501,'Customer_Dim'!$D$2:$D$501) -> Female | S7: =_xlfn.XLOOKUP(C7,'Customer_Dim'!$A$2:$A$501,'Customer_Dim'!$L$2:$L$501) -> Young | T7: =_xlfn.XLOOKUP(E7,Store_Dim!$A$2:$A$21,Store_Dim!$C$2:$C$21) -> South | U7: =_xlfn.XLOOKUP(E7,Store_Dim!$A$2:$A$21,Store_Dim!$E$2:$E$21) -> Outlet | V7: =Table8[[#This Row],[Cost]]*Table8[[#This Row],[Quantity]] -> 265.47 | W7: =Table8[[#This Row],[Total_Amount]]-Table8[[#This Row],[Total Cost]] -> 91.7643
A8: SALE741 | B8: 45372 | C8: CUST1002 | D8: PROD86 | E8: STORE9 | F8: =IF(ISBLANK(Sales_Fact[[#This Row],[Quantity]]),MEDIAN(Sales_Fact[Quantity]),Sales_Fact[[#This Row],[Quantity]]) -> 2 | G8: =IF(ISBLANK(Sales_Fact[[#This Row],[Unit_Price]]),MEDIAN(Sales_Fact[Unit_Price]),Sales_Fact[[#This Row],[Unit_Price]]) -> 785.31 | H8: =IF(ISBLANK(Sales_Fact[[#This Row],[Discount]]),MEDIAN(Sales_Fact[Discount]),Sales_Fact[[#This Row],[Discount]]) -> 0.15 | I8: Credit Card | J8: =Sales_Fact[[#This Row],[Quantity2]]*Sales_Fact[[#This Row],[Unit_Price3]]*(1-Sales_Fact[[#This Row],[Discount4]]) -> 1335.027 | K8: =Sales_Fact[[#This Row],[Quantity2]]*Sales_Fact[[#This Row],[Unit_Price3]] -> 1570.62 | L8: =Sales_Fact[[#This Row],[Gross Amount]]*Sales_Fact[[#This Row],[Discount4]] -> 235.593 | M8: =IF(Sales_Fact[[#This Row],[Total_Amount5]]>1000,"High Value","Standard") -> High Value | N8: =_xlfn.XLOOKUP(D8,Product_Dim!$A$2:$A$101,Product_Dim!$B$2:$B$101,"Not Found") -> Kitchen Cutting Board | O8: =_xlfn.XLOOKUP(D8,Product_Dim!$A$2:$A$101,Product_Dim!$C$2:$C$101) -> Home | P8: =_xlfn.XLOOKUP(D8,Product_Dim!$A$2:$A$101,Product_Dim!$H$2:$H$101) -> 176.07 | Q8: =_xlfn.XLOOKUP(C8,'Customer_Dim'!$A$2:$A$501,'Customer_Dim'!$I$2:$I$501) -> Platinum | R8: =_xlfn.XLOOKUP(C8,'Customer_Dim'!$A$2:$A$501,'Customer_Dim'!$D$2:$D$501) -> Female | S8: =_xlfn.XLOOKUP(C8,'Customer_Dim'!$A$2:$A$501,'Customer_Dim'!$L$2:$L$501) -> Young | T8: =_xlfn.XLOOKUP(E8,Store_Dim!$A$2:$A$21,Store_Dim!$C$2:$C$21) -> South | U8: =_xlfn.XLOOKUP(E8,Store_Dim!$A$2:$A$21,Store_Dim!$E$2:$E$21) -> Flagship | V8: =Table8[[#This Row],[Cost]]*Table8[[#This Row],[Quantity]] -> 352.14 | W8: =Table8[[#This Row],[Total_Amount]]-Table8[[#This Row],[Total Cost]] -> 982.887
A9: SALE1040 | B9: 45861 | C9: CUST1002 | D9: PROD75 | E9: STORE17 | F9: =IF(ISBLANK(Sales_Fact[[#This Row],[Quantity]]),MEDIAN(Sales_Fact[Quantity]),Sales_Fact[[#This Row],[Quantity]]) -> 4 | G9: =IF(ISBLANK(Sales_Fact[[#This Row],[Unit_Price]]),MEDIAN(Sales_Fact[Unit_Price]),Sales_Fact[[#This Row],[Unit_Price]]) -> 342.39 | H9: =IF(ISBLANK(Sales_Fact[[#This Row],[Discount]]),MEDIAN(Sales_Fact[Discount]),Sales_Fact[[#This Row],[Discount]]) -> 0.23 | I9: PayPal | J9: =Sales_Fact[[#This Row],[Quantity2]]*Sales_Fact[[#This Row],[Unit_Price3]]*(1-Sales_Fact[[#This Row],[Discount4]]) -> 1054.5612 | K9: =Sales_Fact[[#This Row],[Quantity2]]*Sales_Fact[[#This Row],[Unit_Price3]] -> 1369.56 | L9: =Sales_Fact[[#This Row],[Gross Amount]]*Sales_Fact[[#This Row],[Discount4]] -> 314.9988 | M9: =IF(Sales_Fact[[#This Row],[Total_Amount5]]>1000,"High Value","Standard") -> High Value | N9: =_xlfn.XLOOKUP(D9,Product_Dim!$A$2:$A$101,Product_Dim!$B$2:$B$101,"Not Found") -> Women's Ankle Boots | O9: =_xlfn.XLOOKUP(D9,Product_Dim!$A$2:$A$101,Product_Dim!$C$2:$C$101) -> Clothing | P9: =_xlfn.XLOOKUP(D9,Product_Dim!$A$2:$A$101,Product_Dim!$H$2:$H$101) -> 158.14 | Q9: =_xlfn.XLOOKUP(C9,'Customer_Dim'!$A$2:$A$501,'Customer_Dim'!$I$2:$I$501) -> Platinum | R9: =_xlfn.XLOOKUP(C9,'Customer_Dim'!$A$2:$A$501,'Customer_Dim'!$D$2:$D$501) -> Female | S9: =_xlfn.XLOOKUP(C9,'Customer_Dim'!$A$2:$A$501,'Customer_Dim'!$L$2:$L$501) -> Young | T9: =_xlfn.XLOOKUP(E9,Store_Dim!$A$2:$A$21,Store_Dim!$C$2:$C$21) -> North | U9: =_xlfn.XLOOKUP(E9,Store_Dim!$A$2:$A$21,Store_Dim!$E$2:$E$21) -> Flagship | V9: =Table8[[#This Row],[Cost]]*Table8[[#This Row],[Quantity]] -> 632.56 | W9: =Table8[[#This Row],[Total_Amount]]-Table8[[#This Row],[Total Cost]] -> 422.0012
A10: SALE105 | B10: 45214 | C10: CUST1002 | D10: PROD79 | E10: STORE17 | F10: =IF(ISBLANK(Sales_Fact[[#This Row],[Quantity]]),MEDIAN(Sales_Fact[Quantity]),Sales_Fact[[#This Row],[Quantity]]) -> 2 | G10: =IF(ISBLANK(Sales_Fact[[#This Row],[Unit_Price]]),MEDIAN(Sales_Fact[Unit_Price]),Sales_Fact[[#This Row],[Unit_Price]]) -> 448.25 | H10: =IF(ISBLANK(Sales_Fact[[#This Row],[Discount]]),MEDIAN(Sales_Fact[Discount]),Sales_Fact[[#This Row],[Discount]]) -> 0.07 | I10: Credit Card | J10: =Sales_Fact[[#This Row],[Quantity2]]*Sales_Fact[[#This Row],[Unit_Price3]]*(1-Sales_Fact[[#This Row],[Discount4]]) -> 833.745 | K10: =Sales_Fact[[#This Row],[Quantity2]]*Sales_Fact[[#This Row],[Unit_Price3]] -> 896.5 | L10: =Sales_Fact[[#This Row],[Gross Amount]]*Sales_Fact[[#This Row],[Discount4]] -> 62.755 | M10: =IF(Sales_Fact[[#This Row],[Total_Amount5]]>1000,"High Value","Standard") -> Standard | N10: =_xlfn.XLOOKUP(D10,Product_Dim!$A$2:$A$101,Product_Dim!$B$2:$B$101,"Not Found") -> Decorative Lamp Shade | O10: =_xlfn.XLOOKUP(D10,Product_Dim!$A$2:$A$101,Product_Dim!$C$2:$C$101) -> Home | P10: =_xlfn.XLOOKUP(D10,Product_Dim!$A$2:$A$101,Product_Dim!$H$2:$H$101) -> 228.53 | Q10: =_xlfn.XLOOKUP(C10,'Customer_Dim'!$A$2:$A$501,'Customer_Dim'!$I$2:$I$501) -> Platinum | R10: =_xlfn.XLOOKUP(C10,'Customer_Dim'!$A$2:$A$501,'Customer_Dim'!$D$2:$D$501) -> Female | S10: =_xlfn.XLOOKUP(C10,'Customer_Dim'!$A$2:$A$501,'Customer_Dim'!$L$2:$L$501) -> Young | T10: =_xlfn.XLOOKUP(E10,Store_Dim!$A$2:$A$21,Store_Dim!$C$2:$C$21) -> North | U10: =_xlfn.XLOOKUP(E10,Store_Dim!$A$2:$A$21,Store_Dim!$E$2:$E$21) -> Flagship | V10: =Table8[[#This Row],[Cost]]*Table8[[#This Row],[Quantity]] -> 457.06 | W10: =Table8[[#This Row],[Total_Amount]]-Table8[[#This Row],[Total Cost]] -> 376.685
A11: SALE689 | B11: 45876 | C11: CUST1002 | D11: PROD54 | E11: STORE5 | F11: =IF(ISBLANK(Sales_Fact[[#This Row],[Quantity]]),MEDIAN(Sales_Fact[Quantity]),Sales_Fact[[#This Row],[Quantity]]) -> 2 | G11: =IF(ISBLANK(Sales_Fact[[#This Row],[Unit_Price]]),MEDIAN(Sales_Fact[Unit_Price]),Sales_Fact[[#This Row],[Unit_Price]]) -> 873.17 | H11: =IF(ISBLANK(Sales_Fact[[#This Row],[Discount]]),MEDIAN(Sales_Fact[Discount]),Sales_Fact[[#This Row],[Discount]]) -> 0.23 | I11: COD | J11: =Sales_Fact[[#This Row],[Quantity2]]*Sales_Fact[[#This Row],[Unit_Price3]]*(1-Sales_Fact[[#This Row],[Discount4]]) -> 1344.6818 | K11: =Sales_Fact[[#This Row],[Quantity2]]*Sales_Fact[[#This Row],[Unit_Price3]] -> 1746.34 | L11: =Sales_Fact[[#This Row],[Gross Amount]]*Sales_Fact[[#This Row],[Discount4]] -> 401.6582 | M11: =IF(Sales_Fact[[#This Row],[Total_Amount5]]>1000,"High Value","Standard") -> High Value | N11: =_xlfn.XLOOKUP(D11,Product_Dim!$A$2:$A$101,Product_Dim!$B$2:$B$101,"Not Found") -> Sports Stopwatch Pro | O11: =_xlfn.XLOOKUP(D11,Product_Dim!$A$2:$A$101,Product_Dim!$C$2:$C$101) -> Sports | P11: =_xlfn.XLOOKUP(D11,Product_Dim!$A$2:$A$101,Product_Dim!$H$2:$H$101) -> 434.84 | Q11: =_xlfn.XLOOKUP(C11,'Customer_Dim'!$A$2:$A$501,'Customer_Dim'!$I$2:$I$501) -> Platinum | R11: =_xlfn.XLOOKUP(C11,'Customer_Dim'!$A$2:$A$501,'Customer_Dim'!$D$2:$D$501) -> Female | S11: =_xlfn.XLOOKUP(C11,'Customer_Dim'!$A$2:$A$501,'Customer_Dim'!$L$2:$L$501) -> Young | T11: =_xlfn.XLOOKUP(E11,Store_Dim!$A$2:$A$21,Store_Dim!$C$2:$C$21) -> North | U11: =_xlfn.XLOOKUP(E11,Store_Dim!$A$2:$A$21,Store_Dim!$E$2:$E$21) -> Outlet | V11: =Table8[[#This Row],[Cost]]*Table8[[#This Row],[Quantity]] -> 869.68 | W11: =Table8[[#This Row],[Total_Amount]]-Table8[[#This Row],[Total Cost]] -> 475.0018
A12: SALE1831 | B12: 45704 | C12: CUST1003 | D12: PROD74 | E12: STORE15 | F12: =IF(ISBLANK(Sales_Fact[[#This Row],[Quantity]]),MEDIAN(Sales_Fact[Quantity]),Sales_Fact[[#This Row],[Quantity]]) -> 1 | G12: =IF(ISBLANK(Sales_Fact[[#This Row],[Unit_Price]]),MEDIAN(Sales_Fact[Unit_Price]),Sales_Fact[[#This Row],[Unit_Price]]) -> 278.63 | H12: =IF(ISBLANK(Sales_Fact[[#This Row],[Discount]]),MEDIAN(Sales_Fact[Discount]),Sales_Fact[[#This Row],[Discount]]) -> 0.07 | I12: Credit Card | J12: =Sales_Fact[[#This Row],[Quantity2]]*Sales_Fact[[#This Row],[Unit_Price3]]*(1-Sales_Fact[[#This Row],[Discount4]]) -> 259.1259 | K12: =Sales_Fact[[#This Row],[Quantity2]]*Sales_Fact[[#This Row],[Unit_Price3]] -> 278.63 | L12: =Sales_Fact[[#This Row],[Gross Amount]]*Sales_Fact[[#This Row],[Discount4]] -> 19.5041 | M12: =IF(Sales_Fact[[#This Row],[Total_Amount5]]>1000,"High Value","Standard") -> Standard | N12: =_xlfn.XLOOKUP(D12,Product_Dim!$A$2:$A$101,Product_Dim!$B$2:$B$101,"Not Found") -> Bluetooth Car Audio System | O12: =_xlfn.XLOOKUP(D12,Product_Dim!$A$2:$A$101,Product_Dim!$C$2:$C$101) -> Electronics | P12: =_xlfn.XLOOKUP(D12,Product_Dim!$A$2:$A$101,Product_Dim!$H$2:$H$101) -> 403.71 | Q12: =_xlfn.XLOOKUP(C12,'Customer_Dim'!$A$2:$A$501,'Customer_Dim'!$I$2:$I$501) -> Bronze | R12: =_xlfn.XLOOKUP(C12,'Customer_Dim'!$A$2:$A$501,'Customer_Dim'!$D$2:$D$501) -> Female | S12: =_xlfn.XLOOKUP(C12,'Customer_Dim'!$A$2:$A$501,'Customer_Dim'!$L$2:$L$501) -> Senior | T12: =_xlfn.XLOOKUP(E12,Store_Dim!$A$2:$A$21,Store_Dim!$C$2:$C$21) -> North | U12: =_xlfn.XLOOKUP(E12,Store_Dim!$A$2:$A$21,Store_Dim!$E$2:$E$21) -> Flagship | V12: =Table8[[#This Row],[Cost]]*Table8[[#This Row],[Quantity]] -> 403.71 | W12: =Table8[[#This Row],[Total_Amount]]-Table8[[#This Row],[Total Cost]] -> -144.5841
A13: SALE1305 | B13: 45616 | C13: CUST1003 | D13: PROD60 | E13: STORE18 | F13: =IF(ISBLANK(Sales_Fact[[#This Row],[Quantity]]),MEDIAN(Sales_Fact[Quantity]),Sales_Fact[[#This Row],[Quantity]]) -> 4 | G13: =IF(ISBLANK(Sales_Fact[[#This Row],[Unit_Price]]),MEDIAN(Sales_Fact[Unit_Price]),Sales_Fact[[#This Row],[Unit_Price]]) -> 286.92 | H13: =IF(ISBLANK(Sales_Fact[[#This Row],[Discount]]),MEDIAN(Sales_Fact[Discount]),Sales_Fact[[#This Row],[Discount]]) -> 0.17 | I13: Credit Card | J13: =Sales_Fact[[#This Row],[Quantity2]]*Sales_Fact[[#This Row],[Unit_Price3]]*(1-Sales_Fact[[#This Row],[Discount4]]) -> 952.5744 | K13: =Sales_Fact[[#This Row],[Quantity2]]*Sales_Fact[[#This Row],[Unit_Price3]] -> 1147.68 | L13: =Sales_Fact[[#This Row],[Gross Amount]]*Sales_Fact[[#This Row],[Discount4]] -> 195.1056 | M13: =IF(Sales_Fact[[#This Row],[Total_Amount5]]>1000,"High Value","Standard") -> Standard | N13: =_xlfn.XLOOKUP(D13,Product_Dim!$A$2:$A$101,Product_Dim!$B$2:$B$101,"Not Found") -> Luxury Perfume Spray | O13: =_xlfn.XLOOKUP(D13,Product_Dim!$A$2:$A$101,Product_Dim!$C$2:$C$101) -> Beauty | P13: =_xlfn.XLOOKUP(D13,Product_Dim!$A$2:$A$101,Product_Dim!$H$2:$H$101) -> 482.75 | Q13: =_xlfn.XLOOKUP(C13,'Customer_Dim'!$A$2:$A$501,'Customer_Dim'!$I$2:$I$501) -> Bronze | R13: =_xlfn.XLOOKUP(C13,'Customer_Dim'!$A$2:$A$501,'Customer_Dim'!$D$2:$D$501) -> Female | S13: =_xlfn.XLOOKUP(C13,'Customer_Dim'!$A$2:$A$501,'Customer_Dim'!$L$2:$L$501) -> Senior | T13: =_xlfn.XLOOKUP(E13,Store_Dim!$A$2:$A$21,Store_Dim!$C$2:$C$21) -> East | U13: =_xlfn.XLOOKUP(E13,Store_Dim!$A$2:$A$21,Store_Dim!$E$2:$E$21) -> Flagship | V13: =Table8[[#This Row],[Cost]]*Table8[[#This Row],[Quantity]] -> 1931 | W13: =Table8[[#This Row],[Total_Amount]]-Table8[[#This Row],[Total Cost]] -> -978.4256
... A2001: SALE1051 | B2001: 45720 | C2001: CUST1499 | D2001: PROD44 | E2001: STORE8 | F2001: =IF(ISBLANK(Sales_Fact[[#This Row],[Quantity]]),MEDIAN(Sales_Fact[Quantity]),Sales_Fact[[#This Row],[Quantity]]) -> 3 | G2001: =IF(ISBLANK(Sales_Fact[[#This Row],[Unit_Price]]),MEDIAN(Sales_Fact[Unit_Price]),Sales_Fact[[#This Row],[Unit_Price]]) -> 68.45 | H2001: =IF(ISBLANK(Sales_Fact[[#This Row],[Discount]]),MEDIAN(Sales_Fact[Discount]),Sales_Fact[[#This Row],[Discount]]) -> 0.17 | I2001: PayPal | J2001: =Sales_Fact[[#This Row],[Quantity2]]*Sales_Fact[[#This Row],[Unit_Price3]]*(1-Sales_Fact[[#This Row],[Discount4]]) -> 170.4405 | K2001: =Sales_Fact[[#This Row],[Quantity2]]*Sales_Fact[[#This Row],[Unit_Price3]] -> 205.35 | L2001: =Sales_Fact[[#This Row],[Gross Amount]]*Sales_Fact[[#This Row],[Discount4]] -> 34.9095 | M2001: =IF(Sales_Fact[[#This Row],[Total_Amount5]]>1000,"High Value","Standard") -> Standard | N2001: =_xlfn.XLOOKUP(D2001,Product_Dim!$A$2:$A$101,Product_Dim!$B$2:$B$101,"Not Found") -> Adjustable Jump Rope | O2001: =_xlfn.XLOOKUP(D2001,Product_Dim!$A$2:$A$101,Product_Dim!$C$2:$C$101) -> Sports | P2001: =_xlfn.XLOOKUP(D2001,Product_Dim!$A$2:$A$101,Product_Dim!$H$2:$H$101) -> 167.12 | Q2001: =_xlfn.XLOOKUP(C2001,'Customer_Dim'!$A$2:$A$501,'Customer_Dim'!$I$2:$I$501) -> Platinum | R2001: =_xlfn.XLOOKUP(C2001,'Customer_Dim'!$A$2:$A$501,'Customer_Dim'!$D$2:$D$501) -> Female | S2001: =_xlfn.XLOOKUP(C2001,'Customer_Dim'!$A$2:$A$501,'Customer_Dim'!$L$2:$L$501) -> Young | T2001: =_xlfn.XLOOKUP(E2001,Store_Dim!$A$2:$A$21,Store_Dim!$C$2:$C$21) -> West | U2001: =_xlfn.XLOOKUP(E2001,Store_Dim!$A$2:$A$21,Store_Dim!$E$2:$E$21) -> Online | V2001: =Table8[[#This Row],[Cost]]*Table8[[#This Row],[Quantity]] -> 501.36 | W2001: =Table8[[#This Row],[Total_Amount]]-Table8[[#This Row],[Total Cost]] -> -330.9195

Sheet Descriptive statistics
B2: Quantity | C2: Unit Price | D2: Discount | E2: Total Amount | F2: Cost | G2: Total Cost | H2: Profit
A3: Mean | B3: 2.4786539 | C3: 513.64393 | D3: 0.14802109 | E3: 1085.7353 | F3: 256.17946 | G3: 632.20916 | H3: 453.52612
A4: Standard Error | B4: 0.024911691 | C4: 6.3125221 | D4: 0.0019619202 | E4: 18.327425 | F4: 2.9609196 | G4: 10.209799 | H4: 17.641667
A5: Median | B5: 2 | C5: 522.72 | D5: 0.14 | E5: 867.5 | F5: 242.965 | G5: 493.84 | H5: 340.577
A6: Mode | B6: 2 | C6: 522.72 | D6: 0.1 | E6: #N/A | F6: 242.965 | G6: 242.965 | H6: #N/A
A7: Standard Deviation | B7: 1.1115752 | C7: 281.66867 | D7: 0.087542102 | E7: 817.78112 | F7: 132.11808 | G7: 455.56761 | H7: 787.18216
A8: Sample Variance | B8: 1.2355994 | C8: 79337.239 | D8: 0.0076636197 | E8: 668765.95 | F8: 17455.186 | G8: 207541.84 | H8: 619655.75
A9: Kurtosis | B9: -1.3439543 | C9: -1.1868542 | D9: -1.2053334 | E9: 0.072310118 | F9: -1.0213968 | G9: 0.036358647 | H9: 0.67777947
A10: Skewness | B10: 0.030710826 | C10: -0.035890439 | D10: 0.065112128 | E10: 0.8858847 | F10: 0.029600982 | G10: 0.88266785 | H10: 0.59933563
A11: Range | B11: 3 | C11: 979.8 | D11: 0.3 | E11: 3889.7838 | F11: 478.41 | G11: 1965.57 | H11: 5269.0668
A12: Minimum | B12: 1 | C12: 20.09 | D12: 0 | E12: 18.459 | F12: 17.31 | G12: 17.31 | H12: -1798.4412
A13: Maximum | B13: 4 | C13: 999.89 | D13: 0.3 | E13: 3908.2428 | F13: 495.72 | G13: 1982.88 | H13: 3470.6256
A14: Sum | B14: 4935 | C14: 1022665.1 | D14: 294.71 | E14: 2161698.9 | F14: 510053.3 | G14: 1258728.4 | H14: 902970.51
A15: Count | B15: 1991 | C15: 1991 | D15: 1991 | E15: 1991 | F15: 1991 | G15: 1991 | H15: 1991

Sheet Pivot Table
A2: Total Sales by Product Category | D2: Total Sales by Region | G2: Payment Type Summary
A3: Category | B3: Sum of Total_Amount | D3: Region | E3: Sum of Total_Amount | G3: Payment Type | H3: Sum of Total_Amount | I3: Count of Sales_ID
A4: Beauty | B4: 345101.88 | D4: East | E4: 616418.17 | G4: COD | H4: 733615.66 | I4: 660
A5: Clothing | B5: 364453.02 | D5: North | E5: 646856.55 | G5: Credit Card | H5: 694552 | I5: 645
A6: Electronics | B6: 466239.63 | D6: South | E6: 666440.46 | G6: PayPal | H6: 745044.04 | I6: 695
A7: Home | B7: 466358.17 | D7: West | E7: 243496.53 | G7: Grand Total | H7: 2173211.7 | I7: 2000
A8: Sports | B8: 531059.02 | D8: Grand Total | E8: 2173211.7
A9: Grand Total | B9: 2173211.7
A11: Loyalty Level Analysis | E11: Monthly Sales Trend | H11: Profit by Category
A12: Loyalty Level | B12: Sum of Total_Amount | C12: Count of Sales_ID | E12: Order Date | F12: Sum of Total_Amount | H12: Category | I12: Sum of Total_Amount | J12: Sum of Profit
A13: Bronze | B13: 542000.69 | C13: 487 | E13: 2023 | F13: 226171.23 | H13: Beauty | I13: 345101.88 | J13: 157218.2
A14: Gold | B14: 504412.92 | C14: 469 | E14: 2024 | F14: 1110573.5 | H14: Clothing | I14: 364453.02 | J14: 143394.41
A15: Platinum | B15: 650426.36 | C15: 622 | E15: 2025 | F15: 836466.93 | H15: Electronics | I15: 466239.63 | J15: 110065.88
A16: Silver | B16: 476371.75 | C16: 422 | E16: Grand Total | F16: 2173211.7 | H16: Home | I16: 466358.17 | J16: 219817.1
A17: Grand Total | B17: 2173211.7 | C17: 2000 | H17: Sports | I17: 531059.02 | J17: 280207.63
H18: Grand Total | I18: 2173211.7 | J18: 910703.22

Sheet Pivot Charts

Sheet DASHBOARD
A1: E-COMMERCE SALES DASHBOARD
B7: Profit by Category | F7: Total Sales by Region | I7: Loyalty Level Analysis
B8: Category | C8: Sum of Total_Amount | D8: Sum of Profit | F8: Region | G8: Sum of Total_Amount | I8: Loyalty Level | J8: Sum of Total_Amount | K8: Count of Sales_ID | M8: Payment Type Summary | Q8: Monthly Sales Trend
B9: Beauty | C9: 345101.88 | D9: 157218.2 | F9: East | G9: 616418.17 | I9: Bronze | J9: 542000.69 | K9: 487 | M9: Payment Type | N9: Sum of Total_Amount | O9: Count of Sales_ID | Q9: Order Date | R9: Sum of Total_Amount
B10: Clothing | C10: 364453.02 | D10: 143394.41 | F10: North | G10: 646856.55 | I10: Gold | J10: 504412.92 | K10: 469 | M10: COD | N10: 733615.66 | O10: 660 | Q10: 2023 | R10: 226171.23
B11: Electronics | C11: 466239.63 | D11: 110065.88 | F11: South | G11: 666440.46 | I11: Platinum | J11: 650426.36 | K11: 622 | M11: Credit Card | N11: 694552 | O11: 645 | Q11: 2024 | R11: 1110573.5
B12: Home | C12: 466358.17 | D12: 219817.1 | F12: West | G12: 243496.53 | I12: Silver | J12: 476371.75 | K12: 422 | M12: PayPal | N12: 745044.04 | O12: 695 | Q12: 2025 | R12: 836466.93
B13: Sports | C13: 531059.02 | D13: 280207.63 | F13: Grand Total | G13: 2173211.7 | I13: Grand Total | J13: 2173211.7 | K13: 2000 | M13: Grand Total | N13: 2173211.7 | O13: 2000 | Q13: Grand Total | R13: 2173211.7
B14: Grand Total | C14: 2173211.7 | D14: 910703.22
